{"Map":{"ah!1":["矣！"],
"aih˨":["噯","哎"],
"ai˥˥":["哀","餲"],
"ai˥˥io˧˧ue˨˦":["哎喲喂"],
"ai˨˩":["愛","噯"],
"ai˨˩kɔ˨˩":["愛顧"],
"ai˨˩mai˧˧":["曖昧"],
"ai˨˩se˨˩dzi˧˧":["愛細膩"],
"ak˨":["沃","握","齷"],
"am˥˥":["掩","醃","罨","闇"],
"am˥˥pɔ˥˥tse˨˦":["𧌄蜅蠐"],
"am˥˧":["泔"],
"am˧˧":["頷"],
"am˧˧kun˥˧":["頷頸"],
"am˨˦":["涵"],
"am˨˩":["暗"],
"am˨˩kʰi˨˩":["暗去"],
"am˨˩kʰĩ˥˥":["安康"],
"an˥˥":["安"],
"an˥˧":["俺"],
"an˥˧ne˥˥":["按呢"],
"an˥˧tsũã˥˧":["按怎"],
"an˧˧":["限"],
"an˨˦":["絚"],
"an˨˩":["案","按"],
"ap˦":["盒"],
"ap˨":["壓"],
"at˨":["遏","楬"],
"au˥˥":["甌","歐","漚"],
"au˥˧":["拗","嘔","漚"],
"au˧˧":["後","后"],
"au˧˧e˨˦":["後的"],
"au˨˦":["喉"],
"au˨˦kʰuaʔ˨":["喉渴"],
"au˨˩":["漚"],
"au˨˩nau˥˧":["懊惱"],
"au˨˩tu˧˧":["懊嘟"],
"aŋ˥˥":["翁","尪"],
"aŋ˥˥a˥˧":["尪仔","翁仔"],
"aŋ˥˧laŋ˥˧":["聬儱"],
"aŋ˨˦":["紅"],
"aŋ˨˩":["甕","齆"],
"aŋ˨˩a˥˧":["甕仔"],
"aʔ˦":["曷","盒"],
"aʔ˨":["矣","鴨","押","壓","啊"],
"a˥˥":["阿","亞","鴉"],
"a˥˥pʰian˨˩":["鴉片"],
"a˥˥tsa˥˥":["腌臢"],
"a˥˧":["仔","子"],
"a˥˧kʰẽ˥˥kʰo˥˥":["梓科"],
"a˥˧pĩ˥˥":["邊"],
"a˥˧tai˧˧tsi˨˩m˥˥":["仔代誌毋"],
"a˥˧tiŋ˨˩":["仔叮"],
"a˥˧tʰau˨˦":["仔頭","頭"],
"bai˥˥":["屄"],
"bai˥˧":["䆀"],
"bai˨˦":["眉","埋"],
"bak˦":["目","墨","木"],
"bak˦am˨˩":["目暗"],
"bak˦kĩã˨˩":["目鏡"],
"bak˦ni˧˧":["茉莉"],
"bak˦tsʰio˨˩":["目笑"],
"bak˨":["沐"],
"ban˥˥":["屘"],
"ban˥˧":["挽"],
"ban˥˧tʰo˨˦":["饅頭"],
"ban˧˧":["萬","慢","漫","瓣"],
"ban˧˧ban˧˧":["萬萬","慢慢"],
"ban˧˧kʰɔ˥˧":["萬苦"],
"ban˧˧sǹg1":["萬算"],
"ban˧˧tɔ˨˦":["萬途"],
"ban˨˦":["蠻"],
"bat˦":["密"],
"bat˦bat˦":["密密"],
"bat˨":["捌"],
"bat˨dzi˧˧":["捌字"],
"bat˨po˥˧":["捌寶"],
"bau˥˧":["卯"],
"bau˧˧":["貿","㴘"],
"baŋ˥˧":["蠓","魍"],
"baŋ˧˧":["網","夢","望"],
"baŋ˨˦":["茫","忙"],
"baʔ˨":["肉"],
"baʔ˨mue˨˦":["肉糜"],
"ba˧˧":["擸","峇","覓"],
"ba˧˧hioʔ˨":["鴟鴞"],
"ba˨˦":["麻","猫","媌"],
"ba˨˦bui˥˥":["峇微"],
"ba˨˦bu˧˧":["貓霧"],
"ba˨˦dzi˨˦":["貓兒"],
"ba˨˦pi˨˩":["麻痺"],
"beʔ˦":["麥"],
"beʔ˨":["欲"],
"beʔ˨be˥˧":["欲買"],
"beʔ˨tsiaʔ˦":["欲食"],
"beʔ˨uaʔ˦":["欲活"],
"be˥˧":["馬","買","碼"],
"be˥˧au˨˦":["馬喉"],
"be˥˧bin˧˧":["馬面"],
"be˥˧bo˨˦":["買無"],
"be˥˧lo˥˧":["瑪瑙"],
"be˥˧tsʰu˨˩":["買厝"],
"be˥˧tʰau˨˦":["碼頭"],
"be˧˧":["袂","賣"],
"be˧˧an˥˧tsũã˥˧":["袂按怎"],
"be˧˧kau˨˩":["袂到"],
"be˧˧kʰi˥˧":["袂起"],
"be˧˧kʰi˨˩":["袂去"],
"be˧˧kʰun˨˩":["袂睏"],
"be˧˧liap˨":["袂攝"],
"be˧˧sai˥˧":["袂使"],
"be˧˧tioʔ˨":["袂著"],
"be˧˧tsi˥˧":["袂止"],
"be˧˧tʰĩã˥˥":["袂聽"],
"be˧˧tʰĩã˨˩":["袂疼"],
"be˨˦":["迷"],
"bian˥˧":["免","勉","鮸"],
"bian˥˧kioŋ˥˧":["勉強"],
"bian˧˧":["面"],
"bian˨˦":["綿"],
"biat˦":["滅"],
"biau˥˧":["藐"],
"biau˥˧biau˥˧":["渺渺"],
"biau˨˦":["描","苗"],
"bin˥˧":["敏","抿","憫"],
"bin˧˧":["面","蝒"],
"bin˧˧kat˨":["面結"],
"bin˧˧tsʰau˨˩":["面臭"],
"bin˨˦":["民","眠","明"],
"bin˨˦siŋ˥˥":["民生"],
"bio˥˧":["母","秒"],
"bio˧˧":["廟"],
"bio˨˦":["描"],
"bit˦":["密","蜜","沕"],
"bit˦gi˥˧":["蜜語"],
"bit˦tĩ˥˥":["蜜甜"],
"biŋ˥˧":["猛"],
"biŋ˧˧":["命"],
"biŋ˨˦":["明","名","盟","冥","鳴"],
"biʔ˦":["篾"],
"biʔ˨":["覕"],
"bi˥˥bi˥˥":["微微"],
"bi˥˧":["米","美"],
"bi˥˧sut˦":["美術"],
"bi˧˧":["味","未","沬","謎","魅"],
"bi˨˦":["微","咪","眉","唯","眯"],
"bok˨":["木","目","莫","漠","牧","睦","揍"],
"bok˨bok˨":["沐沐"],
"bok˨tse˨˩":["木齊"],
"boŋ˥˥":["摸"],
"boŋ˥˧":["罔","網"],
"boŋ˥˧boŋ˥˧":["莽莽"],
"boŋ˥˧toŋ˥˧":["懵懂"],
"boŋ˧˧":["墓","望","忘","夢"],
"boŋ˧˧sioŋ˥˧":["夢想"],
"boŋ˨˦":["亡","雺","芒","茫","盲","肓"],
"boŋ˨˩":["懵","甍"],
"bo˥˧":["母"],
"bo˥˧nŋ˥˥":["母卵"],
"bo˥˧pʰue˨˦":["母皮"],
"bo˥˧sue˨˩":["母稅"],
"bo˧˧":["磨","帽"],
"bo˨˦":["無"],
"bo˨˦dzit˦":["無日"],
"bo˨˦e˨˦":["無的"],
"bo˨˦hi˨˦":["無魚"],
"bo˨˦ho˥˧":["無好"],
"bo˨˦hue˨˦":["無回"],
"bo˨˦kau˨˦":["無猴"],
"bo˨˦kau˨˩":["無夠"],
"bo˨˦kin˥˧":["無緊"],
"bo˨˦kʰioʔ˨hin˧˧":["無抾恨"],
"bo˨˦kʰi˧˧":["無忌"],
"bo˨˦lat˦":["無力"],
"bo˨˦liu˧˧":["無餾"],
"bo˨˦lun˧˧":["無論"],
"bo˨˦m˥˥tioh!1":["無毋著！"],
"bo˨˦ne˥˥":["無拈"],
"bo˨˦nŋ˥˥":["無兩"],
"bo˨˦po˥˥":["無褒"],
"bo˨˦se˨˩":["無細"],
"bo˨˦siam˥˥":["無纖"],
"bo˨˦sim˥˥":["無心"],
"bo˨˦sueʔ˨":["無說"],
"bo˨˦sun˥˧":["無榫"],
"bo˨˦su˨˩":["無思"],
"bo˨˦tsiaʔ˨":["無跡"],
"bo˨˦tsi˨˩":["無誌"],
"bo˨˦tsun˧˧":["無陣"],
"bo˨˦tsʰui˨˩":["無喙"],
"bo˨˦tsʰu˨˩":["無厝"],
"bo˨˦tã˥˧":["無膽","無打"],
"bo˨˦tã˨˩":["無呾"],
"bo˨˦tʰai˨˦":["無刣"],
"buan˥˧":["滿","晚","輓"],
"buat˦":["末"],
"buaʔ˦":["茉"],
"buaʔ˦buaʔ˦":["末末"],
"buaʔ˨":["抹"],
"bua˨˦":["磨"],
"bueʔ˦":["襪"],
"bue˥˧":["尾","美"],
"bue˥˧mŋ˥˥":["尾門"],
"bue˧˧":["未"],
"bue˧˧tsiaʔ˦pŋ˥˥":["未食飯"],
"bue˨˦":["囮"],
"bui˥˥":["微","蝛"],
"bun˧˧":["問","悶","燜"],
"bun˨˦":["文","紋","門","聞"],
"bun˨˩":["濆","鼢"],
"but˦":["物","𢪱","沒"],
"but˨":["魩"],
"but˨but˨":["粅粅"],
"bu˥˧":["母","舞","武","拇","撫"],
"bu˥˧dziok˨":["侮辱"],
"bu˥˧koŋ˥˥":["拇公"],
"bu˥˧ku˧˧":["母舅"],
"bu˧˧":["務","霧"],
"bu˨˦":["無","誣"],
"bu˨˦dzi˧˧":["無二"],
"bu˨˦tʰian˥˥":["無天"],
"bɔ˥˧":["某","牡"],
"bɔ˥˧kĩã˥˧":["某囝"],
"bɔ˧˧":["幕","募","貿","戊","慕"],
"bɔ˧˧pan˥˥":["戊班"],
"bɔ˨˦":["模","謀"],
"dziam˥˧":["染"],
"dzian˨˦":["然","燃"],
"dziap˦":["廿"],
"dziat˦":["熱"],
"dziat˦a˥˧":["熱仔"],
"dziau˥˧":["爪","擾"],
"dziau˨˦":["饒","皺","鱙"],
"dziau˨˩":["抓","繞"],
"dziaŋ˥˧":["嚷"],
"dziaŋ˧˧":["攘"],
"dziaʔ˨":["跡"],
"dzia˥˥":["遮"],
"dzia˥˧":["惹"],
"dzia˥˧hɔ˥˧":["惹虎"],
"dzim˥˧":["忍"],
"dzim˧˧":["任"],
"dzim˨˦":["壬","撏"],
"dzin˧˧":["認"],
"dzin˨˦":["人","仁"],
"dzin˨˦ke˥˥":["人家"],
"dzin˨˦uan˨˦":["人員"],
"dziok˨":["弱","肉","逐","搙"],
"dzioŋ˧˧":["讓"],
"dzioŋ˨˦":["絨","茸"],
"dzio˧˧":["尿"],
"dzip˦":["入"],
"dzip˦mŋ˥˥":["入門"],
"dzip˦paŋ˨˦":["入房"],
"dzit˦":["日"],
"dzit˦a˥˧":["日仔"],
"dzit˦gueʔ˦":["日月"],
"dziu˨˦":["柔","鰇","揉","榆"],
"dzi˥˧":["子"],
"dzi˧˧":["字","二","餌","膩"],
"dzi˧˧hue˧˧":["字會"],
"dzi˧˧kɔ˨˩":["二顧"],
"dzi˧˧lɔ˧˧":["二路"],
"dzi˧˧tsʰiu˥˧":["二手"],
"dzi˨˦":["兒","而"],
"dzi˨˦tsioŋ˥˥":["而將"],
"dzi˨˩puʔ˨":["吉普"],
"dzuaʔ˦":["熱"],
"dzue˨˦":["挼"],
"dzun˧˧":["潤","韌","閏"],
"dzu˥˧":["愈","乳"],
"dzu˧˧":["喻","裕"],
"dzu˨˦":["如","挐","儒"],
"dzu˨˦tsʰu˥˧":["如此"],
"e!5kiu˥˧kian˨˩kiu˥˧kian!3kin˧˧lai˨˦loŋ˥˧teʔ˨bo˨˦iŋ˨˦sĩãʔ˨":["的！久見久見！近來攏咧無閒啥"],
"eʔ˦":["狹"],
"eʔ˨":["呃","厄","喂","欸"],
"e˥˥":["挨"],
"e˥˥am˨˩":["下暗"],
"e˥˥hŋ˥˥":["下昏"],
"e˥˥tsai˥˧":["下早"],
"e˥˧":["矮"],
"e˥˧kau˥˧":["啞口"],
"e˧˧":["會","下","禍"],
"e˨˦":["的","个","鞋"],
"e˨˩":["裔"],
"gai˧˧":["礙"],
"gai˨˦":["涯"],
"gak˦":["樂","獄","岳"],
"gam˧˧":["儑"],
"gam˧˧a˥˧":["𩸶仔"],
"gam˧˧bin˧˧":["儑面"],
"gam˨˦":["癌"],
"gam˨˦tsioʔ˨":["岩石"],
"gan˥˧":["眼"],
"gan˧˧":["雁","諺"],
"gan˨˦":["顏","寒"],
"gan˨˩":["𫝏"],
"gan˨˩kǹg1":["𫝏鋼"],
"gan˨˩tsui˥˧":["𫝏水"],
"gan˨˩tsĩ˨˦":["𫝏錢"],
"gau˨˦":["𠢕"],
"gaŋ˧˧":["愣"],
"ga˨˦":["牙"],
"geʔ˦tʰo˨˦":["月桃"],
"ge˧˧":["藝"],
"ge˨˦":["牙","芽","㤉","衙"],
"ge˨˦mŋ˥˥":["衙門"],
"ge˨˩":["嚙"],
"giam˥˧ŋe˧˧":["儼硬"],
"giam˧˧":["驗"],
"giam˨˦":["嚴","岩"],
"giam˨˦kun˥˥":["閻君"],
"giam˨˦lo˨˦oŋ˨˦":["閻羅王"],
"giam˨˦oŋ˨˦":["閻王"],
"gian˥˧huat˨":["研發"],
"gian˥˧kiu˨˩":["研究"],
"gian˥˧pʰũã˨˩":["研判"],
"gian˥˧sip˦":["研習"],
"gian˥˧tʰok˨":["研讀"],
"gian˥˧tʰo˥˧":["研討"],
"gian˥˧ĩ˧˧":["研院"],
"gian˧˧gian˧˧":["殗殗"],
"gian˨˦":["言"],
"gian˨˩":["癮"],
"giap˦":["業","挾"],
"giap˨":["鋏"],
"giap˨a˥˧":["鋏仔"],
"giat˦":["孽"],
"giat˨a˥˧":["蠍仔"],
"giau˨˦gi˨˦":["憢疑"],
"giaŋ˥˥":["鈃","婸"],
"giaŋ˨˩":["齴"],
"giaŋ˨˩ge˨˦":["齴牙"],
"giaʔ˦":["額","攑"],
"giaʔ˦dziau˥˧a˥˧":["攑爪仔"],
"giaʔ˦hĩũ˥˥":["攑香"],
"giaʔ˦ki˨˦":["攑旗"],
"giaʔ˦kuan˨˦":["攑懸"],
"giaʔ˦ti˧˧":["攑箸"],
"giaʔ˦tsʰiu˥˧":["攑手"],
"giaʔ˦tʰau˨˦":["攑頭"],
"giaʔ˦tʰau˨˦sã˥˥tsʰioʔ˨":["攑頭三尺"],
"giaʔ˨":["撠"],
"gia˨˦":["夯"],
"gia˨˦kaŋ˥˥":["蜈蚣"],
"gik˦":["逆","玉"],
"gik˦a˥˧":["玉仔"],
"gik˦tʰai˧˧":["虐待"],
"gim˥˧":["錦"],
"gim˥˧a˥˧":["笒仔"],
"gim˥˧tsua˨˦":["錦蛇"],
"gim˧˧":["扲"],
"gim˨˦":["吟","砛"],
"gim˨˦a˥˧":["砛仔"],
"gim˨˦si˥˥":["吟詩"],
"gim˨˩gim˨˩":["錦錦"],
"gim˨˩ku˥˥":["錦痀"],
"gin˥˧a˥˧":["囡仔"],
"gin˧˧":["猌"],
"gin˨˦":["銀","睨"],
"giok˨":["玉"],
"giok˨gi˥˧":["玉語"],
"giok˨lan˨˦hue˥˥":["玉蘭花"],
"giok˨san˥˥":["玉山"],
"gioŋ˥˧":["仰"],
"gioʔ˨":["謔","虐"],
"gio˨˦":["蟯"],
"giŋ˥˧":["眼","研"],
"giŋ˥˧puaʔ˨":["研缽"],
"giŋ˥˧tso˨˦":["研槽"],
"giŋ˨˦":["迎","凝"],
"giŋ˨˦hueʔ˨":["凝血"],
"giŋ˨˦sim˥˥":["凝心"],
"gi˥˧":["語","擬"],
"gi˧˧":["義","議"],
"gi˨˦":["疑","宜","儀","誼"],
"gi˨˦kui˥˧":["疑鬼"],
"goŋ˧˧":["戇"],
"goŋ˧˧bin˧˧":["戇面"],
"goŋ˧˧laŋ˨˦":["戇人"],
"goŋ˨˦":["楞"],
"go˧˧":["餓"],
"go˨˦":["鵝","遨","熬"],
"guan˥˧":["阮"],
"guan˥˧hĩã˥˥ko˥˥":["阮兄哥"],
"guan˧˧":["願"],
"guan˨˦":["原","元","源","員"],
"guan˨˦tsai˧˧":["原在"],
"guat˦":["月"],
"gua˥˧":["我"],
"gua˧˧":["外","偌"],
"gua˧˧hue˨˩":["外歲"],
"gua˧˧ku˥˧":["偌久"],
"gua˧˧sun˥˥":["外孫"],
"gueʔ˦":["月"],
"gueʔ˦lai˧˧":["月內"],
"gueʔ˦tsʰim˥˥":["月深"],
"gue˧˧":["外"],
"gue˧˧siŋ˥˥":["外甥"],
"gui˧˧tso˧˧":["偽造"],
"gui˨˦hai˧˧":["危害"],
"gui˨˦hiam˥˧":["危險"],
"gui˨˦kip˨":["危急"],
"gui˨˦ki˥˥":["危機"],
"gu˥˧":["語"],
"gu˧˧":["遇","禦","寓"],
"gu˨˦":["牛"],
"gɔ˧˧":["五","誤","午"],
"gɔ˧˧sik˨":["五色"],
"gɔ˧˧si˨˦":["五時"],
"gɔ˧˧si˨˦tsui˥˧":["午時水"],
"gɔ˧˧tsap˦":["五十"],
"gɔ˨˦lok˨":["娛樂"],
"hai!7":["害！"],
"haih˨":["唉"],
"hai˥˥":["奒"],
"hai˥˥hai˥˥":["咍咍"],
"hai˥˧":["海"],
"hai˥˧bi˧˧":["海味"],
"hai˥˧se˨˩":["海誓"],
"hai˧˧":["害","亥","械"],
"hai˧˧biŋ˧˧":["害命"],
"hai˧˧li˥˧":["害理"],
"hai˨˦":["頦","諧","骸","孩"],
"hai˨˦dzi˨˦":["孩兒"],
"hak˦":["學","礐"],
"hak˦siŋ˥˥":["學生"],
"hak˨":["蓄"],
"ham˥˥":["蚶","𦜆","䈄"],
"ham˥˧":["撼"],
"ham˧˧":["陷","憾","和"],
"ham˨˦":["含","涵","函"],
"ham˨˩":["譀"],
"han˥˥tsi˨˦":["番薯"],
"han˥˧":["罕","喊"],
"han˧˧":["限","旱"],
"han˨˦":["寒","閒","𫟂","韓"],
"han˨˦ban˧˧":["頇顢"],
"han˨˩":["漢"],
"hap˦":["合"],
"hap˨":["欱"],
"hat˦":["乏","核"],
"hat˨":["轄","喝"],
"hau˥˥":["嘐"],
"hau˥˧":["吼"],
"hau˧˧":["校","效","候","鱟","後"],
"hau˨˩":["孝"],
"haŋ˥˥":["烘","魴"],
"haŋ˧˧":["項","巷"],
"haŋ˧˧haŋ˧˧":["項項"],
"haŋ˨˦":["行","航","降"],
"haŋ˨˩":["肨","胮"],
"haʔ˦":["合","箬"],
"haʔ˨hi˨˩":["哈唏"],
"haʔ˨tsʰĩũ˨˩":["哈啾"],
"ha˥˥":["哈"],
"ha˥˧ma˥˧":["哈瑪"],
"ha˧˧":["下","夏"],
"ha˧˧huan˧˧":["下凡"],
"ha˨˦":["縖","荷"],
"ha˨˩":["孝"],
"heʔ˨":["嚇","嘿"],
"he˥˥":["彼","痚"],
"he˥˥ku˥˥":["痚呴"],
"he˧˧":["下","系","夏","係","蟹","繫"],
"he˨˦":["蝦","霞"],
"he˨˩se˥˥":["屏遮"],
"hiam˥˥":["薟"],
"hiam˥˧":["險"],
"hiam˨˦":["嫌"],
"hiam˨˩":["喊"],
"hian˥˥":["掀"],
"hian˥˧":["顯","搟"],
"hian˧˧":["現"],
"hian˨˦":["絃","弦","賢","玄"],
"hian˨˦hue˧˧":["賢慧"],
"hian˨˩":["獻","憲","羶","現"],
"hiap˦":["協","拹","脅"],
"hiat˦":["穴"],
"hiat˨":["血","㧒"],
"hiat˨kak˦":["㧒捔"],
"hiauʔ˨":["藃"],
"hiau˥˥":["僥","梟"],
"hiau˥˥pai˥˥":["囂俳"],
"hiau˥˧":["曉"],
"hiau˥˧sĩũ˧˧":["曉想"],
"hiau˨˦":["嬈"],
"hiaŋ˥˥":["香"],
"hiaŋ˥˧":["享","響"],
"hiaŋ˨˩":["向"],
"hiaʔ˦":["額"],
"hiaʔ˦a˥˧":["額仔"],
"hiaʔ˨":["遐"],
"hiaʔ˨kin˥˧":["遐緊"],
"hiaʔ˨taŋ˨˩sŋ˥˥":["遐凍霜"],
"hia˥˥":["遐","桸","靴"],
"hia˧˧":["瓦","蟻"],
"hik˦":["核","域","惑","或"],
"hik˨":["嚇"],
"him˥˥":["欣"],
"him˨˦":["熊"],
"hin˧˧":["恨"],
"hin˨˦":["眩"],
"hioŋ˥˥":["鄉","凶","香","兇"],
"hioŋ˥˧":["響","享"],
"hioŋ˨˦":["雄"],
"hioŋ˨˩":["向"],
"hioʔ˨":["歇","葉","諾"],
"hioʔ˨kʰun˨˩":["歇睏"],
"hio˧˧":["後","后"],
"hio˧˧ko˥˧":["後果"],
"hip˨":["翕"],
"hit˨":["彼"],
"hiu˥˥":["休","咻"],
"hiu˨˦":["裘"],
"hiu˨˩":["𫝺"],
"hiŋ˥˥":["興","胸","兄"],
"hiŋ˧˧":["行","幸","杏","莧","倖","貺"],
"hiŋ˨˦":["行","形","型","刑","還","雄","衡","橫"],
"hiŋ˨˩":["興"],
"hi˥˥":["虛","稀","希","犧","墟"],
"hi˥˥hi˥˥hua˧˧hua˧˧":["嘻嘻嘩嘩"],
"hi˥˧":["喜","許"],
"hi˥˧bin˧˧":["喜面"],
"hi˥˧hi˥˧":["喜喜"],
"hi˨˦":["魚","漁"],
"hi˨˩":["戲","肺"],
"hi˨˩hŋ˥˥":["戲園"],
"hi──ū5":["魚──有"],
"hmʔ˨":["摁"],
"hmʔ˨hmʔ˨":["噷噷"],
"hm˥˥":["茅"],
"hok˨":["服","福","復","複","袱","覆","幅","輻","伏"],
"hok˨hiŋ˥˥":["復興"],
"hok˨liŋ˨˦":["茯苓"],
"hooh!1i˥˥na˥˧e˧˧tsiaʔ˨put˨su˥˧kui!2":["謼！伊哪會遮不死鬼！"],
"hoŋ˥˥":["風","方","封","豐","鋒","芳","轟","峰","揈","荒"],
"hoŋ˥˧":["訪","況","仿"],
"hoŋ˥˧hut˨":["彷彿"],
"hoŋ˧˧":["鳳","奉","俸"],
"hoŋ˧˧hoŋ˧˧":["烘烘"],
"hoŋ˨˦":["防","皇","黃","癀","紅","磺","妨","凰","縫","弘","潢","逢","宏"],
"hoŋ˨˦lai˨˦":["蓬萊"],
"hoŋ˨˩":["放"],
"hoʔ˨":["鶴"],
"ho˥˧":["好"],
"ho˥˧aʔ˨":["好矣"],
"ho˥˧sio˥˥kʰũã˨˩":["好相看"],
"ho˧˧":["號","賀","禍"],
"ho˨˦":["和","何","河","毫","壕","貉","富","豪","荷"],
"ho˨˦tsai˧˧":["何在"],
"huai˧˧":["壞"],
"huai˨˦":["懷","淮"],
"huan˥˥":["番","翻","歡","幡"],
"huan˥˥hu˨˩":["吩咐"],
"huan˥˥sin˥˥":["翻身"],
"huan˥˧":["反"],
"huan˥˧to˥˧":["反倒"],
"huan˧˧":["犯","範","凡","患","梵","還"],
"huan˨˦":["煩","凡","還","繁","礬","帆"],
"huan˨˩":["販","幻","喚","泛"],
"huat˦":["罰","發"],
"huat˦hi˨˦":["活魚"],
"huat˦pʰuat˨":["活潑"],
"huat˨":["法","發","髮"],
"huat˨tsai˨˦":["發財"],
"huaʔ˦":["伐"],
"huaʔ˨":["喝","砉"],
"huaʔ˨to˥˧":["喝倒"],
"hua˥˥":["花","化","華"],
"hua˨˦":["華"],
"hua˨˩":["化"],
"hueʔ˨":["血"],
"hue˥˥":["花","灰"],
"hue˥˥hue˥˥":["花花"],
"hue˥˥liŋ˨˦":["飛行"],
"hue˥˧":["火","伙","悔","賄"],
"hue˥˧a˥˧":["伙仔"],
"hue˥˧ki˨˩":["夥計"],
"hue˥˧toʔ˨":["火著"],
"hue˥˧tsʰia˥˥tsam˧˧":["火車站"],
"hue˥˧tua˧˧":["火大"],
"hue˧˧":["會","匯","繪","薈"],
"hue˨˦":["回","迴","𫝻"],
"hue˨˦lian˨˦":["荷蘭"],
"hue˨˦sĩũ˧˧":["和尚"],
"hue˨˩":["貨","歲"],
"hui˥˥":["非","飛","妃","揮","暉"],
"hui˥˥hoŋ˨˦":["輝煌"],
"hui˥˧":["匪","毀","翡"],
"hui˥˧poŋ˨˩":["誹謗"],
"hui˧˧":["惠","慧"],
"hui˨˦":["瓷"],
"hui˨˩":["費","廢"],
"hui˨˩tak˨":["費觸"],
"hun˥˥":["分","薰","婚","紛","昏","氛"],
"hun˥˥hun˥˥":["紛紛"],
"hun˥˥sin˥˥":["分身"],
"hun˥˧":["粉"],
"hun˧˧":["份","昏","恨","混","分"],
"hun˨˦":["魂","痕","雲"],
"hun˨˦hua˨˩":["焚化"],
"hun˨˩":["訓","憤","奮","楦"],
"hut˦":["佛","核"],
"hut˨":["忽","拂","囫"],
"hut˨hut˨":["唿唿"],
"hu˥˥":["夫","烌","膚","麩","撫"],
"hu˥˥hu˥˥":["虎虎"],
"hu˥˥lɔ˥˧":["俘虜"],
"hu˥˧":["府","拊","輔","腐","腑","撫"],
"hu˧˧":["婦","父","負","腐"],
"hu˨˦":["符","扶"],
"hu˨˩":["付","富","副","附","赴","賦","訃"],
"hãĩ˥˥":["哼"],
"hãĩ˨˩":["幌"],
"hãũʔ˦hãũʔ˦":["澩澩"],
"hãʔ˨":["唅","熁"],
"hã˥˧":["嚇"],
"hã˧˧":["迒"],
"hõ˥˥":["呼","齁"],
"hõ˥˧":["否"],
"hõ˨":["乎"],
"hõ˨˩":["好"],
"hún──khuann3":["粉──看"],
"hĩãʔ˨":["挔","嚇"],
"hĩã˥˥":["兄"],
"hĩã˥˥ko˥˥":["兄哥"],
"hĩã˥˥ti˧˧":["兄弟"],
"hĩã˥˧":["顯"],
"hĩã˧˧":["艾"],
"hĩã˨˦":["燃","惶"],
"hĩã˨˩":["向"],
"hĩũ˥˥":["香","鄉"],
"hĩũ˥˥u˧˧po˥˧pi˨˩":["香有保庇"],
"hĩ˧˧":["耳","硯"],
"hĩ˨˩":["挕"],
"hŋʔ˨":["哼"],
"hŋ˥˥":["園","方","昏","荒","遠"],
"hŋ˥˥a˥˧":["園"],
"hŋ˥˥kʰu˥˥":["園區"],
"hũãĩ˨˦":["橫","莖"],
"hũã˥˥":["歡"],
"hũã˥˧":["晃"],
"hũã˧˧":["岸","扞","旱"],
"hũã˨˦":["鼾"],
"hɔʔ˨":["謼"],
"hɔ˥˥":["呼"],
"hɔ˥˧":["虎","唬","滸"],
"hɔ˧˧":["予","雨","戶","護","互","厚","後"],
"hɔ˨˦":["鬍","撈","葫"],
"hɔ˨˦liu˥˥":["鰗鰡"],
"hɔ˨˦li˨˦":["狐狸"],
"hɔ˨˦lui˨˩lui˨˩":["糊瘰瘰"],
"hɔ˨˦sin˨˦":["胡蠅"],
"hɔ˨˦tsio˥˥":["胡椒"],
"hɔ˨˦tsʰiu˥˥":["鬍鬚"],
"hɔ˨˦tɔ˨˦":["糊塗"],
"hɔ˨˩":["戽"],
"iam˥˥":["閹"],
"iam˥˥ĩũ˨˦":["陰陽"],
"iam˥˥ĩũ˨˦a˥˧ma˧˧":["陰陽仔嘛"],
"iam˥˧":["掩"],
"iam˧˧":["炎","豔"],
"iam˨˦":["鹽"],
"ian˥˥":["煙","嫣","胭","淵"],
"ian˥˧":["演","偃","衍"],
"ian˨˦":["緣","鉛","延","沿","蝝"],
"ian˨˦sui˥˥":["芫荽"],
"ian˨˦tau˨˦":["緣投"],
"ian˨˩":["宴","燕","厭"],
"ian˨˩o˥˥":["燕窩"],
"iap˨":["揜"],
"iap˨iap˨":["揜揜"],
"iat˦":["擛"],
"iau˥˥":["枵","妖","邀","要"],
"iau˥˧":["猶","夭"],
"iau˥˧siu!7":["夭壽！"],
"iau˥˧siu˧˧tinn!1":["夭壽甜！"],
"iau˧˧":["耀"],
"iau˨˦":["謠","遙","搖"],
"iau˨˩":["要"],
"iau˨˩kin˥˧":["要緊"],
"iaŋ˥˥":["央"],
"iaŋ˥˥kaʔ˨":["央教"],
"iaŋ˧˧":["煬"],
"iaʔ˦":["抑","驛","頁","蝶","蛾","疫","易"],
"iaʔ˨":["搤","抑"],
"ia˥˥":["埃"],
"ia˥˧":["野"],
"ia˧˧":["也","夜","掖"],
"ia˨˦":["爺","耶","椰"],
"ia˨˩":["厭"],
"ik˦":["疫","浴","譯","役","易","液","亦"],
"ik˦tĩũ˨˦":["浴場"],
"ik˨":["益","憶","溢","億"],
"im˥˥":["音","陰","淹"],
"im˥˥tʰim˥˥":["陰鴆"],
"im˥˧":["飲"],
"im˨˦":["淫"],
"im˨˩":["蔭","廕"],
"in˥˥":["因","姻","恩","𪜶","絪"],
"in˥˧":["引","允"],
"in˧˧":["孕"],
"in˨˦":["寅"],
"in˨˦bau˥˧":["寅卯"],
"in˨˩":["印","應"],
"in˨˩tsiʔ˦":["應舌"],
"iok˨":["約","育","欲","籲","慾"],
"ioŋ˥˥":["央"],
"ioŋ˥˧":["養","勇","擁","氧"],
"ioŋ˥˧hua˨˩tʰũã˨˩":["氧化碳"],
"ioŋ˥˧iok˨":["踴躍"],
"ioŋ˧˧":["用"],
"ioŋ˧˧e˨˦":["用的"],
"ioŋ˨˦":["容","陽","揚","融"],
"ioʔ˨":["藥","臆","唷"],
"ioʔ˨a˥˧":["藥仔"],
"ioʔ˨tsʰut˨":["臆出"],
"io˥˥":["腰","育","么"],
"io˥˥dzi˧˧":["么二"],
"io˥˧":["扷"],
"io˨˦":["搖","窯"],
"ip˨boŋ˧˧":["挹墓"],
"it˨":["一","乙","憶"],
"it˨i˨˩":["一意"],
"it˨kʰoŋ˨˩it˨":["101"],
"it˨lɔ˧˧":["一路"],
"it˨sit˨":["一失"],
"it˨tan˨˩":["一旦"],
"it˨tioŋ˨˩":["一中"],
"it˨ĩũ˧˧":["一樣"],
"iu˥˥":["優","憂","幽","釉","猶"],
"iu˥˧":["有","友","誘","酉"],
"iu˥˧hiŋ˧˧":["有幸"],
"iu˥˧hoŋ˥˥":["有方"],
"iu˥˧sɔ˨˩":["有數"],
"iu˥˧tsun˧˧":["有陣"],
"iu˧˧":["又","柚","右","佑"],
"iu˨˦":["油","遊","郵","由","游","尤"],
"iu˨˦dzin˨˦":["由人"],
"iu˨˦tʰĩ˥˥":["由天"],
"iu˨˩":["幼"],
"iu˨˩a˥˧":["幼仔"],
"iu˨˩tsʰiu˥˧":["幼手"],
"iŋ˥˥":["英","鷹","應","鸚","癰","坱","嬰","櫻","鶯"],
"iŋ˥˥hue˥˥":["櫻花"],
"iŋ˥˥tai˨˦":["英台"],
"iŋ˥˧":["湧","永","往","影","泳"],
"iŋ˧˧":["用"],
"iŋ˨˦":["閒","營","榮","螢"],
"iŋ˨˦u˨˦":["盈餘"],
"iŋ˨˩":["應","壅","映"],
"iŋ˨˩pian˨˩":["應變"],
"iŋ˨˩tsʰai˨˩":["蕹菜"],
"i˥˥":["伊","醫","衣","遺"],
"i˥˥bo˨˦":["依無"],
"i˥˥huat˨":["依法"],
"i˥˥hu˨˩":["依附"],
"i˥˥ki˨˩":["依據"],
"i˥˥nai˧˧":["依賴"],
"i˥˥to˧˧bo˨˦m˥˥tioʔ˨laʔ˨":["伊就無毋著啦"],
"i˥˥tsiau˨˩":["依照"],
"i˥˥ua˥˧":["依倚"],
"i˥˧":["以","椅","已"],
"i˥˧tioŋ˧˧":["倚重"],
"i˧˧":["預","異","易","奕"],
"i˧˧suan˨˩":["預算"],
"i˨˦":["姨","移","於"],
"i˨˦tsʰi˨˦":["維持"],
"i˨˩":["意"],
"i˨˩dzin˨˦":["薏仁"],
"kai˥˥":["該","階","皆"],
"kai˥˧":["解","改","骱"],
"kai˥˧eʔ˨":["解厄"],
"kai˥˧ut˨":["解鬱","改鬱"],
"kai˨˩":["界","介","概","蓋","戒","誡","芥","屆"],
"kai˨˩buaʔ˦":["芥末"],
"kak˦":["捔"],
"kak˨":["角","覺","鵤","桷"],
"kam˥˥":["甘","柑","疳","魽","監"],
"kam˥˥hiam˨˦laʔ˨":["甘嫌啦"],
"kam˥˧":["感","敢","𥴊"],
"kam˨˦":["含"],
"kam˨˩":["監","鑑"],
"kan˥˥":["干","間","矸","奸","姦","乾","肝","杆"],
"kan˥˥a˥˧beh!1":["干仔欲！"],
"kan˥˥kʰɔ˥˧":["艱苦"],
"kan˥˥lan˨˦":["艱難"],
"kan˥˥na˥˧":["橄欖"],
"kan˥˥sin˨˦":["奸臣"],
"kan˥˥tau˧˧":["關渡"],
"kan˥˧":["簡","𡢃"],
"kan˨˩":["姦","幹","間"],
"kan˨˩sũã˨˩":["幹線"],
"kap˨":["敆","佮","蛤","合"],
"kat˨":["結","墼","葛"],
"kat˨bin˧˧":["結面"],
"kauʔ˨":["𩛩","軋"],
"kau˥˥":["交","溝","勾","鉤","郊","蛟"],
"kau˥˥i˥˧":["交椅"],
"kau˥˥liaŋ˨˦":["高粱"],
"kau˥˥tsʰiaŋ˨˦":["高長"],
"kau˥˧":["狗","九","垢","狡"],
"kau˥˧be˧˧pui˧˧":["狗袂吠"],
"kau˥˧kʰa˥˥tsʰŋ˥˥":["九尻川"],
"kau˥˧kʰi˨˩":["狗去"],
"kau˧˧":["厚"],
"kau˧˧kau˧˧":["詬詬"],
"kau˧˧tsi˥˧":["厚子"],
"kau˨˦":["猴"],
"kau˨˩":["教","到","夠","校"],
"kau˨˩am˨˩":["到暗"],
"kau˨˩kau˨˩":["夠夠"],
"kaŋ˥˥":["工","公","江","功"],
"kaŋ˥˥sioŋ˥˥":["工商"],
"kaŋ˥˧":["港","講","犅","江"],
"kaŋ˧˧":["仝","共"],
"kaŋ˧˧sim˥˥":["仝心"],
"kaŋ˨˩":["降"],
"kaʔ˨":["甲","佮","䘥","蓋","鴿","較","柙"],
"kaʔ˨sim˥˥":["胛心"],
"kaʔ˨ui˨˩":["甲飫"],
"ka˥˥":["家","加","佳","嘉","膠","鉸","交","咳","鮫"],
"ka˥˥buaʔ˦":["茄茉"],
"ka˥˥lat˦":["栗"],
"ka˥˥lauʔ˦":["交落"],
"ka˥˥le˥˧":["傀儡"],
"ka˥˥liŋ˧˧":["鵁鴒"],
"ka˥˥li˥˧":["咖哩"],
"ka˥˥lo˥˧":["茭荖"],
"ka˥˥lun˥˧sun˥˧":["交懍恂"],
"ka˥˥pi˥˥":["咖啡"],
"ka˥˥taŋ˥˥":["茄苳"],
"ka˥˥tsau˥˧":["虼蚤"],
"ka˥˥tsuaʔ˦":["虼蚻"],
"ka˥˥tsue˧˧":["瞌睡"],
"ka˥˧":["假","絞"],
"ka˧˧":["共","咬"],
"ka˨˩":["教","駕","架","假","較","漖"],
"ka˨˩kau˥˧":["教狗"],
"ka˨˩kau˨˦":["教猴"],
"ke!1tsap˦":["家！十"],
"keʔ˦":["扴"],
"keʔ˨":["格","隔","鍥","骼","挌"],
"keʔ˨piaʔ˨":["隔壁"],
"ke˥˥":["家","雞","加","街"],
"ke˥˥a˥˧":["雞仔","街仔"],
"ke˥˥laŋ˨˦":["家人","基隆"],
"ke˥˧":["假"],
"ke˥˧kuai˨˩":["假怪"],
"ke˥˧pʰok˨":["假博"],
"ke˥˧se˨˩dzi˧˧":["假細膩"],
"ke˥˧tak˨":["假觸"],
"ke˥˧uaʔ˦":["假活"],
"ke˧˧":["低"],
"ke˨˦":["膎","枷"],
"ke˨˩":["價","計","嫁","架","界","繼","疥"],
"ke˨˩kau˨˩":["計較"],
"ke˨˩na˨˦":["芥藍"],
"khǹg1":["勸","囥"],
"kiam˥˥":["兼"],
"kiam˥˧":["減","檢"],
"kiam˥˧liau˧˧":["減料"],
"kiam˨˦":["鹹"],
"kiam˨˩":["劍"],
"kian˥˥":["堅"],
"kian˥˧":["繭"],
"kian˧˧":["健","胘","鍵"],
"kian˨˩":["見","建","毽"],
"kian˨˩tsi˥˧":["腱子"],
"kiap˨":["劫","峽","裌","俠"],
"kiat˦":["傑"],
"kiat˨":["結","吉","桔","潔","搩"],
"kiat˨toŋ˥˧":["結黨"],
"kiau˥˥":["嬌","轎","交"],
"kiau˥˥ŋɔ˧˧":["驕傲"],
"kiau˥˧":["筊","繳","攪","餃","矯"],
"kiau˥˧iam˨˦":["攪鹽"],
"kiau˧˧":["撬","撟"],
"kiau˨˦":["僑"],
"kiau˨˩kiau˨˩":["噭噭"],
"kiaʔ˦":["屐"],
"kia˧˧":["崎"],
"kia˨˩":["寄"],
"kik˦":["極","劇"],
"kik˨":["激","擊","革"],
"kim˥˥":["金","今"],
"kim˥˧":["錦"],
"kim˧˧":["妗"],
"kim˨˩":["禁"],
"kin˥˥":["今","筋","根","巾","斤","跟","均"],
"kin˥˧":["緊","謹"],
"kin˥˧tsau˥˧":["緊走"],
"kin˧˧":["近"],
"kin˨˩":["絹"],
"kiok˨":["局","劇","菊","侷"],
"kiok˨kioŋ˥˥":["鞠躬"],
"kioŋ˥˥":["宮","供","芎","恭"],
"kioŋ˧˧":["共","強"],
"kioŋ˧˧kioŋ˧˧":["強強"],
"kioŋ˨˦":["強","窮"],
"kioʔ˨":["腳"],
"kio˧˧":["轎"],
"kio˨˦":["橋","茄"],
"kio˨˩":["叫"],
"kio˨˩bu˥˧":["叫母"],
"kio˨˩kʰɔ˥˧":["叫苦"],
"kio˨˩tsʰai˨˩":["叫菜"],
"kip˦":["及","笈"],
"kip˨":["級","急","給"],
"kiu˥˥":["勼"],
"kiu˥˥tsʰiu˥˧":["勼手"],
"kiu˥˧":["九","久"],
"kiu˥˧liu˨˦":["九流"],
"kiu˥˧uan˥˧":["久遠"],
"kiu˨˦":["球","求","毬"],
"kiu˨˦a˥˧":["球仔"],
"kiu˨˩":["救","糾","究"],
"kiŋ˥˥":["經","間","弓","更","供","宮","肩","庚"],
"kiŋ˥˥kaʔ˨":["肩胛"],
"kiŋ˥˥li˥˧":["經理"],
"kiŋ˥˥sin˥˥an˥˥":["耕莘安"],
"kiŋ˥˥tsio˥˥":["弓蕉"],
"kiŋ˥˧":["警","景","境","揀","襇","筧","繭"],
"kiŋ˧˧":["競","楗"],
"kiŋ˨˦":["窮"],
"kiŋ˨˩":["敬","竟","徑","更","供"],
"ki˥˥":["機","基","枝","技","居","肢","支","飢","裾","吱","箕","妓","梔","乩"],
"ki˥˥hŋ˥˥kʰu˥˥":["技園區"],
"ki˥˥li˥˧gan˧˧":["唭哩岸"],
"ki˥˥tsian˨˦":["車前"],
"ki˥˥tsʰĩũ˥˧":["機廠"],
"ki˥˥tĩũ˨˦":["機場"],
"ki˥˧":["舉","指","己","矩","紀","幾"],
"ki˧˧":["己","忌","距","拒"],
"ki˧˧tan˨˩":["巨蛋"],
"ki˨˦":["期","奇","其","棋","旗","祈","歧","耆"],
"ki˨˦lim˨˦":["淇淋"],
"ki˨˦lin˨˦":["麒麟"],
"ki˨˦miau˧˧":["其妙"],
"ki˨˩":["記","據","紀","痣","鋸","既"],
"kok˨":["國","各","咯","穀","顎","谷","焗"],
"kok˨giap˦":["各業"],
"kok˨sio˥˧":["國小"],
"kok˨sĩã˨˦":["國城"],
"kok˨tioŋ˥˥":["國中"],
"koŋ˥˥":["公","光","功","攻","工","剛","崗","岡","栱","肱","綱"],
"koŋ˥˥hŋ˥˥":["公園"],
"koŋ˥˥san˥˥":["岡山"],
"koŋ˥˥tsu˥˧":["公子","功主"],
"koŋ˥˧":["講","管","廣"],
"koŋ˥˧a˥˧":["管仔"],
"koŋ˨˦":["狂","栱"],
"koŋ˨˩":["摃","貢"],
"koŋ˨˩koŋ˨˩":["絳絳"],
"koʔ˨":["閣","過","胳","各","哥"],
"koʔ˨bu˥˧":["各母"],
"ko˥˥":["高","哥","膏","糕","篙","歌","鍋","戈"],
"ko˥˥nua˧˧":["哥瀾"],
"ko˥˥tioŋ˥˥":["高中"],
"ko˥˧":["果","稿","裹"],
"ko˧˧":["滒"],
"ko˧˧ko˧˧":["翱翱"],
"ko˨˦":["笱"],
"ko˨˦ko˨˦":["膏膏"],
"ko˨˩":["告","個","過","划"],
"kuai˥˥":["乖","胿"],
"kuai˥˧":["拐","枴"],
"kuai˨˩":["怪"],
"kuan˥˥":["關","觀","冠","官","捐","鵑","棺"],
"kuan˥˧":["管","館"],
"kuan˥˧lah!1":["管啦！"],
"kuan˧˧":["縣"],
"kuan˨˦":["懸","權"],
"kuan˨˩":["罐","灌","券","貫","眷","卷","慣"],
"kuat˨":["決","訣","抉","括"],
"kuaʔ˨":["割","括"],
"kua˥˥":["歌","柯","瓜"],
"kua˥˧":["寡"],
"kua˧˧kua˧˧":["呱呱"],
"kua˨˩":["掛","蓋","卦","褂"],
"kua˨˩tsʰai˨˩":["芥菜"],
"kueʔ˦":["橛"],
"kueʔ˨":["刮","蕨"],
"kue˥˥":["瓜"],
"kue˥˧":["粿","跂"],
"kue˥˧a˥˧":["粿仔"],
"kue˥˧tsi˥˧":["果子"],
"kue˨˩":["過","髻","鱖","會","怪"],
"kue˨˩hai˥˧":["過海"],
"kue˨˩liau˥˧au˧˧":["過了後"],
"kui˥˥":["規","胿","歸","龜","機","䲅"],
"kui˥˥a˥˧":["胿仔"],
"kui˥˥toŋ˥˧":["規黨"],
"kui˥˧":["鬼","幾","詭","軌","癸"],
"kui˥˧a˥˧":["鬼仔"],
"kui˥˧nau˥˧":["鬼腦"],
"kui˧˧":["櫃","膭","跪","饋"],
"kui˨˩":["貴","季","桂","挂","劌"],
"kui˨˩ho˨˦":["貴和"],
"kun˥˥":["軍","君"],
"kun˥˧":["滾","蚓"],
"kun˨˦":["拳","群","裙","𤉙"],
"kun˨˦a˥˧":["裙仔"],
"kun˨˩":["棍"],
"kut˦":["滑","掘"],
"kut˦a˥˧":["掘仔"],
"kut˨":["骨"],
"ku˥˥":["龜","痀","居","跔"],
"ku˥˥li˥˧":["苦力"],
"ku˥˧":["久","韭"],
"ku˥˧a˥˧":["久仔"],
"ku˧˧":["舊","具","舅"],
"ku˧˧siaʔ˨":["舊錫"],
"ku˧˧tsʰau˨˩":["舊臭"],
"ku˨˩":["句","灸"],
"ku˨˩ku˨˩":["句句"],
"kãĩ˥˥":["喈"],
"kãĩ˨˦":["睚"],
"kã˥˥":["監"],
"kã˥˧":["敢"],
"kã˨˦":["含"],
"kã˨˩":["酵"],
"kõ˨˦":["鼾"],
"kĩã˥˥":["驚","京"],
"kĩã˥˥ŋe˧˧":["驚硬"],
"kĩã˥˧":["囝"],
"kĩã˥˧iu˨˩":["囝幼"],
"kĩã˥˧sun˥˥":["囝孫"],
"kĩã˧˧":["件","健"],
"kĩã˨˦":["行","檠"],
"kĩã˨˩":["鏡"],
"kĩũ˥˥":["薑","羌","姜"],
"kĩ˥˥":["鹼"],
"kĩ˨˦":["墘"],
"kĩ˨˩":["見"],
"kńg1":["管","卷","捲"],
"kńg1le˨˦":["捲螺"],
"kŋ˥˥":["光","缸","扛"],
"kũãĩ˥˥":["關","杆"],
"kũãĩ˥˧":["稈","桿"],
"kũãĩ˧˧":["拐"],
"kũã˥˥":["官","肝","乾","菅","棺","杆","倌"],
"kũã˥˥baŋ˨˦":["菅芒"],
"kũã˥˥tsin˥˥":["竿蓁"],
"kũã˥˧":["趕"],
"kũã˧˧":["汗","捾","綰"],
"kũã˨˦":["寒"],
"kǹg1":["鋼","貫","券","槓","卷"],
"kɔ˥˥":["姑","孤","菇","蛄","罟","膏","辜","溝","枯"],
"kɔ˥˥tai˥˥":["鮕鮘"],
"kɔ˥˧":["古","鼓","股","估","鈷"],
"kɔ˥˧ki˥˧":["枸杞"],
"kɔ˥˧pan!2":["古板！"],
"kɔ˧˧":["怙"],
"kɔ˨˦":["糊"],
"kɔ˨˩":["顧","故","構","固","購","過"],
"kɔ˨˩au˧˧":["顧後"],
"kʰai˥˥":["開"],
"kʰai˥˧":["楷"],
"kʰai˥˧suan˨˦":["凱旋"],
"kʰai˨˩":["概","慨"],
"kʰak˦":["咯"],
"kʰak˨":["殼","確","麴"],
"kʰam˥˥":["堪","勘","龕"],
"kʰam˥˧":["坎","歁"],
"kʰam˨˩":["崁"],
"kʰam˨˩bin˧˧":["崁面"],
"kʰam˨˩kua˨˩":["崁蓋"],
"kʰan˥˥":["牽","刊"],
"kʰan˥˥gu˨˦":["牽牛"],
"kʰan˨˩":["看"],
"kʰap˦":["磕"],
"kʰap˨":["匼"],
"kʰat˨":["𣁳"],
"kʰau˥˥":["剾","鬮","薅","扣","敲"],
"kʰau˥˧":["口"],
"kʰau˥˧tsʰi˨˩":["口試"],
"kʰau˨˩":["哭","扣","叩","銬"],
"kʰau˨˩bu˥˧":["哭母"],
"kʰau˨˩kʰau˨˩":["哭哭"],
"kʰaŋ˥˥":["空"],
"kʰaŋ˥˥a˥˧":["空仔"],
"kʰaŋ˥˥dzip˦":["空入"],
"kʰaŋ˥˥kʰue˨˩":["工課"],
"kʰaŋ˥˥tsʰut˨":["空出"],
"kʰaŋ˥˧":["孔"],
"kʰaŋ˨˩":["空","控"],
"kʰaʔ˦":["闔","卡"],
"kʰaʔ˦tiau˨˦leh!1":["卡牢咧！"],
"kʰaʔ˨":["較","卡","籗","盍"],
"kʰaʔ˨ke˧˧":["較低"],
"kʰaʔ˨taŋ˥˧hĩãʔ˨":["較懂嚇"],
"kʰaʔ˨tsim˥˥tsiok˨":["較斟酌"],
"kʰa˥˥":["跤","腳","佳"],
"kʰa˥˥a˥˧":["跤仔"],
"kʰa˥˥peʔ˦":["茭白"],
"kʰa˥˥tsiaʔ˨":["尻脊"],
"kʰa˥˥tsiaʔ˨pʰĩã˥˥":["尻脊骿"],
"kʰa˥˥tsʰia˥˥":["枷車"],
"kʰa˥˥tsʰiu˥˧":["跤手"],
"kʰa˥˥tsʰĩũ˨˩":["咳啾"],
"kʰa˥˥tsʰŋ˥˥":["尻川"],
"kʰa˥˥ue˧˧":["跤話"],
"kʰa˥˧":["巧"],
"kʰa˥˧gi˥˧":["巧語"],
"kʰa˨˩":["敲"],
"kʰeʔ˦":["挈"],
"kʰeʔ˨":["客","瞌","𤲍","篋"],
"kʰeʔ˨a˥˧":["篋仔"],
"kʰe˥˥":["溪","稽","刮"],
"kʰe˥˧":["啟"],
"kʰe˨˦":["㧎"],
"kʰe˨˩":["契","齧"],
"kʰiak˦kʰiak˦":["確確"],
"kʰiam˥˥":["謙"],
"kʰiam˧˧":["儉"],
"kʰiam˨˩":["欠","歉"],
"kʰiam˨˩kʰueʔ˨sĩãʔ˨":["欠缺啥"],
"kʰian˥˥":["圈","掔"],
"kʰian˥˧":["遣","譴"],
"kʰian˨˦":["虔","乾"],
"kʰian˨˩":["芡","譴"],
"kʰiap˨":["㾀"],
"kʰiat˦kʰiat˦":["坷坷"],
"kʰiat˨":["戛","譎"],
"kʰiau˥˥":["曲","蹺"],
"kʰiau˥˧":["巧"],
"kʰiau˥˧e˨˦":["巧的"],
"kʰiau˨˩":["翹","竅"],
"kʰiaŋ˥˥":["勍","腔"],
"kʰiaŋ˨˩":["勥"],
"kʰiaʔ˨":["隙"],
"kʰia˥˥":["奇","欹","迦"],
"kʰia˧˧":["徛"],
"kʰia˧˧ŋ˥˥":["徛黃"],
"kʰia˨˦":["騎"],
"kʰik˨":["刻","曲","克","剋"],
"kʰik˨kʰik˨":["刻刻"],
"kʰim˥˥":["襟"],
"kʰim˨˦":["琴","禽","擒"],
"kʰin˥˥":["輕"],
"kʰin˨˦":["勤"],
"kʰin˨˦tsʰai˨˩":["芹菜"],
"kʰiok˨":["曲","卻"],
"kʰioŋ˥˥":["殭"],
"kʰioŋ˥˧":["恐"],
"kʰioʔ˨":["抾"],
"kʰio˨˩":["叩","筧","竅"],
"kʰip˦":["扱"],
"kʰip˨":["吸"],
"kʰit˦":["杙","煡"],
"kʰit˨":["乞"],
"kʰiu˥˧":["搝"],
"kʰiu˧˧":["𩚨"],
"kʰiu˨˦":["虯"],
"kʰiŋ˥˥":["框","銎","筐","傾"],
"kʰiŋ˥˥pian˧˧":["輕便"],
"kʰiŋ˥˧":["肯","頃"],
"kʰiŋ˧˧":["虹"],
"kʰiŋ˨˦":["窮","瓊"],
"kʰiŋ˨˦kʰoŋ˥˥":["窮空"],
"kʰiŋ˨˩":["慶"],
"kʰiʔ˨":["缺"],
"kʰi˥˥":["欺","敧","蹊"],
"kʰi˥˥sin˨˦":["欺神"],
"kʰi˥˧":["起","齒","紀"],
"kʰi˥˧iu˥˧":["豈有"],
"kʰi˥˧kin˥˥":["齒根"],
"kʰi˧˧":["柿","忌"],
"kʰi˨˦":["疧","蜞","騎"],
"kʰi˨˩":["去","氣","器","棄","汽","企"],
"kʰi˨˩ah!1":["去矣！"],
"kʰi˨˩ku˧˧":["棄舊"],
"kʰi˨˩kʰi˨˩":["去去"],
"kʰok˨":["擴","觳","硞","酷","鵠","柝","嘓","鱷"],
"kʰok˨kʰok˨":["硞硞","涸涸"],
"kʰoŋ˥˥":["空","悾","康","框"],
"kʰoŋ˥˥loŋ˨˦":["槺榔"],
"kʰoŋ˥˧":["孔","紺","慷"],
"kʰoŋ˧˧":["吭","鞏"],
"kʰoŋ˨˩":["抗","控","礦","炕","壙","曠","空"],
"kʰoŋ˨˩it˨":["空一"],
"kʰo˥˥":["科"],
"kʰo˥˥tai˧˧":["科大"],
"kʰo˥˧":["可","考","洘"],
"kʰo˥˧onn!3":["可惡！"],
"kʰo˨˦":["苛"],
"kʰo˨˩":["課","靠","犒"],
"kʰo˨˩se˨˩":["靠勢"],
"kʰuai˨˩":["快"],
"kʰuai˨˩kue˨˩":["快過"],
"kʰuai˨˩lau˧˧":["快老"],
"kʰuan˥˥":["寬","圈"],
"kʰuan˥˧":["款"],
"kʰuan˥˧laŋ˨˦":["款人"],
"kʰuan˨˦":["權","環"],
"kʰuan˨˩":["勸"],
"kʰuat˨":["缺"],
"kʰuaʔ˨":["闊","渴"],
"kʰua˥˥":["誇"],
"kʰua˥˧":["可"],
"kʰua˨˩":["掛","靠"],
"kʰueʔ˨":["缺"],
"kʰue˥˥":["詼","盔","恢"],
"kʰue˨˦":["瘸","葵"],
"kʰue˨˩":["架"],
"kʰui˥˥":["開","虧"],
"kʰui˥˥a˥˧":["開仔"],
"kʰui˥˥kʰa˥˥":["開跤"],
"kʰui˨˩":["氣"],
"kʰui˨˩ioŋ˨˦":["潰瘍"],
"kʰun˥˥":["昆","髡"],
"kʰun˥˧":["捆","菌","懇","墾"],
"kʰun˨˦":["囷","蜷"],
"kʰun˨˩":["睏","困"],
"kʰut˦":["𣮈"],
"kʰut˨":["屈","窟"],
"kʰut˨a˥˧":["窟仔"],
"kʰuʔ˨kʰuʔ˨":["呿呿"],
"kʰu˥˥":["區","軀","拘","坵","驅"],
"kʰu˥˥a˥˧":["邱仔"],
"kʰu˧˧":["臼","具"],
"kʰu˧˧lok˨":["俱樂"],
"kʰu˨˦":["跍"],
"kʰãĩ˥˥":["掮"],
"kʰãĩ˥˧":["敱"],
"kʰãũʔ˦":["摳"],
"kʰã˥˥":["坩"],
"kʰĩũ˥˥":["腔"],
"kʰĩũ˧˧":["噤"],
"kʰĩ˨˦":["鉗","拑"],
"kʰŋʔ˨":["吭"],
"kʰŋ˥˥":["糠"],
"kʰũã˥˥kʰũã˥˥":["寬寬"],
"kʰũã˥˥pan˧˧":["寬辦"],
"kʰũã˥˧":["款"],
"kʰũã˨˩":["看"],
"kʰũã˨˩be˧˧tioʔ˨":["看袂著"],
"kʰũã˨˩bo˨˦":["看無"],
"kʰũã˨˩kuan˨˦":["看懸"],
"kʰũã˨˩ĩũ˧˧":["看樣"],
"kʰũĩ˨˩":["快"],
"kʰɔ˥˥":["箍","呼"],
"kʰɔ˥˥a˥˧":["箍仔"],
"kʰɔ˥˥kʰɔ˥˧aʔ˨":["可可仔"],
"kʰɔ˥˥tũã˥˥":["呼蛋"],
"kʰɔ˥˧":["苦"],
"kʰɔ˥˧bin˧˧":["苦面"],
"kʰɔ˥˧tsĩã˥˧":["苦汫"],
"kʰɔ˨˩":["褲","庫"],
"kʰɔ˨˩kʰɔ˨˩":["怐怐"],
"kʰẽʔ˦":["喀"],
"kʰẽ˥˥":["坑"],
"kʰẽ˥˥a˥˧":["坑"],
"kẽ˥˥":["經","更","羹","庚"],
"kẽ˥˥tit˦":["驚蟄"],
"kẽ˥˥tsʰiu˥˧":["經手"],
"kẽ˥˧":["哽","耞"],
"kẽ˨˩":["桱"],
"lah!1":["啦！"],
"lai!5":["來！"],
"lai˥˧":["滓"],
"lai˧˧":["內","利"],
"lai˧˧e˨˦":["內的"],
"lai˨˦":["來","梨"],
"lai˨˦tau˨˩sã˥˥kang!7":["來鬥相共！"],
"lak˦":["六","搦"],
"lak˦dzio˧˧":["搦尿"],
"lak˦kiŋ˥˥":["六肩"],
"lak˦lak˦":["慄慄","搦搦"],
"lak˦tak˦":["磟碡"],
"lak˨":["落","戮","轆","鹿"],
"lak˨te˧˧":["橐袋"],
"lam˥˥":["籠"],
"lam˥˧":["覽","攬","荏","纜","腩"],
"lam˧˧":["濫","艦"],
"lam˨˦":["南","男","淋","楠"],
"lam˨˦kĩã˥˥":["南京"],
"lam˨˩":["湳","𨂾"],
"lan˥˥":["趼"],
"lan˥˧":["咱","懶"],
"lan˧˧":["𡳞","難"],
"lan˧˧tʰan˨˦":["亂彈"],
"lan˨˦":["難","鱗","蘭","欄","㔂"],
"lan˨˦hiŋ˨˦":["難行"],
"lan˨˦kam˥˥":["㔂甘"],
"lan˨˦san˥˥":["零星"],
"lap˦":["納"],
"lap˨":["塌","凹"],
"lat˦":["力","栗"],
"lau˥˥":["蹓"],
"lau˥˧":["老","佬","粩","荖","扭"],
"lau˧˧":["老","漏","鬧"],
"lau˧˧su˥˥":["老師"],
"lau˨˦":["流","樓","留","鐃"],
"lau˨˦kʰo˥˧":["流洘"],
"lau˨˩":["落"],
"lau˨˩kʰui˨˩":["落氣"],
"laŋ˥˥":["櫳","郎","籠"],
"laŋ˥˥ho˥˧tsiaʔ˦":["郎好食"],
"laŋ˥˧":["籠","攏"],
"laŋ˧˧":["弄","籠"],
"laŋ˨˦":["人","膿","籠","礱","聾","龍"],
"laŋ˨˦i˨˩":["人意"],
"laŋ˨˦kong!2":["人講！"],
"laŋ˨˩":["閬"],
"laʔ˦":["蠟","曆","鱲","臘","獵"],
"laʔ˨":["啦"],
"laʔ˨sap˨":["垃圾"],
"laʔ˨sap˨lah!1":["垃圾啦！"],
"la˥˥":["拉"],
"la˥˧paʔ˨":["喇叭"],
"la˧˧":["抐"],
"la˧˧ke˨˩":["抐計"],
"la˧˧pue˥˥":["抐桮"],
"la˧˧tʰeʔ˦":["抐宅"],
"la˨˦":["膋","蜊"],
"la˨˦gia˨˦":["蟧蜈"],
"la˨˦gia˨˦tsʰia˥˥":["蟧蜈車"],
"la˨˦li˥˧":["鯪鯉"],
"la˨˦lun˨˦":["拉圇"],
"la˨˦sam˨˦":["垃儳"],
"leh!1":["咧！"],
"leʔ˦":["笠","剺"],
"leʔ˨":["咧"],
"leʔ˨leʔ˨":["肭肭"],
"le˥˥":["絡"],
"le˥˧":["禮","嬭","醴","詈"],
"le˧˧":["例","麗","勵","鱺","篱","隸","鑢"],
"le˨˦":["螺","犁","麗","黎","腡"],
"le˨˦boŋ˥˧":["檸檬"],
"le˨˦hŋ˥˥":["梨園"],
"le˨˩":["礪"],
"liam˥˥":["拈","跕"],
"liam˥˧":["膁"],
"liam˧˧":["念","唸","殮","捻"],
"liam˨˦":["黏","簾","鯰"],
"liam˨˦mi˥˥":["連鞭"],
"liam˨˦mi˥˥to˧˧":["連鞭就"],
"liam˨˩":["捻"],
"lian˥˥":["蔫"],
"lian˥˧":["輪","撚","輦","臉","蓮","碾"],
"lian˧˧":["練","鍊","煉"],
"lian˨˦":["連","聯","蓮","年","憐","鰱","𦟪"],
"lian˨˦lo˨˦":["嗹囉"],
"lian˨˦pʰun˨˦":["連盆"],
"lian˨˦sun˥˥":["連孫"],
"lian˨˦tʰian˥˥":["連天"],
"lian˨˩":["輾"],
"lian˨˩tńg1":["輾轉"],
"liap˦":["粒","捏"],
"liap˦tsik˨":["粒積"],
"liap˨":["攝","𥍉"],
"liat˦":["列","烈","裂"],
"liau˥˧":["了"],
"liau˥˧au˧˧":["了後"],
"liau˥˧dzian˨˦":["了然"],
"liau˥˧kʰi˨˩nia˧˧nia˧˧":["了去爾爾"],
"liau˥˧pun˥˧":["了本"],
"liau˧˧":["料","繚"],
"liau˧˧li˥˧":["料理"],
"liau˨˦":["寮","療","聊","僚","嘹","條","蹽","瞭","撩"],
"liau˨˦ge˨˦":["獠牙"],
"liau˨˦loʔ˨":["蹽落"],
"liaŋ˥˥":["喨"],
"liaŋ˧˧":["亮"],
"liaŋ˨˦":["涼"],
"liaʔ˦":["掠"],
"liaʔ˨":["裂"],
"lik˦":["力","歷","綠","曆","壢","碌","栗","勒"],
"lik˨":["勒"],
"lim˥˥":["啉"],
"lim˥˥tsiu˥˧":["啉酒"],
"lim˥˧":["臨"],
"lim˨˦":["林","臨"],
"lim˨˦iau˧˧":["臨曜"],
"lin˥˥loŋ˥˥":["玲瑯"],
"lin˥˧":["恁"],
"lin˨˦":["鄰","麟","遴"],
"liok˨":["陸","六","略"],
"lioŋ˥˧":["兩","輛"],
"lioŋ˥˧i˨˩":["兩意"],
"lioŋ˥˧lip˦":["兩立"],
"lioŋ˥˧tuan˧˧":["兩斷"],
"lioŋ˧˧":["量","冗","諒"],
"lioŋ˨˦":["龍","良","量","隆","瀧"],
"lioŋ˨˩":["躘"],
"lioʔ˨":["略"],
"lio˥˧":["瞭"],
"lio˨˦":["𠞭","撩"],
"lip˦":["立"],
"liu˥˥":["溜"],
"liu˥˧":["鈕","綹","柳","扭"],
"liu˥˧ko˥˥":["柳哥"],
"liu˥˧lak˦":["扭搦"],
"liu˥˧tiŋ˥˥":["柳丁"],
"liu˧˧":["餾"],
"liu˨˦":["流","留","瘤","㨨","硫"],
"liu˨˦lian˨˦":["榴槤"],
"liu˨˩":["遛"],
"liu˨˩liu˨˩kĩã˨˦":["溜溜行"],
"liŋ˥˥":["奶"],
"liŋ˥˥a˥˧":["奶仔"],
"liŋ˥˧":["冷","領"],
"liŋ˥˧li˧˧":["伶俐"],
"liŋ˧˧":["令","另","冗","楝","稜"],
"liŋ˧˧si˥˥":["翎鷥"],
"liŋ˨˦":["能","龍","靈","鈴","寧","齡","凌","稜","零","拎","嚀","𦊓","菱"],
"liŋ˨˦lo˨˦tiu˨˦tuan˧˧":["綾羅綢緞"],
"liŋ˨˦ŋa˥˧un˧˧":["苓雅運"],
"liŋ˨˩liŋ˨˩":["蘢蘢"],
"liʔ˦":["裂"],
"liʔ˨":["哩"],
"li˥˥":["縭"],
"li˥˥li˥˥":["離離"],
"li˥˥li˥˥lo˥˥lo˥˥":["哩哩囉囉"],
"li˥˥lo˥˥":["哩囉"],
"li˥˥niau˥˥":["哩貓"],
"li˥˧":["你","理","里","女","旅","李","裡","履","鯉"],
"li˥˧kuan˥˧":["旅館"],
"li˧˧":["利","離","慮","厲","濾","痢"],
"li˧˧toŋ˧˧":["呂洞"],
"li˨˦":["簾","籬","離","厘","驢","狸"],
"li˨˩":["剺"],
"lok˨":["樂","錄","落","鹿","漉","橐","祿","諾","洛","絡"],
"lok˨kʰok˨":["碌硞"],
"lok˨lok˨":["彔彔"],
"lok˨sin˨˦":["洛神"],
"lok˨to˨˦":["駱駝"],
"lop˨":["橐"],
"loŋ˥˥":["瑯","囊"],
"loŋ˥˧":["攏","朗"],
"loŋ˧˧":["浪","弄"],
"loŋ˨˦":["農","囊","狼","籠","郎","廊","濃","櫳"],
"loŋ˨˩":["挵"],
"loŋ˨˩loŋ˨˩":["閬閬"],
"loʔ˨":["落","絡"],
"loʔ˨baʔ˨":["落肉"],
"loʔ˨kʰi˨˩":["落去"],
"loʔ˨lam˨˩":["落湳"],
"loʔ˨pak˨":["落腹"],
"loʔ˨tʰɔ˨˦":["落塗"],
"lo˥˥":["叨","囉"],
"lo˥˧":["惱","老","腦","潦"],
"lo˧˧":["號","囉","烙","勞"],
"lo˧˧kʰa˥˥tsʰŋ˥˥":["號尻川"],
"lo˨˦":["勞","羅","鑼","癆","濁","邏","牢"],
"lo˨˩":["躼"],
"luan˥˧":["暖","軟","卵","耎"],
"luan˧˧":["亂"],
"luan˨˦":["戀"],
"luaʔ˦":["捋","辣"],
"luaʔ˨":["捋"],
"lua˧˧":["賴","瀨"],
"lua˨˦":["籮"],
"lue˥˧":["餒"],
"lue˧˧":["內"],
"lui˥˧":["蕊","壘","累"],
"lui˧˧":["類","累","淚","彙","縋"],
"lui˨˦":["雷","擂","癗"],
"lun˥˥":["圇"],
"lun˥˧":["忍","懍","碖"],
"lun˧˧":["論","崙"],
"lun˨˦":["輪","倫","淪"],
"lut˦":["率","律"],
"lut˨":["甪"],
"lu˥˥":["攄"],
"lu˥˧":["女"],
"lu˨˩":["鑢"],
"lɔʔ˨":["囉"],
"lɔ˥˧":["滷","魯","惱","櫓","努","勞"],
"lɔ˥˧kɔ˥˧":["硓𥑮"],
"lɔ˥˧mia˧˧":["惱命"],
"lɔ˧˧":["路","露","𢲸"],
"lɔ˧˧gio˧˧":["蕗蕎"],
"lɔ˨˦":["爐","蘆","奴","鱸"],
"lɔ˨˦si˥˥":["螺絲"],
"lɔ˨˦tsi˨˦":["鸕鶿"],
"mai˥˥":["哩"],
"mai˥˧":["買"],
"mai˧˧":["覓","賣"],
"mai˨˩":["莫"],
"mai˨˩tsiaʔ˦":["莫食"],
"mauʔ˨":["卯"],
"mau˥˥":["㧌"],
"mau˧˧":["貌"],
"mau˨˦tun˥˧":["矛盾"],
"maʔ˨":["嘛","媽"],
"ma˥˥ka˥˧tau˥˧":["馬卡道"],
"ma˥˥la˥˧soŋ˥˧":["馬拉松"],
"ma˥˧":["馬","媽","碼"],
"ma˥˧se˥˥":["馬西"],
"ma˥˧sẽ˥˥":["媽生"],
"ma˧˧":["嘛","罵"],
"ma˧˧tsai˥˥":["嘛知"],
"ma˨˦":["麻"],
"ma˨˩ma˨˩":["嘛嘛"],
"meʔ˦":["脈"],
"meʔ˨":["蜢","咩"],
"me˥˥":["搣"],
"me˥˧":["猛"],
"me˧˧":["罵"],
"me˧˧me˧˧leʔ˨nia˧˧nia˧˧":["罵罵咧爾爾"],
"me˨˦":["暝","盲","鋩","明"],
"me˨˦ni˨˦tsio˥˥":["明年招"],
"miau˧˧":["妙"],
"mia˧˧":["命"],
"mia˧˧tsau˥˧":["命走"],
"mia˨˦":["名","樠"],
"miʔ˦":["物"],
"miʔ˨":["物"],
"miʔ˨a˥˧":["物仔"],
"mi˥˥mi˥˥":["糜糜"],
"mi˥˧":["乜","彌"],
"mi˧˧":["麵"],
"mi˧˧sũã˨˩":["麵線"],
"mi˨˦":["棉","綿"],
"mi˨˦nua˧˧":["綿爛"],
"muai˨˦":["糜"],
"mua˥˥":["幔"],
"mua˥˧":["滿"],
"mua˧˧":["蔓"],
"mua˨˦":["麻","瞞","鰻","痲"],
"mue˧˧":["妹"],
"mue˨˦":["糜","梅"],
"mue˨˦laŋ˨˦":["媒人"],
"mui˥˧":["每"],
"mui˨˦":["媒","梅"],
"mui˨˦kui˨˩":["玫瑰"],
"mńg1":["晚"],
"mŋ˥˥":["門","毛","問"],
"mŋ˥˥liau˥˧au˧˧":["門了後"],
"mŋ˥˥put˦":["問佛"],
"mɔʔ˨":["膜","𢯾","瘼"],
"mɔ˥˥":["毛","摸"],
"mɔ˧˧":["冒"],
"mɔ˨˦":["毛","魔","盲","摩","蘑","磨"],
"m˥˥":["毋","莓","梅"],
"m˥˥tat!8":["毋值！"],
"nai˥˥":["奶"],
"nai˧˧":["耐","賴","內","奈"],
"nai˧˧ho˨˦":["奈何"],
"nai˧˧tsi˥˥":["荔枝"],
"nauʔ˨":["喃"],
"nau˥˧":["腦","惱"],
"nau˧˧":["鬧"],
"naʔ˨":["凹","爁"],
"na˥˥":["焦"],
"na˥˧":["哪","若","那"],
"na˥˧bo˨˦":["若無"],
"na˥˧gu˨˦pi˥˥leʔ˨":["若牛螕咧"],
"na˥˧puat˦":["林菝"],
"na˧˧":["若","但","吶"],
"na˧˧tsʰiŋ˥˥liam˨˦":["若清廉"],
"na˨˦":["籃","林","藍"],
"na˨˦au˨˦":["嚨喉"],
"na˨˦lai˧˧":["林內"],
"neʔ˨":["躡","呢"],
"neʔ˨tɔ˧˧":["凹肚"],
"ne˥˥":["奶"],
"ne˨˦":["晾"],
"niau˥˥":["貓"],
"niau˥˧":["鳥"],
"niau˥˧tsʰi˥˧":["鳥鼠"],
"nia˥˧":["領","嶺"],
"nia˥˧hian˧˧":["領現"],
"nia˥˧pian˧˧":["領便"],
"nia˧˧":["陵"],
"nia˧˧nia˧˧":["爾爾"],
"nia˨˦":["娘"],
"niu˥˧":["兩","扭"],
"niu˥˧sĩũ˥˧":["兩想"],
"niu˧˧":["讓","量"],
"niu˨˦":["娘","糧","量","梁"],
"niu˨˦a˥˧":["娘仔"],
"niu˨˦niu˨˦":["娘娘"],
"niu˨˦sũã˨˩":["涼傘"],
"niu˨˦tse˨˩":["量債"],
"niʔ˨":["𥍉","呢"],
"niʔ˨a˥˧":["𥍉仔"],
"ni˥˥":["拈"],
"ni˥˧":["耳","染"],
"ni˧˧":["爾"],
"ni˨˦":["年","連","尼","呢","哖","泥"],
"ni˨˦kɔ˥˥am˥˥":["尼姑庵"],
"ni˨˦lau˧˧":["年老"],
"ni˨˦tsĩ˨˦":["簾簷"],
"ni˨˦tʰau˨˦":["年頭"],
"nua˥˧":["撋"],
"nua˧˧":["瀾","爛","懶","僆"],
"nua˨˦":["欄"],
"nua˨˩":["躽"],
"nńg1":["軟"],
"nŋ˥˥":["卵","兩","瓤","圇","郎","軁"],
"nŋ˥˥te˥˧":["兩短"],
"nǹg1":["軁"],
"nɔ˥˧":["腦","老"],
"nɔ˥˧dzin˨˦":["老人"],
"nɔ˧˧":["怒"],
"ok˨":["惡","屋"],
"om˥˥":["掩"],
"om˧˧":["茂"],
"oŋ˥˥ioŋ˨˦":["汪洋"],
"oŋ˥˧":["往","枉"],
"oŋ˧˧":["旺"],
"oŋ˨˦":["王"],
"oŋ˨˦ia˨˦":["王爺"],
"oʔ˨":["學","僫"],
"oʔ˨kau˨˩":["僫到"],
"o˥˥lo˥˧":["呵咾"],
"o˨˦":["蚵"],
"o˨˩":["澳"],
"o˨˩gio˨˦":["薁蕘"],
"o˨˩miau˧˧":["奧妙"],
"o˨˩un˧˧":["奧運"],
"pai˥˧":["擺","跛"],
"pai˥˧a˥˧":["擺仔"],
"pai˧˧":["敗"],
"pai˧˧siok˨":["敗俗"],
"pai˨˦":["排","牌","棑"],
"pai˨˦a˥˧":["牌仔","牌","棑仔"],
"pai˨˩":["拜"],
"pak˦":["縛","贌"],
"pak˨":["北","腹","剝","幅"],
"pak˨sin˥˥":["北新","北新（北投子"],
"pak˨tɔ˨˦":["幅圖"],
"pan˥˥":["班","斑","頒"],
"pan˥˧":["板","版","扳"],
"pan˧˧":["辦","範","扮"],
"pan˨˦":["瓶","便"],
"pat˦":["別"],
"pat˦a˥˧":["拔","菝仔"],
"pat˨":["八"],
"pat˨tat˦":["八達"],
"pau˥˥":["包","胞","鮑"],
"pau˨˦":["包"],
"paŋ˥˥":["枋","幫","崩","邦","板","封"],
"paŋ˥˥a˥˧":["枋仔"],
"paŋ˥˧":["綁"],
"paŋ˧˧":["棒"],
"paŋ˨˦":["房","縫"],
"paŋ˨˩":["放"],
"paʔ˨":["百","爸"],
"pa˥˥":["巴","吧","疤","𢼌","笆","芭"],
"pa˥˥kiat˨":["巴結"],
"pa˥˥le˨˦":["芭蕾"],
"pa˥˧":["飽","把"],
"pa˥˧bue˧˧":["飽未"],
"pa˧˧":["罷"],
"pa˨˦":["爸"],
"pa˨˩":["霸","豹","把"],
"peʔ˦":["白","帛"],
"peʔ˦a˥˧":["白仔"],
"peʔ˦dzit˦":["白日"],
"peʔ˨":["八","伯","𬦰","擘","百"],
"peʔ˨a˥˧":["伯仔"],
"peʔ˨ia˨˦":["八爺"],
"peʔ˨ke˧˧":["𬦰低"],
"peʔ˨kʰau˨˩":["八扣"],
"peʔ˨lau˧˧":["八老"],
"peʔ˨tsa˥˧":["八早"],
"peʔ˨ũã˨˩":["八晏"],
"pe˥˥":["扒"],
"pe˥˧":["把"],
"pe˧˧":["爸","耙"],
"pe˧˧bu˥˧":["爸母"],
"pe˨˦":["耙","扒","爬","杷"],
"pe˨˩":["弊","幣"],
"piak˨":["煏"],
"pian˥˥":["編","邊","扳","鞭"],
"pian˥˥ik˦":["編譯"],
"pian˥˧":["諞","匾","貶","扁"],
"pian˥˧sian˥˥":["諞仙"],
"pian˧˧":["便","辯","辨"],
"pian˧˧pŋ˥˥":["便飯"],
"pian˨˩":["變","遍"],
"piat˦":["別"],
"piau˥˥":["標"],
"piau˥˧":["表","婊"],
"piaŋ˨˩":["迸"],
"piaʔ˨":["壁"],
"pik˦":["白"],
"pik˨":["迫","逼"],
"pin˥˥":["賓"],
"pin˥˥gi˨˦kuan˥˧":["殯儀館"],
"pin˥˥hai˥˧":["濱海"],
"pin˥˥nŋ˥˥":["檳榔"],
"pin˥˧":["箅","鉼","稟"],
"pin˨˦":["頻","貧","屏","憑"],
"pin˨˦to˧˧":["貧道"],
"pin˨˩":["鬢","篦"],
"pio˥˥":["標","鏢","飆"],
"pio˥˧":["錶","表"],
"pio˧˧":["鰾"],
"pit˨":["筆","必","畢"],
"pit˨a˥˧":["筆仔"],
"pit˨lo˨˦":["伯勞"],
"piŋ˥˥":["冰","兵"],
"piŋ˥˧":["反"],
"piŋ˥˧kʰi˨˩":["反去"],
"piŋ˧˧":["並"],
"piŋ˨˦":["平","爿","朋","秤","憑"],
"piŋ˨˩":["併"],
"piʔ˨":["撆","鱉","湢","馝"],
"piʔ˨piʔ˨":["鱉鱉"],
"pi˥˥":["悲","卑","觱","碑","埤","螕"],
"pi˥˧":["比"],
"pi˥˧kau˨˩":["比較"],
"pi˧˧":["備","避","被","婢"],
"pi˨˦":["脾","枇","皮"],
"pi˨˦pe˨˦":["琵琶"],
"pi˨˩":["祕","閉","庇","泌"],
"pi˨˩hŋ˥˥":["祕方"],
"pok˨":["駁","薄","卜","暴","噗","爆"],
"poŋ˧˧":["磅","碰","蓬","鎊"],
"poŋ˨˦":["旁","房","篷"],
"poŋ˨˩":["嗙"],
"poŋ˨˩ĩã˥˧":["嗙影"],
"poʔ˨":["薄","卜","箔","駁"],
"po˥˥":["褒"],
"po˥˥le˨˦":["玻璃"],
"po˥˧":["保","寶","堡"],
"po˧˧":["暴"],
"po˨˦":["婆"],
"po˨˩":["報"],
"puan˧˧":["叛"],
"puan˨˩":["半"],
"puan˨˩gi˨˦":["半疑"],
"puan˨˩kai˥˧":["半解"],
"puan˨˩peʔ˦":["半白"],
"puat˦":["拔"],
"puat˦a˥˧":["菝仔"],
"puaʔ˦":["跋","拔"],
"puaʔ˨":["撥","缽"],
"pua˨˩":["簸"],
"pua˨˩ki˥˥":["簸箕"],
"pueʔ˦":["拔"],
"pue˥˥":["飛","杯","桮"],
"pue˥˥liŋ˨˦":["菠薐"],
"pue˥˧":["掰"],
"pue˧˧":["背","倍","培","佩","焙","狽"],
"pue˧˧gi˧˧":["背義"],
"pue˧˧tʰĩã˨˩":["背疼"],
"pue˨˦":["陪","培","賠"],
"pue˨˩":["輩","貝","褙"],
"pui˧˧":["吠"],
"pui˨˦":["肥"],
"pui˨˩":["痱"],
"pun˥˥":["分"],
"pun˥˥e˨˦":["分的"],
"pun˥˥li˥˧":["分你"],
"pun˥˧":["本","扁"],
"pun˥˧tsun˥˥":["本尊"],
"pun˧˧":["笨"],
"pun˨˦":["歕"],
"pun˨˩":["畚","糞"],
"pun˨˩ki˥˥":["奮起"],
"pun˨˩so˨˩":["糞埽"],
"put˦":["佛"],
"put˦tsɔ˥˧":["佛祖"],
"put˨":["不","柫","抔"],
"put˨biŋ˨˦":["不明"],
"put˨dzin˨˦":["不仁"],
"put˨hau˨˩":["不孝"],
"put˨kak˨":["不覺"],
"put˨piŋ˨˦":["不平"],
"put˨su˨˩":["不四"],
"put˨tat˦":["不達"],
"put˨tsʰit˨":["不七"],
"puʔ˨":["發"],
"pu˥˥":["哹"],
"pu˧˧":["婦","孵"],
"pu˨˦":["匏","垺","炰"],
"pu˨˦hia˥˥":["匏桸"],
"pu˨˩":["富"],
"pĩã˥˧":["餅","丙"],
"pĩã˥˧tiŋ˥˥":["丙丁"],
"pĩã˨˦":["平"],
"pĩã˨˩":["拚","摒"],
"pĩ˥˥":["邊","鞭"],
"pĩ˥˧":["扁"],
"pĩ˧˧":["辮"],
"pĩ˨˦":["坪"],
"pĩ˨˩":["變"],
"pĩ˨˩kuai˨˩":["變怪"],
"pńg1":["榜"],
"pŋ˥˥":["飯","楓","傍","幫"],
"pũã˥˥":["搬","般"],
"pũã˥˧":["魬"],
"pũã˧˧":["拌"],
"pũã˧˧baŋ˥˧":["拌蠓"],
"pũã˨˦":["盤"],
"pũã˨˦tsʰĩũ˨˦":["盤牆"],
"pũã˨˩":["半","絆"],
"pũã˨˩me˨˦":["半暝"],
"pɔ˥˥":["埔","晡","埠"],
"pɔ˥˧":["補","脯","捕"],
"pɔ˥˧te˥˧":["補短"],
"pɔ˥˧tʰau˨˦":["斧頭"],
"pɔ˧˧":["步","部","哺"],
"pɔ˨˦":["捗","酺","裒","蒲","痡"],
"pɔ˨˩":["布","播","佈","怖"],
"pɔ˨˩bue˥˧":["布尾"],
"pʰai˨˩":["派"],
"pʰak˦":["曝"],
"pʰak˦baŋ˧˧":["曝網"],
"pʰak˨":["覆","仆"],
"pʰan˥˥":["攀"],
"pʰan˨˩":["盼","襻"],
"pʰauʔ˦":["雹"],
"pʰau˥˥":["拋"],
"pʰau˥˧":["跑"],
"pʰau˨˦":["跑"],
"pʰau˨˩":["炮","泡"],
"pʰaŋ˥˥":["芳","蜂"],
"pʰaŋ˥˧":["紡","麭"],
"pʰaŋ˧˧":["縫"],
"pʰaŋ˨˦":["捀","帆","篷"],
"pʰaʔ˨":["拍"],
"pʰa˥˥":["拋","脬","葩"],
"pʰa˥˥pʰa˥˥":["拋拋"],
"pʰa˥˥tsʰia˥˥lin˥˥":["拋捙輪"],
"pʰa˧˧":["疱"],
"pʰa˨˩":["怕"],
"pʰe˥˧pʰe˥˧":["襞襞"],
"pʰe˧˧":["稗"],
"pʰe˨˩":["帕"],
"pʰiak˦":["擗"],
"pʰiak˦a˥˧":["擗仔"],
"pʰian˥˥":["偏"],
"pʰian˥˥hok˨":["篇幅"],
"pʰian˨˩":["騙","片","遍"],
"pʰian˨˩li˥˧":["騙你"],
"pʰian˨˩sũã˥˥pʰĩã˨˦tsiŋ˨˩":["片山坪種"],
"pʰiat˨":["撇","𥐵"],
"pʰiau˥˥":["標","飄","漂"],
"pʰiau˨˦":["嫖"],
"pʰiaŋ˧˧":["龐"],
"pʰiaʔ˦":["癖","甓"],
"pʰiaʔ˨":["癖","僻"],
"pʰik˨":["魄","拍","碧","辟","伯"],
"pʰik˨lik˦":["霹靂"],
"pʰin˥˥pʰoŋ˥˧":["乒乓"],
"pʰin˥˧":["品","𥰔"],
"pʰin˨˦":["蹁"],
"pʰio˨˦":["薸"],
"pʰio˨˩":["票"],
"pʰio˨˩peʔ˦":["漂白"],
"pʰit˨":["匹"],
"pʰit˨ma˥˧":["匹馬"],
"pʰiŋ˥˥":["拼"],
"pʰiŋ˧˧":["並"],
"pʰiŋ˨˦":["評"],
"pʰiŋ˨˦se˥˥":["硼砂"],
"pʰiŋ˨˩":["聘"],
"pʰiʔ˦pʰiʔ˦":["咇咇"],
"pʰiʔ˦pʰok˨":["咇噗"],
"pʰiʔ˨":["躄"],
"pʰi˥˥":["披","砒"],
"pʰi˥˧":["疕","鄙"],
"pʰi˨˦":["皮","脾","疲"],
"pʰi˨˩":["譬"],
"pʰok˨":["博","噗"],
"pʰok˨a˥˧":["泡仔","噗仔"],
"pʰoŋ˥˥pʰai˨˩":["豐沛"],
"pʰoŋ˥˧":["捧"],
"pʰoŋ˧˧":["蓬","滂"],
"pʰoŋ˨˦":["蘋"],
"pʰoŋ˨˦koŋ˥˥":["膀胱"],
"pʰoŋ˨˩":["膨","碰","椪"],
"pʰoʔ˨":["粕","樸"],
"pʰoʔ˨a˥˧":["粕仔"],
"pʰo˥˥":["波","坡","泡"],
"pʰo˥˧liok˨":["頗略"],
"pʰo˧˧":["抱","部"],
"pʰo˨˩":["破","泡"],
"pʰuan˨˦":["盤"],
"pʰuaʔ˦":["袚"],
"pʰuaʔ˨":["潑"],
"pʰua˨˩":["破"],
"pʰua˨˩bi˧˧":["破味"],
"pʰua˨˩pẽ˧˧":["破病"],
"pʰueʔ˦":["沫"],
"pʰue˥˥":["批","坯","胚"],
"pʰue˥˧":["䫌"],
"pʰue˧˧":["被"],
"pʰue˨˦":["皮"],
"pʰue˨˩":["配","杮"],
"pʰui˨˩":["屁","呸"],
"pʰun˥˥":["潘","奔"],
"pʰun˥˧":["翸"],
"pʰun˨˦":["盆"],
"pʰun˨˩":["噴"],
"pʰut˦pʰut˦":["𧿳𧿳"],
"pʰut˨":["刜"],
"pʰut˨pʰut˨":["怫怫"],
"pʰuʔ˦":["浡"],
"pʰu˥˧":["殕"],
"pʰu˧˧":["浡"],
"pʰu˨˦":["浮","烰"],
"pʰu˨˦to˨˦":["葡萄"],
"pʰãĩ˥˧":["歹"],
"pʰãĩ˥˧gua˥˧tsʰoŋ˨˩sĩãʔ˨":["歹我創啥"],
"pʰãĩ˥˧se˨˩":["歹勢"],
"pʰãĩ˥˧tʰĩã˥˥":["歹聽"],
"pʰãĩ˧˧":["揹"],
"pʰã˧˧":["奅"],
"pʰã˨˩":["冇"],
"pʰã˨˩tsʰiu˥˧":["冇手"],
"pʰĩã˥˥":["抨"],
"pʰĩã˥˥ki˥˥":["骿支"],
"pʰĩã˥˥liau˨˦":["骿條"],
"pʰĩã˥˧":["鉼"],
"pʰĩã˨˦":["坪"],
"pʰĩ˥˥":["篇","偏"],
"pʰĩ˧˧":["鼻"],
"pʰĩ˧˧a˥˧":["鼻仔","鼻"],
"pʰĩ˧˧liam˨˦":["鼻臁"],
"pʰĩ˨˩":["片"],
"pʰŋʔ˨":["嗙"],
"pʰũã˧˧":["伴"],
"pʰũã˨˩":["判","販"],
"pʰɔ˥˥":["鋪","麩"],
"pʰɔ˥˧":["譜","普"],
"pʰɔ˧˧":["簿","廍"],
"pʰɔ˧˧a˥˧":["簿仔"],
"pʰɔ˨˦":["扶"],
"pʰɔ˨˦sat˨":["菩薩"],
"pʰɔ˨˦tʰe˨˦":["菩提"],
"pʰɔ˨˦tʰã˥˧":["扶挺"],
"pʰɔ˨˩":["舖"],
"pʰẽ˥˥":["伻"],
"pʰẽ˧˧pʰẽ˧˧":["怦怦"],
"pʰẽ˨˦ɔ˨˦":["澎湖"],
"pẽ˥˥":["繃"],
"pẽ˧˧":["病"],
"pẽ˧˧tʰĩã˨˩":["病疼"],
"pẽ˧˧ĩ˧˧":["醫院","病院"],
"pẽ˨˦":["平","棚","坪"],
"pẽ˨˩":["柄"],
"sai˥˥":["師","獅","西","揌","犀"],
"sai˥˥a˥˧":["師仔","獅仔"],
"sai˥˥hu˧˧":["師傅"],
"sai˥˥koŋ˥˥":["司公"],
"sai˥˥kʰia˥˥":["私奇"],
"sai˥˥nai˥˥":["司奶"],
"sai˥˥tsam˧˧":["西站"],
"sai˥˥uai˥˥":["西歪"],
"sai˥˧":["屎","使","駛"],
"sai˥˧be˥˧":["駛馬"],
"sai˥˧pue˥˥":["屎桮"],
"sai˧˧":["侍","姒"],
"sai˨˦":["饞"],
"sai˨˩":["賽","婿","使"],
"sak˨":["捒"],
"sam˥˥":["三","杉"],
"sam˥˥pan˥˧":["舢舨"],
"sam˥˧":["糝"],
"sam˥˧tso˨˩":["糝做"],
"sam˨˩":["毿","三","鬖","搧"],
"san˥˥":["山","刪"],
"san˥˧":["產","瘦","散"],
"san˨˩":["散"],
"sap˨":["雪","霎","屑"],
"sat˨":["殺","蝨","虱","塞"],
"sau˥˥":["梢"],
"sau˨˩":["掃","嗽"],
"saŋ˥˥":["鬆"],
"saŋ˥˥saŋ˥˥":["鬆鬆"],
"saŋ˥˧":["桑","聳"],
"saŋ˨˩":["送"],
"saʔ˦":["煠"],
"sa˥˥":["捎","柵"],
"sa˥˥bui˥˥":["沙微"],
"sa˥˥la˥˧":["沙拉"],
"sa˥˥loŋ˥˥pa˥˥suʔ˨":["沙龍巴斯"],
"sa˥˥puʔ˨luʔ˨":["沙不魯"],
"sa˥˥te˥˥":["沙茶"],
"sa˨˩":["嗄"],
"seʔ˦":["踅"],
"seʔ˦kak˨":["踅角"],
"seʔ˨":["楔","雪"],
"se˥˥":["西","紗","梳","疏","蔬","沙"],
"se˥˥lɔ˧˧":["西路"],
"se˥˧":["洗","黍"],
"se˥˧tsʰiu˥˧":["洗手"],
"se˨˦":["垂"],
"se˨˩":["勢","細","世","誓","洒"],
"se˨˩dzi˧˧":["細膩"],
"se˨˩ki˥˧":["世紀"],
"se˨˩sueʔ˨":["細說"],
"se˨˩su˧˧":["世事"],
"siak˨":["摔"],
"siak˨siak˨":["鑠鑠"],
"siam˥˥":["䀐"],
"siam˥˧":["閃"],
"siam˨˦":["尋"],
"siam˨˩":["滲"],
"sian˥˥":["仙","先","鉎","鮮","身"],
"sian˥˥a˥˧":["仙仔"],
"sian˥˥tan˥˥":["仙丹"],
"sian˥˧":["癬","仙"],
"sian˧˧":["善","𤺪","鱔","腎","羨"],
"sian˧˧tʰaŋ˨˦":["蟮蟲"],
"sian˨˦":["禪","蟬","涎"],
"sian˨˩":["搧","煽"],
"siap˦":["涉","洩"],
"siap˨":["卌","屧","澀"],
"siat˨":["設"],
"siau!1":["痟！"],
"siau˥˥":["消","銷","宵","簫","霄","逍","痟"],
"siau˥˧":["痟","小","少"],
"siau˧˧":["紹"],
"siau˨˦":["潲"],
"siau˨˦ue˧˧":["潲話"],
"siau˨˩":["數","少","笑","肖"],
"siau˨˩lian˨˦":["少年"],
"siaŋ˥˥":["雙"],
"siaŋ˧˧":["𫝛"],
"siaŋ˧˧tsʰe˥˥":["上尺"],
"siaŋ˧˧un˨˦":["𫝛勻"],
"siaŋ˨˩":["摔"],
"siaʔ˦":["杓","夕"],
"siaʔ˦liu˨˦":["石榴"],
"siaʔ˦liu˨˦pan˥˥":["石榴"],
"siaʔ˨":["削","錫"],
"sia˥˥":["賒"],
"sia˥˧":["寫","捨"],
"sia˥˧pʰue˥˥":["寫批"],
"sia˥˧si˨˩":["捨施"],
"sia˧˧":["謝","社","射","麝"],
"sia˧˧kau˨˩":["社教"],
"sia˧˧kʰu˥˥":["社區"],
"sia˨˦":["邪","斜"],
"sia˨˩":["卸","赦","舍","瀉"],
"sia˨˩tsiŋ˨˩":["卸眾"],
"sik˦":["席","熟","汐","石","碩","夕"],
"sik˦sai˧˧":["熟似"],
"sik˨":["色","式","室","識","適","釋","索","析","息","嗇","飾","惜"],
"sim˥˥":["心","參","森"],
"sim˥˥bun˧˧":["心悶"],
"sim˥˧":["審"],
"sim˧˧":["甚","愖"],
"sim˨˩":["㽎"],
"sim˨˩sim˨˩":["㽎㽎"],
"sin˥˥":["身","新","辛","薪","申","伸","紳"],
"sin˥˥koŋ˥˥":["新光"],
"sin˥˥siŋ˥˥":["新生"],
"sin˥˥tsam˧˧":["新站"],
"sin˧˧":["腎","慎"],
"sin˨˦":["神","辰","蠅","臣","承"],
"sin˨˦biŋ˨˦":["神明"],
"sin˨˩":["信","訊","囟","迅"],
"sin˨˩li˥˧":["信你","信女"],
"sioh!1tsit˨pai˥˧e˨˦":["惜！這擺的"],
"siok˨":["俗","屬","續","贖","肅","宿","淑"],
"sioŋ˥˥":["傷","商","相","襄"],
"sioŋ˥˥kʰuan˥˥":["商圈"],
"sioŋ˥˧":["想","賞","尚","上"],
"sioŋ˧˧":["上","象","像","剩","誦"],
"sioŋ˧˧tse˧˧":["上濟"],
"sioŋ˨˦":["常","詳","松","償","祥"],
"sioŋ˨˦ŋɔ˨˦":["嫦娥"],
"sioŋ˨˩":["相"],
"sioʔ˨":["惜","液"],
"sio˥˥":["相","燒"],
"sio˥˥ka˧˧":["相咬"],
"sio˥˥kʰeʔ˨":["相𤲍"],
"sio˥˥kʰũã˨˩":["相看"],
"sio˥˥tsẽ˥˥":["相爭"],
"sio˥˥tʰai˨˦":["相刣"],
"sio˥˧":["小"],
"sio˥˧ki˧˧tan˨˩":["小巨蛋"],
"sio˥˧kʰau˥˧":["小口"],
"sio˥˧sĩã˨˦":["小城"],
"sio˨˦sio˨˦":["荍荍"],
"sip˦":["習","十","襲","拾"],
"sip˦bi˥˧":["十美"],
"sip˨":["溼"],
"sit˦":["實","食","翼","殖"],
"sit˦but˦":["植物"],
"sit˨":["失","穡","息","蝕","熄"],
"sit˨tǹg1":["失頓"],
"siu˥˥":["收","修"],
"siu˥˧":["首","守","手"],
"siu˧˧":["壽","受","岫","授","售"],
"siu˨˦":["泅","仇","囚","酬"],
"siu˨˩":["秀","繡","獸","袖","鞘","宿"],
"siŋ˥˥":["生","先","升","聲","牲","星","昇","芟"],
"siŋ˥˥siŋ˥˥":["猩猩"],
"siŋ˥˧":["省","醒"],
"siŋ˧˧":["盛","倖","剩"],
"siŋ˧˧kĩã˥˧":["倖囝"],
"siŋ˧˧ti˥˥":["倖豬"],
"siŋ˨˦":["成","承","誠","城"],
"siŋ˨˦hoŋ˨˦":["城隍"],
"siŋ˨˩":["性","聖","勝","姓"],
"siŋ˨˩tian˧˧":["聖殿"],
"siʔ˦":["蝕"],
"siʔ˦sut˦":["窸窣"],
"siʔ˨":["爍"],
"siʔ˨sut˨":["蟋蟀"],
"si˥˥":["絲","詩","司","施","屍","噓","私"],
"si˥˥kue˥˥":["西瓜"],
"si˥˥si˥˥sut˦sut˦":["窸窸窣窣"],
"si˥˧":["死","始"],
"si˥˧uaʔ˦":["死活"],
"si˧˧":["是","視","示","序","寺","氏"],
"si˧˧gu˨˦":["是牛"],
"si˧˧sua˧˧":["窸倏"],
"si˧˧tseʔ˨":["是節"],
"si˨˦":["時","匙","辭"],
"si˨˦a˥˧":["時仔","匙仔"],
"si˨˦kan˥˥":["時間"],
"si˨˦tai˧˧":["時代"],
"si˨˩":["四","世","勢"],
"si˨˩kʰau˨˩":["四扣"],
"sok˨":["速","束","縮","塑","宿"],
"sok˨a˥˧":["束仔"],
"sok˨ka˥˥":["塑膠"],
"som˥˥som˥˥":["參參"],
"soŋ˥˥":["喪","鬆","霜"],
"soŋ˥˧":["爽"],
"soŋ˥˧kʰuai˨˩":["爽快"],
"soŋ˨˦":["倯"],
"soŋ˨˩":["宋","喪"],
"soʔ˨":["索"],
"so˥˥":["挲","騷","嗦","鮻"],
"so˥˧":["嫂","鎖"],
"so˨˦":["趖"],
"so˨˦tsʰiu˥˧":["趖手"],
"so˨˩":["燥","埽"],
"suan˥˥":["宣","旋","酸"],
"suan˥˥ɔ˨˦":["珊瑚"],
"suan˥˧":["選"],
"suan˧˧":["璇","漩","訕"],
"suan˨˦":["旋"],
"suan˨˩":["蒜","算"],
"suat˨":["說","雪","鱈","刷"],
"suaʔ˨":["煞","撒"],
"sua˥˥":["沙","砂","痧","鯊"],
"sua˥˧":["徙"],
"sua˥˧tsai˥˥":["徙栽"],
"sua˨˩":["紲"],
"sueʔ˨":["說"],
"sue˥˥":["衰"],
"sue˨˦":["垂"],
"sue˨˩":["稅","說","歲","涗"],
"sui˥˥":["雖","繐","祟","𦉎","嗺","蓑"],
"sui˥˧":["媠","水"],
"sui˧˧":["穗","瑞","遂"],
"sui˨˦":["隨","垂","椹"],
"sui˨˦laŋ˨˦tsʰai˧˧":["隨人祀"],
"sun˥˥":["孫"],
"sun˥˧":["筍","損","榫"],
"sun˥˧sun˥˧":["恂恂"],
"sun˧˧":["順","循"],
"sun˨˦":["巡","純","詢","旬","循","馴"],
"sun˨˩":["瞬"],
"sut˦":["術","述"],
"sut˨":["屑","捽","戌"],
"suʔ˨":["欶"],
"su˥˥":["師","輸","書","私","思","司","需","軀","須","斯"],
"su˥˥toŋ˥˥":["斯當"],
"su˥˧":["使","署","史","暑","死","駛"],
"su˧˧":["事","士","序","仕","嗣","敘","似","緒","侍","嶼","祀"],
"su˧˧siŋ˥˧":["事省"],
"su˨˦":["詞","辭","祠","殊"],
"su˨˩":["四","思","賜","肆","恕"],
"sãʔ˨":["煞","喢"],
"sã˥˥":["三","衫","相"],
"sĩã˥˥":["聲"],
"sĩã˥˥ue˧˧":["聲話"],
"sĩã˥˧":["啥"],
"sĩã˧˧":["𣛮"],
"sĩã˨˦":["城","唌","成"],
"sĩã˨˩":["聖"],
"sĩũ˥˥":["傷","箱","廂"],
"sĩũ˥˥si˥˥":["相思"],
"sĩũ˥˧":["賞","鯗"],
"sĩũ˧˧":["想"],
"sĩũ˧˧beʔ˨tsiaʔ˦hit˨lo˧˧sia˨˩ioʔ˨":["想欲食彼號瀉藥"],
"sĩũ˧˧pue˥˥":["象桮"],
"sĩũ˧˧sai˥˥":["想西"],
"sĩũ˨˦":["𣻸"],
"sĩũ˨˩":["相"],
"sĩ˥˥":["生"],
"sĩ˧˧":["豉"],
"sĩ˨˩":["扇"],
"sńg1":["損","耍"],
"sŋ˥˥":["酸","霜","痠","床","桑","栓"],
"sũãĩ˧˧":["檨"],
"sũã˥˥":["山"],
"sũã˥˥a˥˧":["山"],
"sũã˥˥koŋ˥˥":["山公"],
"sũã˥˥ma˥˧":["山媽"],
"sũã˥˧":["散"],
"sũã˨˩":["線","散","傘"],
"sũã˨˩kʰi˨˩":["散去"],
"sũã˨˩tʰeʔ˦":["散宅"],
"sǹg1":["算","繏"],
"sǹg1hun˥˥":["算分"],
"sɔ˥˥":["酥","疏","蘇","甦","穌","搜"],
"sɔ˥˧":["所"],
"sɔ˥˧tsi˥˧":["所指"],
"sɔ˨˩":["數","素","訴","疏","溯"],
"sẽ˥˥":["生"],
"sẽ˥˥sĩũ˨˩":["生相"],
"sẽ˨˩":["性","姓"],
"tai˥˥":["呆","秮"],
"tai˥˧":["滓"],
"tai˧˧":["大","代","貸","𩸙","舵"],
"tai˧˧a˥˧":["𩸙仔"],
"tai˧˧dzin˨˦":["大人"],
"tai˧˧gi˧˧":["大義"],
"tai˧˧hak˦":["大學"],
"tai˧˧sia˧˧":["代謝"],
"tai˧˧te˨˩":["大帝"],
"tai˧˧tsi˨˩":["代誌"],
"tai˨˦":["臺","台","𧉟","埋","檯"],
"tai˨˩":["帶","代"],
"tak˦":["逐","獨"],
"tak˨":["觸"],
"tam˥˥":["擔","啖"],
"tam˥˧":["膽"],
"tam˧˧":["淡","啖"],
"tam˨˦":["談","澹"],
"tam˨˩":["頕"],
"tan˥˥":["丹","單","癉"],
"tan˥˧":["等"],
"tan˧˧":["但"],
"tan˨˦":["霆","陳"],
"tan˨˦ka˥˥":["陳家"],
"tan˨˦sã˥˥":["陳三"],
"tan˨˩":["誕","擲","旦","蛋"],
"tan˨˩sak˨":["擲捒"],
"tap˦":["踏"],
"tap˦tap˦":["沓沓"],
"tap˦tiʔ˨":["沓滴"],
"tap˨":["答"],
"tat˦":["值","達","笛"],
"tauʔ˦":["沓"],
"tauʔ˦tauʔ˦":["沓沓"],
"tau˥˥":["兜","掜"],
"tau˥˧":["斗","篤"],
"tau˥˧te˥˧":["斗底"],
"tau˧˧":["豆","脰","讀"],
"tau˧˧a˥˧":["豆仔"],
"tau˨˦":["投"],
"tau˨˦a˥˧":["骰仔"],
"tau˨˩":["鬥","晝","到","罩"],
"taŋ˥˥":["冬","東","當"],
"taŋ˥˥kue˥˥":["冬瓜"],
"taŋ˥˥o˥˥":["苳蒿"],
"taŋ˥˥taŋ˥˥":["噹噹"],
"taŋ˥˧":["董"],
"taŋ˥˧hĩãʔ˨":["懂嚇"],
"taŋ˧˧":["重","動"],
"taŋ˧˧tsʰiu˥˧":["動手","重手"],
"taŋ˨˦":["銅","筒","童","同","胴","桐"],
"taŋ˨˦e˨˦":["筒的"],
"taŋ˨˩":["當","凍","㨂"],
"taŋ˨˩sŋ˥˥":["凍霜"],
"taʔ˦":["踏"],
"taʔ˦hɔ˧˧":["踏戶"],
"taʔ˨":["搭","貼","答"],
"ta˥˥":["焦","大","礁"],
"ta˥˥ua˨˦":["奈何"],
"ta˥˧ma˥˧":["打馬"],
"ta˨˩":["罩"],
"teʔ˨":["咧","硩"],
"teʔ˨teʔ˨":["嗲嗲"],
"teʔ˨tsʰut˨":["咧出"],
"te˥˥":["炱"],
"te˥˧":["底","短","貯"],
"te˥˧mia˧˧":["短命"],
"te˧˧":["地","袋","第","弟","代","遞","苧"],
"te˧˧dzi˧˧haŋ˨˦ha˧˧":["第二航廈"],
"te˧˧it˨haŋ˨˦ha˧˧":["第一航廈"],
"te˧˧luan˧˧":["地亂"],
"te˧˧to˧˧":["地道"],
"te˨˦":["茶","題","蹄"],
"te˨˩":["帝","塊","地","締","渧"],
"te˨˩tua˧˧":["帝大"],
"thǹg1":["褪","燙"],
"thǹg1thǹg1":["燙燙"],
"tiak˦":["擉"],
"tiak˦sǹg1":["擉算"],
"tiam˥˥":["砧"],
"tiam˥˧":["點"],
"tiam˥˧a˥˧":["點仔"],
"tiam˥˧hiat˦":["點穴"],
"tiam˧˧":["恬","墊"],
"tiam˧˧tsiŋ˧˧":["恬靜"],
"tiam˨˩":["店","踮"],
"tian˥˥":["顛","癲"],
"tian˥˧":["展","典"],
"tian˧˧":["電","佃","殿"],
"tian˧˧ue˧˧":["電話"],
"tian˨˦":["田"],
"tiap˦":["碟","揲","諜"],
"tiap˨":["霎"],
"tiat˦":["秩"],
"tiat˨":["哲"],
"tiau˥˥":["刁","雕","調","貂","潮"],
"tiau˥˧":["佻"],
"tiau˧˧":["調","掉","兆"],
"tiau˨˦":["條","調","牢","朝","潮"],
"tiau˨˦ki˥˥":["牢枝"],
"tiau˨˩":["吊","召","調"],
"tiaʔ˦":["糴"],
"tiaʔ˨":["摘","的"],
"tiaʔ˨sẽ˨˩":["摘姓"],
"tia˥˥":["爹"],
"tik˦":["特","敵","擇","的"],
"tik˨":["竹","德","得","的"],
"tik˨i˥˧":["得已"],
"tim˧˧":["燖","朕"],
"tim˨˦":["沉"],
"tim˨˩":["掂","抌"],
"tin˥˥":["珍","津"],
"tin˥˧":["振"],
"tin˧˧":["陣"],
"tin˧˧tin˧˧":["陣陣"],
"tin˨˦":["藤","陳","塵","籐"],
"tin˨˩":["鎮"],
"tiok˨":["築"],
"tioŋ˥˥":["中","忠","張"],
"tioŋ˥˥sim˥˥":["中心"],
"tioŋ˥˧":["長"],
"tioŋ˧˧":["重","丈","仗"],
"tioŋ˨˦":["重","長","腸"],
"tioŋ˨˩":["中","脹","漲"],
"tioʔ˨":["著","擢"],
"tioʔ˨bua˨˦":["著磨"],
"tioʔ˨ioʔ˨":["著藥"],
"tioʔ˨kʰũã˨˩":["著看"],
"tioʔ˨tsiaʔ˦":["著食"],
"tioʔ˨tsʰia˥˥":["著車"],
"tioʔ˨tsʰĩã˨˦":["著晟"],
"tioʔ˨tsʰũã˨˩":["著閂"],
"tioʔ˨tʰan˨˩":["著趁"],
"tioʔ˨tʰua˥˥":["著拖"],
"tio˧˧":["癜"],
"tio˨˦":["趒","潮"],
"tio˨˩":["釣"],
"tit˦":["直","值","姪"],
"tit˦tɔ˧˧":["直肚"],
"tit˨":["得"],
"tiuʔ˨":["搐"],
"tiu˥˥":["丟"],
"tiu˧˧":["稻"],
"tiu˨˦":["籌","綢"],
"tiu˨˦tu˨˦":["躊躇"],
"tiŋ˥˥":["燈","釘","徵","丁","登","叮","疔","町"],
"tiŋ˥˧":["頂","等","戥"],
"tiŋ˧˧":["定","訂","𠕇","橂","鄭"],
"tiŋ˧˧koŋ˥˥":["鄧公"],
"tiŋ˧˧tauʔ˨":["𠕇篤"],
"tiŋ˨˦":["程","重","亭","庭","廷","澄"],
"tiŋ˨˦pɔ˥˥":["重"],
"tiŋ˨˩":["釘","中","叮"],
"tiʔ˦":["挃"],
"tiʔ˦a˥˧":["碟仔"],
"tiʔ˨":["滴"],
"tiʔ˨tiʔ˨":["滴滴"],
"ti˥˥":["豬","知","呧"],
"ti˥˥a˥˧":["豬仔"],
"ti˥˥gu˨˦siŋ˨˩":["知魚性"],
"ti˥˥tu˥˥":["蜘蛛"],
"ti˥˧":["抵","底"],
"ti˧˧":["佇","治","弟","箸","底","痔","稚","地","緻"],
"ti˨˦":["池","持","遲","鋤","苔","除"],
"ti˨˩":["致","智","置","蒂","戴","緻"],
"tok˨":["毒","獨","督","啄","剁","㧻"],
"tok˨tok˨":["篤篤"],
"tom˨˦":["丼"],
"tom˨˦tsit˦sĩã˥˥to˧˧":["丼一聲就"],
"toŋ˥˥":["當","東"],
"toŋ˥˥dzian˨˦":["當然"],
"toŋ˥˧":["黨","檔","董"],
"toŋ˧˧":["動","洞","撞","蕩","盪"],
"toŋ˧˧a˥˧":["硐"],
"toŋ˨˦":["同","堂","童","桐","唐","棠","幢"],
"toŋ˨˩":["擋","當","凍","侗","噸","棟"],
"toʔ˨":["桌","著","佗","擇"],
"to˥˥":["刀","多","都"],
"to˥˥kui˥˧":["刀鬼"],
"to˥˥sɔ˨˩":["多數"],
"to˥˧":["倒","佗","島","禱"],
"to˥˧a˥˧":["倒仔"],
"to˧˧":["就","道","導","盜","蹈"],
"to˧˧kʰo˥˧kue!3":["就考過！"],
"to˨˦":["逃","淘","跎","鴕","桃"],
"to˨˩":["倒","到"],
"tsai˥˥":["知","災","栽","齋"],
"tsai˥˥tau˨˩":["知晝"],
"tsai˧˧":["在"],
"tsai˧˧tsai˧˧":["在在"],
"tsai˨˦":["才","財","材","臍"],
"tsai˨˩":["載","再","哉"],
"tsak˦":["嗾"],
"tsak˨":["齪"],
"tsam˥˥":["沾"],
"tsam˥˧":["嶄"],
"tsam˧˧":["站","鏨"],
"tsam˨˩":["蹔"],
"tsan˥˥":["罾","齻"],
"tsan˥˧":["讚"],
"tsan˧˧":["贊"],
"tsan˨˦":["層","殘"],
"tsan˨˩":["層","贊","讚","棧"],
"tsan˨˩be˧˧":["纘袂"],
"tsap˦":["十","雜","咂"],
"tsap˦sik˨":["十色"],
"tsat˦":["實","賊"],
"tsat˨":["節","紮"],
"tsat˨a˥˧":["節仔"],
"tsau˥˥":["糟","㷮","沼"],
"tsau˥˥tʰat˨":["蹧躂"],
"tsau˥˧":["走"],
"tsau˥˧piʔ˨":["走鱉"],
"tsau˥˧pʰa˥˥pʰa˥˥":["走拋拋"],
"tsau˧˧":["找"],
"tsau˨˦":["巢","剿"],
"tsau˨˩":["灶","奏"],
"tsaŋ˥˥":["棕","鬃","鯮","㨑"],
"tsaŋ˥˥lu˨˩":["棕鑢"],
"tsaŋ˥˧":["摠","總"],
"tsaŋ˨˦":["欉","灇"],
"tsaŋ˨˩":["粽","壯"],
"tsaʔ˦":["閘"],
"tsaʔ˨":["紮","扎"],
"tsa˥˥":["查","昨"],
"tsa˥˥bɔ˥˧":["查某"],
"tsa˥˧":["早"],
"tsa˥˧dzit˦":["早日"],
"tsa˥˧kʰi˥˧":["早起"],
"tsa˨˩":["炸","詐","榨"],
"tseʔ˦":["絕"],
"tseʔ˦tsiŋ˥˧":["絕種"],
"tseʔ˨":["節","仄"],
"tse˥˥":["這","災","劑","渣"],
"tse˥˥beʔ˨tsʰoŋ˨˩sĩãʔ˨":["這欲創啥"],
"tse˥˧":["姊"],
"tse˧˧":["濟","坐","寨"],
"tse˧˧kua˨˩":["罪過"],
"tse˨˦":["齊"],
"tse˨˩":["制","債","製","祭","際","濟","劑","晬"],
"tse˨˩hian˨˩":["制憲"],
"tshńg1":["吮"],
"tshǹg1":["串"],
"tsiam˥˥":["針","尖"],
"tsiam˥˥tsiam˥˥":["尖尖"],
"tsiam˧˧":["暫"],
"tsiam˧˧tsiam˧˧":["漸漸"],
"tsiam˨˦":["潛"],
"tsiam˨˩":["占","僭"],
"tsian˥˥":["煎"],
"tsian˥˧":["剪"],
"tsian˧˧":["賤","踐"],
"tsian˨˦":["前"],
"tsian˨˩":["戰","薦","荐"],
"tsiap˦":["捷"],
"tsiap˨":["接","汁"],
"tsiat˦":["截","捷"],
"tsiat˨":["節","折"],
"tsiau˥˥":["招","焦","蕉","昭"],
"tsiau˥˥tsiau˥˥":["昭昭"],
"tsiau˥˧":["鳥"],
"tsiau˥˧a˥˧":["鳥仔"],
"tsiau˨˦":["齊"],
"tsiau˨˩":["照"],
"tsiau˨˩kĩã˨˦":["照行"],
"tsiau˨˩lun˨˦":["照輪"],
"tsiaŋ˥˥":["彰"],
"tsiaŋ˥˥tsuan˨˦":["漳泉"],
"tsiaŋ˥˧":["長"],
"tsiaŋ˨˩":["障"],
"tsiaʔ˦":["食","炸"],
"tsiaʔ˦baʔ˨":["食肉"],
"tsiaʔ˦dzit˦":["食日"],
"tsiaʔ˦lat˦":["食栗"],
"tsiaʔ˦pŋ˥˥":["食飯"],
"tsiaʔ˦sũã˥˥":["食山"],
"tsiaʔ˦tsʰai˨˩":["食菜"],
"tsiaʔ˦tʰiʔ˨":["食鐵"],
"tsiaʔ˨":["才","隻","遮","跡","睫","脊"],
"tsiaʔ˨pŋ˥˥loŋ˥˧bo˨˦":["食飯攏無"],
"tsia˥˥":["遮"],
"tsia˥˧":["者","姐"],
"tsia˥˧boŋ˨˦":["者亡"],
"tsia˥˧tsun˨˦":["者存"],
"tsia˨˩":["蔗","炙"],
"tsia˨˩kɔ˥˥":["鷓鴣"],
"tsik˦":["籍"],
"tsik˦bok˨":["寂寞"],
"tsik˨":["叔","積","責","燭","則","績","蹟","即","擠","跡"],
"tsim˥˥":["唚"],
"tsim˥˥tsiok˨":["斟酌"],
"tsim˥˧":["嬸","枕"],
"tsim˨˦":["蟳"],
"tsim˨˩":["浸"],
"tsin˥˥":["真","升","甄","蓁"],
"tsin˥˥ho˥˧":["真好"],
"tsin˥˥iu˨˩":["真幼"],
"tsin˥˥kũã˨˦":["真寒"],
"tsin˥˥kɔ˥˧tsui˥˥":["真古錐"],
"tsin˥˥lioŋ˧˧":["真冗"],
"tsin˥˥pa˥˧":["真飽"],
"tsin˥˥tsʰiŋ˥˥tsʰo˥˧":["真清楚"],
"tsin˥˥tua˧˧":["真大"],
"tsin˥˧":["診","振","賑","拯","疹"],
"tsin˧˧":["盡"],
"tsin˧˧huan˥˥":["盡歡"],
"tsin˨˦":["繩","秦"],
"tsin˨˩":["進","震"],
"tsiok˨":["足","祝","爵","囑","燭"],
"tsioŋ˥˥":["終","章","將","彰","障"],
"tsioŋ˥˧":["獎","種","掌"],
"tsioŋ˧˧":["狀"],
"tsioŋ˨˦":["從"],
"tsioŋ˨˩":["眾","將","障"],
"tsioʔ˨":["石","借","襀"],
"tsioʔ˨tã˥˧":["借膽"],
"tsio˥˥":["招","椒","蕉"],
"tsio˥˧":["少"],
"tsio˥˧khueh!1":["少缺！"],
"tsio˨˩":["照","醮"],
"tsip˦":["集","輯","𠯗","緝"],
"tsip˨":["執"],
"tsit˦":["一"],
"tsit˦dzun˧˧":["一閏"],
"tsit˦e!7":["一下！"],
"tsit˦e˧˧":["一下"],
"tsit˦e˨˦":["一个"],
"tsit˦hioʔ˨":["一葉"],
"tsit˦kin˥˥":["一斤"],
"tsit˦ku˨˩":["一句"],
"tsit˦siok˨":["一俗"],
"tsit˦si˨˦kan˥˥":["一時間"],
"tsit˦tau˥˧":["一斗"],
"tsit˦tsioʔ˨":["一石"],
"tsit˨":["這","質","職","織","鯽","脊"],
"tsit˨tɔ˨˦":["這途"],
"tsiuʔ˨tsiuʔ˨":["喌喌"],
"tsiu˥˥":["睭","周","洲","週","州"],
"tsiu˥˥a˥˧":["洲"],
"tsiu˥˧":["酒","守"],
"tsiu˧˧":["就"],
"tsiu˨˩":["咒","蛀"],
"tsiŋ˥˥":["精","鐘","爭","舂","增","偵","鍾","征","晶","菁"],
"tsiŋ˥˥sẽ˥˥":["精牲"],
"tsiŋ˥˧":["整","種","指","腫"],
"tsiŋ˥˧kaʔ˨":["指甲"],
"tsiŋ˧˧":["靜","淨","贈","靖"],
"tsiŋ˨˦":["情","前","曾","從"],
"tsiŋ˨˩":["政","正","證","症","眾","種"],
"tsiʔ˦":["舌","折"],
"tsiʔ˨":["摺","接"],
"tsi˥˥":["支","之","芝","脂","膣"],
"tsi˥˥paʔ˨":["之百"],
"tsi˥˥pʰio˨˩":["支票"],
"tsi˥˥sim˥˥":["之心"],
"tsi˥˥tsai˨˦":["之財"],
"tsi˥˥tsu˥˧":["之主"],
"tsi˥˥tsʰẽ˥˥":["之星"],
"tsi˥˥tɔ˨˦":["之徒"],
"tsi˥˧":["子","止","指","只","姊","紫","址","旨","黹"],
"tsi˥˧a˥˧":["姊仔","止仔","子仔"],
"tsi˥˧mue˧˧":["姊妹"],
"tsi˥˧tŋ˥˥":["指腸"],
"tsi˧˧":["巳"],
"tsi˨˦":["薯","糍","薺"],
"tsi˨˩":["志","至","誌","薦"],
"tsok˨":["作","族"],
"tsoŋ˥˥":["裝","宗","莊","蹤","妝","綜","贓"],
"tsoŋ˥˧":["總"],
"tsoŋ˥˧tsam˧˧":["總站"],
"tsoŋ˧˧":["狀","臟","藏"],
"tsoŋ˨˦":["傱","藏","崇"],
"tsoŋ˨˦tik˨":["崇德"],
"tsoŋ˨˩":["壯","葬"],
"tsoʔ˨":["作","昨"],
"tso˥˥":["遭","慒"],
"tso˥˥tso˥˥":["慒慒"],
"tso˥˧":["棗","左"],
"tso˧˧":["造","座","坐","嘈","皂"],
"tso˨˦":["槽"],
"tso˨˩":["做"],
"tso˨˩be˧˧tsʰut˨lai!5":["做袂出來！"],
"tsuan˥˥":["專"],
"tsuan˥˧":["轉","賺"],
"tsuan˥˧i˨˩":["轉意"],
"tsuan˧˧":["轉","撰"],
"tsuan˨˦":["全","泉"],
"tsuan˨˦su˥˥":["全書"],
"tsuat˦":["絕"],
"tsuat˨":["泏"],
"tsuaʔ˦":["縒","差"],
"tsuaʔ˨":["泏"],
"tsua˥˧":["紙"],
"tsua˥˧e˨˦":["紙的"],
"tsua˧˧":["逝","誓"],
"tsua˨˦":["蛇"],
"tsue˧˧":["罪"],
"tsue˨˩":["最"],
"tsui˥˥":["脽","錐","鵻"],
"tsui˥˧":["水"],
"tsui˥˧bue˥˧":["瑞穗"],
"tsui˥˧to!7":["水道！"],
"tsui˨˦":["𠞩","誰"],
"tsui˨˩":["醉"],
"tsun˥˥":["尊","遵"],
"tsun˥˧":["準","准","撙"],
"tsun˧˧":["陣","捘"],
"tsun˨˦":["船","存","前"],
"tsun˨˩":["圳","顫","峻"],
"tsut˦bi˥˧":["秫米"],
"tsut˦tsut˦":["秫秫"],
"tsut˨":["卒"],
"tsut˨tsut˨":["朒朒"],
"tsuʔ˨":["泏"],
"tsu˥˥":["資","珠","書","姿","滋","朱","諮","鮢"],
"tsu˥˥se˥˥":["硃砂"],
"tsu˥˧":["主","子","煮","梓"],
"tsu˥˧toŋ˧˧laʔ˨":["主動啦"],
"tsu˧˧":["自","住","苴","聚"],
"tsu˧˧siu˧˧":["自受"],
"tsu˧˧tsuan˥˥":["自專"],
"tsu˨˦":["慈","喌","磁"],
"tsu˨˩":["注","註","駐","鑄"],
"tsãĩ˥˧":["指","宰","載"],
"tsã˧˧":["㨻"],
"tsã˨˩":["乍"],
"tsĩã˥˥":["精","正"],
"tsĩã˥˥si˨˦":["正時"],
"tsĩã˥˧":["汫"],
"tsĩã˧˧":["掙"],
"tsĩã˨˦":["誠","成","情"],
"tsĩã˨˩":["正"],
"tsĩũ˥˥":["漿","樟","章"],
"tsĩũ˥˥tsi˨˦":["螿蜍"],
"tsĩũ˥˧":["掌","槳"],
"tsĩũ˧˧":["上","癢"],
"tsĩũ˧˧tsʰi˧˧":["上市"],
"tsĩũ˨˩":["醬"],
"tsĩ˥˥":["晶","櫼","精"],
"tsĩ˥˧":["茈","井"],
"tsĩ˧˧":["舐"],
"tsĩ˨˦":["錢","簷"],
"tsĩ˨˩":["箭","糋","搢"],
"tsŋ˥˥":["庄","粧","莊","磚","狀","妝","裝","旋","全"],
"tsũãĩ˧˧":["跩"],
"tsũã˥˥":["煎"],
"tsũã˥˧":["怎","盞"],
"tsũã˧˧":["濺"],
"tsũã˨˦":["泉","殘"],
"tsũã˨˩":["炸"],
"tsǹg1":["鑽"],
"tsɔ˥˥":["組","租"],
"tsɔ˥˧":["祖","阻"],
"tsɔ˧˧":["助"],
"tsʰai˥˥":["猜","差"],
"tsʰai˥˧":["彩","採","綵","采","踩"],
"tsʰai˧˧":["𫞼","祀"],
"tsʰai˨˦":["裁","才"],
"tsʰai˨˩":["菜"],
"tsʰai˨˩kaʔ˨":["菜佮"],
"tsʰak˦":["鑿"],
"tsʰam˥˥":["參","摻"],
"tsʰam˥˧":["慘"],
"tsʰam˨˩":["讖","摻"],
"tsʰan˥˥":["餐","呻"],
"tsʰan˨˦":["田","蠶","殘"],
"tsʰan˨˦tsʰan˨˦":["殘殘"],
"tsʰan˨˩lan˧˧":["燦爛"],
"tsʰap˦tsʰap˦":["㴙㴙","眨眨"],
"tsʰap˦tsʰap˦tiʔ˨":["㴙㴙滴"],
"tsʰap˨":["插"],
"tsʰap˨li˥˧":["插你"],
"tsʰap˨tsiʔ˦":["插舌"],
"tsʰat˦":["賊"],
"tsʰat˨":["察","漆","擦","檫"],
"tsʰauʔ˦tsʰauʔ˦":["嘈嘈"],
"tsʰau˥˥":["操","抄","臊","鈔"],
"tsʰau˥˥pun˥˧":["抄本"],
"tsʰau˥˧":["草"],
"tsʰau˨˩":["臭"],
"tsʰaŋ˥˥":["蔥","娼"],
"tsʰaŋ˥˧tsʰaŋ˥˧":["氅氅"],
"tsʰaŋ˨˩":["聳","藏"],
"tsʰaʔ˨":["插"],
"tsʰa˥˥":["差"],
"tsʰa˥˧":["吵","炒"],
"tsʰa˨˦":["柴","查"],
"tsʰeʔ˨":["冊","慼","嘖"],
"tsʰe˥˥":["叉","初","妻","差","尺","淒","棲"],
"tsʰe˥˥laŋ˨˦":["叉人"],
"tsʰe˥˧":["扯"],
"tsʰe˥˧kʰi˨˩":["扯去"],
"tsʰe˧˧":["坐"],
"tsʰe˧˧siau˨˩":["坐數"],
"tsʰe˨˦":["䠡"],
"tsʰe˨˩":["摖","粞","脆","𤺅","切"],
"tsʰiak˦":["嚓"],
"tsʰiak˦tsʰiak˦":["嚓嚓"],
"tsʰiam˥˥":["簽","籤","攕"],
"tsʰiam˥˧":["攕"],
"tsʰian˥˥":["千","遷"],
"tsʰian˥˥tsʰiu˥˥":["韆鞦"],
"tsʰian˥˧":["淺"],
"tsʰian˨˦":["延","錢"],
"tsʰiap˨":["妾","竊"],
"tsʰiat˨":["切"],
"tsʰiau˥˥":["超","搜"],
"tsʰiau˨˦":["撨"],
"tsʰiau˨˩":["笑"],
"tsʰiaŋ˥˧kʰa˥˥":["蹌跤"],
"tsʰiaŋ˥˧kʰɔ˥˥":["蹌箍"],
"tsʰiaŋ˧˧":["䢢"],
"tsʰiaŋ˨˦":["沖","腸","常"],
"tsʰiaŋ˨˩":["唱"],
"tsʰiaʔ˨":["赤","刺","鍤"],
"tsʰiaʔ˨siu˨˩":["刺繡"],
"tsʰiaʔ˨tsʰiʔ˦":["赤蠘"],
"tsʰiaʔ˨ĩã˧˧ĩã˧˧":["赤焱焱"],
"tsʰia˥˥":["車","捙","奢"],
"tsʰia˥˥hua˥˥":["奢華"],
"tsʰia˥˥tsam˧˧":["車站"],
"tsʰia˨˦":["斜"],
"tsʰik˦":["摵"],
"tsʰik˨":["粟","測","策","促","觸","戚"],
"tsʰim˥˥":["深","侵"],
"tsʰim˥˥kut˦":["深掘"],
"tsʰim˥˥kʰẽ˥˥":["深坑"],
"tsʰim˥˧":["寢"],
"tsʰim˨˦":["鑱"],
"tsʰin˥˥":["親"],
"tsʰin˨˩":["凊","秤"],
"tsʰin˨˩bin˧˧":["凊面"],
"tsʰiok˨":["雀","促","觸","浞"],
"tsʰioŋ˥˥":["充","沖","衝","槍","昌"],
"tsʰioŋ˥˥pɔ˨˦":["菖蒲"],
"tsʰioʔ˨":["尺","蓆","沢"],
"tsʰio˥˥":["𪁎","俏"],
"tsʰio˧˧":["炤"],
"tsʰio˨˩":["笑"],
"tsʰio˨˩bin˧˧":["笑面"],
"tsʰit˨":["七","拭","姼"],
"tsʰit˨a˥˧":["七仔","拭仔","姼仔"],
"tsʰit˨kʰoŋ˥˧":["七孔"],
"tsʰit˨tʰo˨˦":["𨑨迌"],
"tsʰiu˥˥":["秋","鬚","鶖","羞"],
"tsʰiu˥˥tsʰaŋ˨˩":["鬚聳"],
"tsʰiu˥˥tsʰiu˥˥":["瞅瞅"],
"tsʰiu˥˧":["手","帚"],
"tsʰiu˥˧in˨˩":["手印"],
"tsʰiu˥˧iu˨˩":["手幼"],
"tsʰiu˥˧lɔ˧˧sĩũ˥˥tsʰɔ˥˥laʔ˨":["手路傷粗啦"],
"tsʰiu˥˧pi˨˩":["手痺"],
"tsʰiu˧˧":["樹"],
"tsʰiu˨˦":["愁","揫"],
"tsʰiu˨˦tin˨˦":["揫藤"],
"tsʰiŋ˥˥":["清","稱","千","青"],
"tsʰiŋ˥˥kʰi˨˩":["清氣"],
"tsʰiŋ˥˥liam˨˦":["清廉"],
"tsʰiŋ˥˥tsʰo˥˧":["清楚"],
"tsʰiŋ˥˧":["請","筅","惝"],
"tsʰiŋ˧˧":["穿"],
"tsʰiŋ˨˦":["榕"],
"tsʰiŋ˨˩":["銃","擤","衝","熗"],
"tsʰiʔ˦":["揤","蠘"],
"tsʰiʔ˦tsʰuaʔ˦":["揤斜"],
"tsʰiʔ˦tsʰŋʔ˨":["嗤噌"],
"tsʰiʔ˨":["𩑾"],
"tsʰiʔ˨tsʰiʔ˨":["𩑾𩑾"],
"tsʰi˥˥":["痴","蛆","鰓","腮"],
"tsʰi˥˥bu˥˧tsʰiʔ˦":["嗤舞嗤"],
"tsʰi˥˥pa˥˥":["七八"],
"tsʰi˥˥tsʰam˥˧":["悽慘"],
"tsʰi˥˧":["鼠"],
"tsʰi˧˧":["市","飼"],
"tsʰi˧˧a˥˧":["市仔"],
"tsʰi˧˧tĩũ˨˦":["市場"],
"tsʰi˨˦":["持","溡"],
"tsʰi˨˦hue˧˧":["徐匯"],
"tsʰi˨˩":["試","刺","翅"],
"tsʰi˨˩toŋ˨˦":["莿桐"],
"tsʰok˨":["撮","簇"],
"tsʰoŋ˥˥":["窗","創","聰"],
"tsʰoŋ˥˥soŋ˥˥":["滄桑"],
"tsʰoŋ˥˧":["衝"],
"tsʰoŋ˨˩":["創"],
"tsʰoŋ˨˩ti˧˧laʔ˨":["創治啦"],
"tsʰoʔ˨":["𧮙"],
"tsʰo˥˥":["臊","操"],
"tsʰo˥˧":["草"],
"tsʰo˨˩":["錯","噪","剉","糙"],
"tsʰuan˥˥":["川","釧","穿","村"],
"tsʰuan˥˧":["喘"],
"tsʰuan˨˦":["攢"],
"tsʰuan˨˩":["串","竄","篡"],
"tsʰuaʔ˦":["斜"],
"tsʰuaʔ˨":["掣","礤","疶"],
"tsʰua˧˧":["娶","𤆬","泄"],
"tsʰua˧˧tʰau˨˦":["𤆬頭"],
"tsʰue˥˥":["吹","炊"],
"tsʰue˥˧":["髓"],
"tsʰue˧˧":["揣"],
"tsʰue˨˦":["箠"],
"tsʰui˥˥":["催","推","摧","吹"],
"tsʰui˨˩":["喙","碎","翠","粹","脆"],
"tsʰui˨˩a˥˧":["喙仔"],
"tsʰun˥˥":["春","伸","賰","村"],
"tsʰun˥˥tsʰut˨":["伸出"],
"tsʰun˨˦":["存"],
"tsʰun˨˩":["寸","吋"],
"tsʰut˨":["出","齣"],
"tsʰut˨ku˥˥lun˥˧":["出痀崙"],
"tsʰut˨pʰiaʔ˦":["出癖"],
"tsʰuʔ˨":["眵","焠"],
"tsʰu˥˥":["趨","舒","樞"],
"tsʰu˥˧":["取","此","處"],
"tsʰu˧˧":["跙","呲","澍"],
"tsʰu˨˩":["厝","次","處","趣"],
"tsʰã˧˧":["錚"],
"tsʰĩã˥˧":["請","且"],
"tsʰĩã˨˦":["晟"],
"tsʰĩã˨˦kik˨":["成格"],
"tsʰĩã˨˩":["倩"],
"tsʰĩũ˥˥":["鯧","腔","槍"],
"tsʰĩũ˥˧":["廠","搶"],
"tsʰĩũ˧˧":["像","上","象","匠"],
"tsʰĩũ˨˦":["牆","颺"],
"tsʰĩũ˨˩":["唱"],
"tsʰĩ˥˥":["鮮","菁"],
"tsʰĩ˨˦":["瀳"],
"tsʰŋ˥˥":["床","倉","瘡","艙","穿"],
"tsʰũã˥˥":["扦"],
"tsʰũã˨˩":["閂"],
"tsʰɔ˥˥":["粗","初"],
"tsʰɔ˥˧":["礎"],
"tsʰɔ˨˩":["醋","措"],
"tsʰẽ˥˥":["青","星","生","腥","親","菁"],
"tsʰẽ˥˥tsiaʔ˦":["生食"],
"tsʰẽ˥˧":["醒"],
"tsʰẽ˥˧aʔ˨":["醒矣"],
"tsʰẽ˨˩":["腥"],
"tsẽ˥˥":["爭"],
"tsẽ˥˧":["井","阱"],
"tsẽ˧˧":["靜"],
"tsẽ˨˩":["諍"],
"tuan˥˥":["端"],
"tuan˥˧":["短"],
"tuan˧˧":["斷","傳"],
"tuan˨˩":["斷","鍛"],
"tuat˦":["奪"],
"tuaʔ˨":["掇"],
"tua˧˧":["大"],
"tua˧˧han˨˩":["大漢"],
"tua˧˧kaŋ˥˧":["大港"],
"tua˧˧kui˨˩":["大貴"],
"tua˧˧lau˨˦":["大樓"],
"tua˧˧mia˧˧":["大命"],
"tua˧˧piŋ˨˦":["大爿"],
"tua˧˧sin˥˥":["大身"],
"tua˧˧sĩã˥˥hau˥˧":["大聲吼"],
"tua˧˧tsiŋ˥˧":["大種"],
"tua˧˧ui˧˧":["大位"],
"tua˨˩":["帶","蹛"],
"tue˧˧":["兌"],
"tue˨˩":["綴"],
"tue˨˩au˧˧":["綴後"],
"tui˥˥":["追","堆"],
"tui˧˧":["隊","墜","兌"],
"tui˨˦":["捶"],
"tui˨˩":["對","碓"],
"tun˥˥":["墩","鈍","屯"],
"tun˥˥hoŋ˨˦":["敦煌"],
"tun˥˥hua˨˩":["敦化"],
"tun˥˧":["囤"],
"tun˧˧":["鈍","屯","燉"],
"tun˨˦":["脣"],
"tun˨˩":["頓","噸","鈍"],
"tut˦":["突"],
"tuʔ˦":["揬"],
"tuʔ˦tuʔ˦":["揬揬"],
"tuʔ˨":["盹","拄"],
"tu˥˥":["㧣","株"],
"tu˥˧":["拄"],
"tu˧˧":["駐","嘟"],
"tu˨˦":["除","櫥","廚"],
"tu˨˩":["注","著","滯"],
"tãĩ˥˧":["刐"],
"tã˥˥":["今","擔"],
"tã˥˧":["打","膽"],
"tã˥˧hĩãʔ˨":["膽嚇"],
"tã˥˧pan˧˧":["打扮"],
"tã˧˧":["淡"],
"tã˨˦":["耽"],
"tã˨˩":["擔","呾"],
"tã˨˩a˥˧":["擔仔"],
"tĩã˥˧":["鼎"],
"tĩã˧˧":["定","碇"],
"tĩã˨˦":["埕"],
"tĩũ˥˥":["張"],
"tĩũ˥˧":["長"],
"tĩũ˧˧":["丈"],
"tĩũ˨˦":["場"],
"tĩũ˨˩":["脹","漲"],
"tĩ˥˥":["甜"],
"tĩ˧˧":["滇"],
"tĩ˨˦":["纏"],
"tńg1":["轉"],
"tńg1kʰi˨˩ah!1":["轉去矣！"],
"tńg1lai˨˦":["轉來"],
"tńg1uat˨":["轉斡"],
"tŋ˥˥":["長","腸","斷","當","堂","張","搪","唐","盪","丈","蕩"],
"tũã˥˥":["單","端","蛋"],
"tũã˧˧":["段","惰","彈"],
"tũã˨˦":["壇","彈","檀"],
"tũã˨˩":["旦"],
"tǹg1":["頓","當"],
"tǹg1te˨˦":["頓蹄"],
"tǹg1toʔ˨":["頓桌"],
"tɔ˥˥":["都"],
"tɔ˥˧":["肚","堵","賭"],
"tɔ˧˧":["度","肚","渡","杜"],
"tɔ˧˧tiŋ˧˧":["杜定"],
"tɔ˨˦":["圖","途","徒","屠","廚"],
"tɔ˨˩":["𪐞","妒"],
"tʰai˥˥":["颱","篩","胎"],
"tʰai˥˧ko˥˥":["癩𰣻"],
"tʰai˧˧":["待","態"],
"tʰai˨˦":["刣"],
"tʰai˨˩":["太","態","泰","呔","汰"],
"tʰai˨˩piŋ˨˦":["太平"],
"tʰak˦":["讀"],
"tʰak˦tsʰeʔ˨":["讀冊"],
"tʰak˨":["剔"],
"tʰam˥˥":["貪","探"],
"tʰam˧˧":["窞"],
"tʰam˧˧tʰui˧˧":["窞倕"],
"tʰam˨˦":["痰","潭"],
"tʰam˨˩":["探"],
"tʰam˨˩paŋ˨˦":["探房"],
"tʰan˥˥":["蟶"],
"tʰan˥˧":["坦","毯","疸"],
"tʰan˨˩":["趁","嘆"],
"tʰan˨˩gɔ˨˩":["探戈"],
"tʰan˨˩tua˧˧tsĩ˨˦looh!1":["趁大錢囉！"],
"tʰap˨":["塌"],
"tʰat˨":["踢","窒"],
"tʰat˨a˥˧":["窒仔"],
"tʰau˥˥":["偷"],
"tʰau˥˥tsiaʔ˦":["偷食"],
"tʰau˥˧":["敨"],
"tʰau˧˧":["毒"],
"tʰau˨˦":["頭"],
"tʰau˨˦a˥˧":["頭仔"],
"tʰau˨˦bue˥˧":["頭尾"],
"tʰau˨˦ke˥˥tiŋ˨˩":["頭家叮"],
"tʰau˨˦kiŋ˥˥":["調羹"],
"tʰau˨˦tsaŋ˥˥":["頭鬃"],
"tʰau˨˦tsaŋ˥˧":["頭摠"],
"tʰau˨˦tsʰiu˥˧":["頭手"],
"tʰau˨˩":["透"],
"tʰaŋ˥˥":["通","窗","熥"],
"tʰaŋ˥˧":["桶"],
"tʰaŋ˨˦":["蟲"],
"tʰaŋ˨˩":["迵","痛"],
"tʰaŋ˨˩tʰĩ˥˥":["迵天"],
"tʰaʔ˦":["疊"],
"tʰaʔ˦tʰaʔ˦":["疊疊"],
"tʰaʔ˨":["塔","踢"],
"tʰa˨˩":["挓"],
"tʰeʔ˦":["提","宅"],
"tʰeʔ˨":["裼"],
"tʰe˥˥":["推","䖙","撐","胎","梯"],
"tʰe˥˧":["體"],
"tʰe˧˧":["䖳","頹"],
"tʰe˨˦":["提"],
"tʰe˨˩":["退","替"],
"tʰiam˥˥":["添"],
"tʰiam˥˧":["忝"],
"tʰiam˧˧":["填"],
"tʰian˥˥":["天"],
"tʰian˥˥tʰoʔ˨":["顛倒"],
"tʰian˥˧":["展"],
"tʰiap˦":["疊"],
"tʰiap˨":["帖","貼","疊"],
"tʰiat˨":["撤","澈"],
"tʰiau˥˥":["刁","挑"],
"tʰiau˥˥kaŋ˥˥":["刁工"],
"tʰiau˥˥laŋ˧˧":["挑俍"],
"tʰiau˥˧":["挑"],
"tʰiau˧˧":["柱","𤶃","祧"],
"tʰiau˨˦":["鮡"],
"tʰiau˨˩":["跳"],
"tʰiaʔ˨":["拆"],
"tʰik˨":["畜","斥"],
"tʰin˧˧":["伨"],
"tʰin˨˦":["斟"],
"tʰiok˨":["畜"],
"tʰioŋ˥˥":["衷"],
"tʰioŋ˥˧":["塚","寵"],
"tʰioŋ˨˦":["蟲"],
"tʰioŋ˨˩":["暢"],
"tʰio˥˥":["挑"],
"tʰio˨˩":["糶"],
"tʰiu˥˥":["抽","紬"],
"tʰiu˥˧":["丑"],
"tʰiŋ˥˧":["逞"],
"tʰiŋ˥˧siŋ˧˧":["寵倖"],
"tʰiŋ˨˦":["停","程","騰","呈","謄"],
"tʰiŋ˨˩":["聽"],
"tʰiʔ˦":["喋"],
"tʰiʔ˨":["鐵","軌"],
"tʰi˥˥":["黐","麶"],
"tʰi˥˧":["恥","褫"],
"tʰi˧˧":["雉"],
"tʰi˨˦":["啼","苔"],
"tʰi˨˩":["剃"],
"tʰi˨˩tʰau˨˦":["剃頭"],
"tʰok˨":["讀","託","拓","戳"],
"tʰok˨dzi˨˦":["托兒"],
"tʰok˨si˨˩":["託四"],
"tʰoŋ˥˥":["通","蓪"],
"tʰoŋ˥˧":["統","捅"],
"tʰoŋ˧˧":["緟","宕"],
"tʰoŋ˨˩":["痛"],
"tʰoʔ˨":["魠"],
"tʰo˥˧":["討"],
"tʰo˥˧hai˥˧":["討海"],
"tʰo˨˦":["桃"],
"tʰo˨˩":["套","妥"],
"tʰuan˨˦":["傳","團"],
"tʰuat˨":["脫"],
"tʰuaʔ˨":["挩","屜","獺"],
"tʰua˥˥":["拖"],
"tʰua˥˥mia˧˧":["拖命"],
"tʰua˥˥pẽ˨˦":["拖棚"],
"tʰua˧˧":["汰","豸"],
"tʰui˥˥":["推","梯"],
"tʰui˥˧":["腿"],
"tʰui˨˦":["槌","錘"],
"tʰun˥˥":["吞"],
"tʰun˥˥nua˧˧":["吞瀾"],
"tʰun˥˧":["𧿬"],
"tʰun˧˧":["坉"],
"tʰun˨˦":["黗","豚"],
"tʰut˦":["脫"],
"tʰut˨":["黜","脫","禿"],
"tʰuʔ˨":["黜","禿","托"],
"tʰã˥˥":["他"],
"tʰã˥˧":["挺","坦"],
"tʰã˧˧":["娗"],
"tʰĩã˥˥":["聽","廳"],
"tʰĩã˥˥lui˨˦":["聽雷"],
"tʰĩã˧˧":["侹"],
"tʰĩã˨˩":["疼"],
"tʰĩ˥˥":["天","添"],
"tʰĩ˥˥i˨˩":["天意"],
"tʰĩ˥˥koŋ˥˥":["天公"],
"tʰĩ˧˧":["紩"],
"tʰŋ˥˥":["糖","湯","傳","碭","熥","杖"],
"tʰŋ˥˥tsʰĩũ˥˧":["糖廠"],
"tʰũã˥˥":["攤","灘"],
"tʰũã˥˧":["剷"],
"tʰũã˨˩":["炭","湠","碳"],
"tʰɔ˥˧":["土","吐"],
"tʰɔ˨˦":["塗","土"],
"tʰɔ˨˦tau˧˧":["塗豆"],
"tʰɔ˨˩":["吐","兔"],
"tʰẽ˨˩":["牚"],
"tẽ˥˥":["蹬"],
"tẽ˧˧":["捏"],
"tẽ˨˩":["佯","瞪"],
"tẽ˨˩goŋ˧˧":["佯戇"],
"uai˥˥":["歪"],
"uan˥˥":["冤","彎","灣"],
"uan˥˥ĩũ˥˥":["鴛鴦"],
"uan˥˧":["遠","宛","苑"],
"uan˧˧":["援","緩"],
"uan˨˦":["員","完","丸","灣","園","圓"],
"uan˨˩":["怨"],
"uan˨˩te˧˧":["怨地"],
"uat˦":["越","閱"],
"uat˨":["斡"],
"uat˨kʰi˨˩":["斡去"],
"uaŋ˥˥":["嚾"],
"uaʔ˦":["活"],
"uaʔ˦tsiaʔ˦":["活食"],
"ua˥˧":["倚","瓦"],
"ua˧˧hɔ˥˧ua˧˧pʰi˨˦lan˨˦ua˧˧":["畫虎畫皮難畫"],
"ue!7":["話！"],
"ueʔ˦":["劃"],
"ueʔ˨":["喂"],
"ue˥˥":["鍋","椏","煨","萵"],
"ue˧˧":["話","畫","衛"],
"ue˨˩":["穢"],
"ui˥˥":["威","萎","揻"],
"ui˥˧":["委","偉"],
"ui˧˧":["位","胃","為","謂"],
"ui˨˦":["圍","為","遺","違","維","惟","帷","唯"],
"ui˨˦an˥˥":["為安"],
"ui˨˦a˥˧":["圍仔","圍"],
"ui˨˦hun˥˥":["為婚"],
"ui˨˦tsi˥˧":["為止"],
"ui˨˩":["慰","畏","飫","對"],
"un˥˥":["溫","恩","鰮","蝹","瘟"],
"un˥˧":["穩","隱"],
"un˧˧":["運","韻"],
"un˨˦":["勻"],
"un˨˩":["搵","塭"],
"ut˦":["遹","聿"],
"ut˨":["鬱","熨"],
"uʔ˨":["噎"],
"u˥˥":["趺","汙"],
"u˥˥dziam˥˧":["汙染"],
"u˥˧":["雨","與"],
"u˥˧mɔ˨˦":["羽毛"],
"u˥˧tiu˧˧":["宇宙"],
"u˧˧":["有","譽"],
"u˧˧dzi˧˧pɔ˧˧tsʰit˨a!2":["有二步七仔！"],
"u˨˦":["餘"],
"u˨˩":["焐"],
"u˨˩li˧˧":["汙吏"],
"ãĩ˧˧":["偝"],
"ã˧˧":["餡"],
"ã˨˦":["攔"],
"ã˨˩":["向"],
"õ˥˥":["唔","嗚"],
"õ˨˩":["惡"],
"ĩãũ˥˥":["喓"],
"ĩã˥˥":["泱"],
"ĩã˥˧":["影"],
"ĩã˧˧":["颺"],
"ĩã˧˧ĩã˧˧":["颺颺"],
"ĩã˨˦":["贏","營"],
"ĩã˨˩ĩã˨˩":["映映"],
"ĩũ˥˧":["養","舀"],
"ĩũ˧˧":["樣"],
"ĩũ˨˦":["洋","羊","楊","溶","熔"],
"ĩ˥˥tĩ˨˦":["纓纏"],
"ĩ˥˧":["穎"],
"ĩ˧˧":["院"],
"ĩ˨˦":["圓","櫞"],
"ĩ˨˩":["燕","嬰"],
"ĩ˨˩õ˨˩":["喑噁"],
"ńg1":["䘼","蔭","捥","鈗"],
"ŋai˧˧":["艾"],
"ŋau˧˧":["藕"],
"ŋa˥˧":["雅"],
"ŋeʔ˦":["挾"],
"ŋeʔ˨":["莢","夾"],
"ŋeʔ˨a˥˧":["夾仔"],
"ŋe˧˧":["硬","勁"],
"ŋiauʔ˦":["蟯"],
"ŋiau˥˥":["擽"],
"ŋiau˥˧":["撓"],
"ŋia˨˦":["迎"],
"ŋiu˥˧":["扭"],
"ŋɔ˥˧":["五","午","伍","我","𩵱","忤","偶"],
"ŋɔ˥˧dzin˨˦":["五仁"],
"ŋɔ˥˧kiŋ˥˥":["五經"],
"ŋɔ˧˧":["悟"],
"ŋɔ˨˦":["梧"],
"ŋɔ˨˦kueʔ˨":["吳郭"],
"ŋɔ˨˦kʰi˨˦":["蜈蜞"],
"ŋ˥˥":["黃","掩","央","秧","暈"],
"ũãĩ˥˥ũãĩ˥˥":["歪歪"],
"ũãĩ˥˧":["𨂿"],
"ũãĩ˨a˥˧":["𨂿仔"],
"ũã˥˥":["鞍"],
"ũã˥˧":["碗"],
"ũã˧˧":["換","旱"],
"ũã˧˧iau˥˥":["換枵"],
"ũã˨˩":["晏","案"],
"ǹg1":["向"],
"ɔʔ˨":["喔"],
"ɔ˥˥":["烏","槔"],
"ɔ˥˥hɔ˥˥":["嗚呼"],
"ɔ˥˥mi˥˧tɔ˨˦":["阿彌陀"],
"ɔ˥˧":["挖"],
"ɔ˧˧":["芋"],
"ɔ˨˦":["湖","壺"],
"ɔ˨˦tiap˦":["蝴蝶"],
"ɔ˨˦tsiu˥˥":["葫洲"],
"ḿ1":["姆"],
"ẽ˥˥":["嬰"],
"ẽ˨˦":["楹"]},"SrcMulti":null,"DstMulti":null,"SrcMultiSuffix":null,"DstMultiSuffix":null,"DropLast":null,"DstMultiPrefix":null,"PrePhonWordSteps":[{"Normalize":"NFC"}],
"SplitBefore":null,"SplitAfter":["》","）",")","。","？","、","，","：","、","；","！","?","!",".","”"],
"SplitAt":null,"IsDuplex":false,"IsSrcSurround":false,"SrcDuplicate":null}