{"Map":{"-":["ˈ","n","ɾ"],
"-1":["nˈgɯl"],
"05":["oˈʃeɾ"],
"07":["oˈleɾʃ"],
"1":["tɾuː"],
"175271":["zɯleɾtʃeɾ"],
"18":["ʃɯnˈtɯn"],
"26":["s26"],
"28":["sˈɯtˈsɯt"],
"40":["ɑˈɾɯ"],
"5":["s"],
"88":["sɛ88"],
"a":["ɑ","a","aˈ","ɑˈ","aː","ɑː","æ","ɯ","a'","ɑːˈ","l","n","ɾ","m","ˈ","b","t","s","k","e","aːˈ","d","ɫ","ə","kˈ","ʃ","tʃ","aːɫ","ɾˈ","æˈ","jɑ","z","i","j","o","ɛ","ʒ","ɯˈ","f","ʊ","v","u","p","eː","g","ɪˈ","dʒɑ","ɣ","iˈ","ʰ","ˈdʑ","ʲ","ʔ","ä","oˈ","ɔ","ɑˌ","oː","ɫa"],
"ac":["ɑdʒ","adʒ","j","ɑˈdʒ","ɑk","k","ɑtʃ","aːdʒ","aˈdʒ","ɑ","aʤ","aʒ","tʃ","adʒɑ","dʒ","ɑdʒɑ","ɑːdʒ","dʒɑk","ɑː","aˈd","aʃ","ɑːtʃ","ad","tʃɑ","tɑ","ʒæ","eɪ","ɑˈc","aːk","ac","an","ækˈ","aç","eːʒ","ɑg","jˈdʒ","ak","eːd","aːt","dʒɑ","ktʃ","ɑc","ɾɑ","ʊˈ","ɑˈk","aʧ","ʃɑ"],
"acı":["ɑˈdʒɯ","ɑdʒɯˈ","ɑdʒɯ","ɑːdʒ","ɑˈdʒɯˈ","aˈdʒɯ","ɑːd","ɑˈ"],
"ah":["ah","ɑh","aχˈ","aχ","aʃ","ɑːh","ɑhˈ","ɑˈh","aç","aɾ","aˈh","aːh","aɫ","ɑˈt","aːɫ","ˈh","aˈ","ax","ɫɫ","aːhˈ","aːi","sa","aˈʃ","ˈɫ","aʰ","ɑˈ","aɯ","aɦ","aɰ"],
"ann":["ɑnː","ɑnn","ˈanː","ann","ɑnˈn","anˈn","anː","ane","ɑnɛ","ˈɑːn","aˈn","anˈ","ɑnˈ","ˈan"],
"ağ":["ɑː","aːɫ","aːɫɫ","ɑːˈ","ɑːɯ","ɑːɣ","aː","aːɣ","aːɰ","aːɯ","ɑːˈg","ɑːˈʒ","aɣ","ʃ","ɑ","aːɾ","ɑːɾ","aːˈ","ɑɰ","ɑɣ","aːɟ","ʒɯ","ɯɾ","ɑːɰ","ʃɑː","ˈk","ɯn","ağ","ɑːˈɯ","ɑːˈɟ","ɑɾ","ɯʃ","ɯj","saː","ɣɯ","ɑːg","taː","ɯˈ","ˈc","aʒ"],
"b":["b","ˈ","ɯ","β","p","ɑ","bː","ɾ","a","e","n","i","m","dʒ"],
"bi":["bi","b","bɯ","biˈ","bɪ","il","be","bɪˈ","ɯl","ə","ɯɾ","iˈ","ɯˈ","ˈb","biː","ib","iɫ","ɾi","iɾ","bɯˈ","je","ɑb","jɯ","biˌ","ij","sɛ","ɾɯ","bɫ","mɪ","je̞","ɑd","bːɯ","ji","beˈ","ɯɫ"],
"c":["k","dʒ","tʃ","t","ʃ","ɛ","ˈdʒ","d","ʤ","ˈ","ɯ","c","ʊ","ʒ","ɑ","ɪ","ɔ","n","kˈ","ɾ","aː","æ","s","o","ç","ʧ","ʲ","z","a","j","ɟ"],
"ca":["dʒɑ","dʒa","kɑ","tʃɑ","ʒɑ","ʤɑ","ˈdʒɑ","ka","ˈdʒa","ʃɑ","ʃa","ˈdʒ","cɑ","ɑk","tʃa","ʒa","kˈ","ˈk","ˈdʒɑː","ʤa","ˈdʒæ","dʒɑˈ","dʒɑn","dʒaˈ","d","ʧa","ca","ʤɑˈ","ɑɾ","dʒæ","ʒaˈ","dʒ","dʒɑː","ʃɑˈ","ʤaˈ","kʰ","dʒɑk","ʃaˈ","kɯ","dʒaː","tʃ","ʃɑː","ʃaː","aɫ","dʒɛ","jɑ","laː","tʃɑˈ","ak","ʧk","tʃɯ","ɑkˈ","ʤɑː","ˈd","dʒɯ","kaˈ","ʧaˈ","ndʒɑ","dʒa'","dʒɑkˈ","sə","ˈdʒe","an","ʧaː","ʤɑːˈ","ʃæ","nt","kæˈ","dʒɑm","aːk","ça","kæ","ʃæˈ","ktʃ"],
"cağ":["dʒɯ","dʒɑː","dʒ","ɑɣɯ","dʒaː","ɑgɯ","ʒɯˈ","g","dʒɑːˈ","ɟɯɑ","dʒɑːɯ","dʒɑɰ"],
"ce":["dʒe","tʃe","ʃe","dʒɛ","ʤe","tʃeˈ","ʒe","ˈdʒe","ʃeˈ","ʃɛ","tʃɛ","d","tʃ","ʤɛˈ","ʃel","se","ʲeˈ","dʒ","ce","ʧe","ʤɛ","ʃɛˈ","sɛ","ʤeˈ","nʃ","ʲe","ʒɛ","ntʃ","jæ","ˈdʒ","ˈd","ts","ɛt","cɛ","dʒæ","eˈ","tˈ","ˈdʒeˈ","je","ˈdʒɛ","dʒɯ","ʃl","dʒɛˈ","ɛk","tʃeˌ","kˈ","ek"],
"cek":["tʃek","dʒek","tʃɛk","dʒe","ʤek","tʃec","ʒek","dʒɛk","tʃe","ʧek","ʃek","tʃɛkˈ","cæk","dʒec","ʒe","cɛk","dʒekˈ","dʒɛkˈ","dʒɛc","tʃɛ","ʤe","tʃekˈ","dʒɛ","dʒecˈ","ce","ʒec","dʒ","tʃki","dʒe̞kˈ","cæˈ","sek","ʒekˈ","tʃecˈ","dʒeˌc","esk","ʒeˈk","ʃe","tʃes","etʃ","ece","tʃej","ɛkˈ","tʃeˈk","tʃæˈ","tʃi","dʒɛt","dʒet","dʒe̞k"],
"ceğ":["dʒ","dʒe","tʃeɣ","etʃ","ɛtʃ","dʒeˈ","dʒeˈʁ","tʃeɟ","tʃeg","dʒeɣ","dʒeˈʒ","dʒeˈɾ","ʒec","ʒeɟ","dʒi","tʃi","dʒeˌc","ʒeˈʒ","ˈtʃ","dʒeç","dʒeɟ","tʃeː","tʃɛg","dʒeʝ","ʒeɣ","dʒeˈc","dʒeˈdʒ","tʃeːg","jeʒ","tʃeːˈ","dʒeˈʝ","ʒeˈ","tʃeˈc","ʒeˈc","tʃeˈk","ʒeˈtʃ","dʒec","ʃeg","dʒeˈtʃ","tʃeɰ","ʧeːʒ","eʒi","dʒeːɟ","ʒeˈɟ","dʒeʁ","tʃɛɰ","sje","dʒɛˈɾ","dʒek","ʒe̞ˈʒ","jet","ʒɯˈ","dʒeˈj","tʃɛɣ","dʒɛɣ","eʒe","ʒeːʒ","dʒeɰ","dʒɛc","seɟ","tʃeːʒ","tʃi̯","tʃiɾ","ʒim","ʒeɾ","eˈc","dʒeːɣ","etʃɯ","ʒeˌʤ","tʃiɟ","jeʤ","tʃe̞ɟ","dʒeˈʃ","tʃek","dʒeˌʝ","tʃe","ʒeˈʝ","tʃæˈk","dʒeːc","dʒeʒ"],
"ch":["tʃ","ç","ʃɑ","ˈt","ʃɛ","ʃæ","çi","ɪt","aʃ","ʃa","nt","ʃɔ","çɑ","ˈʃ","ʃe"],
"ci":["dʒi","tʃi","ʃi","dʒɪ","ˈdʒi","dʒiˈ","ʤi","dʒ","tʃ","ʒi","dʒɯ","ˈd","dʒiː","tʃiˈ","ˈtʃ","tʃj","ʒiˈ","tʃiː","ʃiˈ","tʃɯ","ʒɯ","tʃɪ","nˈd̪","ʃiˌ","ɪʃ","jɯ","nˈ","nd","tʒ","sɪ","ʃɯ","ˈdʒɯ","ˈdʒɪ","ˈt","ʒeˌ","sɯ","ci","dʒiˌ"],
"coo":["kuː","uː"],
"cu":["dʒu","tʃu","ʤu","d","dʒʊ","ot","dʒ","cu","tʃuˈ","dʒuː","dʒʌ","ˈdʒu","dʒɯ","ʒy","tʃʊ","ˈdʒɜː","ʃu","tu","ˈdʒʏ","ku","ˈdʒʌ","ʒɛ","tʃ"],
"d":["d","ˈd","ɯ","ɾ","e","ˈ","n","ʒ","ɑ","t","ɟ","dː","ɫ","da","a","æ","d̪","ð","ɛ","r","dʒ","l","y","s","j","m","u","ɣ","aː","eː","z","ɰ","i","ɖ","nˈ","c","ŋ","ʃ"],
"da":["da","dɑ","daː","d","d̪a","daˈ","dɑˈ","dav","ɫɑ","dɯ","d̪ɑ","dal","ða","ɾɑ","ʒa","daɫ","dɑː","ɫa","mɑ","ʒɑ","ˈdɑ","daj","tɑ","daɯ","dæ","ˈda","ˈd","ɾa","daːˈ","yda","ɑn","nˈ","de","ˈdaː","ɯda","ɟɑ","nda","ˈdɯ","jɑ","zɯ","ma","das","tɯ","ɑɾ","nɑ","an","aɫ","ad","dɯˈ","ðɑ","un","ada","ɟɑˌ","deː","dɑˌ","da'","dɑːˈ","nˈd","dɑ̟","dːɑ","aːda","ɾɯ","ɾda","ɯd"],
"dağ":["daː","daːɫ","daːɯ","daːɣ","dɑː"],
"de":["de","dɛ","ˈde","deˈ","ˈd","dæ","ˈ","d̪e","ˈdeː","ˈdɛ","del","deː","dɛˈ","ˈdæ","ɟe","di","dʒe","da","dʒeˈ","ðe","nd","ed","ðɛ","ze","ðæ","ðeː","en","ŋ","et","d̪æ","de̞","ʒɛ","eˈ","dːɛ","nɛ","ˈn","dʒɛ","ɫe","eɫ","ɫɛ","d̪ɛ","d̪e̞","ɾiˈ","el","s̪e","ɫæ","ŋk","ciˈ","dj","ʒe","ɾˈ","nˈd","ntʃ","ɟæ","dʒɯ","ce","ˈdiː","dɛˌ","dɜ","dø","dʒd","ej","diː","dɯ","sɯ","diˈ","deˌ","ad","de̞ˈ"],
"di":["di","diˈ","ˈdi","dɯ","i","d","dɪ","diː","ˈ","ˈd","ɟi","d̪i","de","ɟɯ","jɯ","ˈdɪ","ˈdiː","iˈ","ɟiˈ","ði","dʒi","dɪˈ","diːˈ","d̪ɯ","jiː","ji","ɫɯ","ij","dʒɯ","il","ˈdɯ","diˌ","da","deˌ","ɯm","ɑd","ik","ɾd","jd","ɯɾ","do","ðɟ","di̞ˈ","di'","dʒiˈ","d̪ɪ","ɟe","daɪˈ","id","daɪ̯","di̯"],
"e":["e","ɛ","eˈ","æ","ɛˈ","ˈ","m","j","eː","i","ɾ","t","n","s","e̞","iː","ə","d","l","æˈ","k","ɑ","iˈ","ʒ","b","ʃ","eˌ","f","a","ɯ","e'","ɾˈ","r","v","mˈ","ø","ɪ","z","ʃe","e̞ˈ","ɫ","o","æˌ","h","dʒe","ʊ","ʲ","ɛˌ","dʒ","ɑː","c","tʃ","nˌ","ʰ","ẽ","ɜ","ε"],
"ek":["ek","ɛk","ec","ɛc","e̞k","ekˈ","ɛkˈ","eˈk","e","eɫ","æk","ɛˈk","eg","e̞c","ʃɛ","eç","eːk","e̞kˈ","eˈc","eʃ","eɾ","ˈk","ke","ɛcˈ","ék","cˈ","tʃ","ækˈ","eːc","ʃeː","ɛl","ecˈ","eɟ","ɛˈc","eːl","c'","en","æɫ","ɛkˌ","ɛɾ","eˌk","e̞ˈj","ɯɫ","ˈs","mˈ","eːˈ","mɛ","eːm","ʃæ","eːkˈ","mˈs","ɛm","cl","kl"],
"el":["el","ɛl","ele","eˈl","eli","ɛˈl","ɛlˈ","eɫ","æl","eld","le","ˈl","eˈɫ","ælˈ","me","lˈ","lɛ","mɛ","ɛɫ","e̞l","bel","æˈl","eˈ","eɫˈ","ɫɛ","li","eliˈ","æɫ","eˌl","sɛ","ʃɛ","je","e̞ˈl","elɪ","eʎ","ɑl","al","bɛ","oːl","zel","əl","ɯl","æˈ","kɛ","eʃ","elʲ","ɾl","fel","he","ɫt","ɾi","ke","ɪl","æˌl","tʃɛ","ɯt","ɾɛ","ej","jel","el̪","iˈr","iˈl","ilˈ","ˈd","se","iːl","em","ne","nel","nɛ","tm","et","elj"],
"en":["en","ɛn","n","enˈ","eˈn","æn","ɛnˈ","æŋ","eːn","ɛˈn","ɛŋ","nˈ","eɲ","e̞n","ne","ən","ʰ","in","ˈn","ʒe","enˌ","eɾ","eˈ","t̪","æɱ","eŋ","iːn","ɑn","æˈn","æŋˈ","ɑnˈ","eˌn","je","œn","ʃe","eˈz","eɫ","ɛŋˈ","tʃ","ɛɾ","hɛ","æm","me","ˈj","ˈv","εn","ˈm","e̞nˈ","ɛnˌ","mˈ","ɛm","ˈɛ","e̞n̪","ɾɛ","iˈn","ed","ʰe"],
"ew":["uː","u","ɛw","eˈv","ʊˈ","uˈ"],
"f":["f","fˈ","ɯ","o","ˈ","ɛ","ɫ","t","ɑ","p","i","e","ɸ"],
"g":["g","ɟ","ŋ","ɣ","ɯ","ʒ","dʒ","d","ˈ","ʝ","ˈg","ɾ","ɾc","t","j","ç","k","ʤ","ʃ","v","ʊ","ɰ","oʁ"],
"gu":["gu","ɯɫ","gʊ","ɣu","ɯˈ","guˈ","ˈɟ","ˈgu","gw","ɾɟ","ˈɣ","gʏ","ɯl","ɯn","gi","ɟu","ɰʊ","ɰu","ʊl"],
"h":["h","ɦ","hˈ","aː","ʃ","ɯ","i","ɪ","ˈ","ɰ","t","ɛ","x","χ","a","ɾ","ɑ","ç","χˈ","l","e","ɫ","ʰ","u","o","ɔ","d"],
"ha":["ha","hɑ","ah","h","haˈ","haː","ahˈ","ɦɑ","ʃa","ha'","ahk","aˈ","ahp","hɑˈ","hæ","ɑɾ","ɑn","ɦa","an","hɑː","he","ˈh","ɾa","ɑˈ","ɦɑː","ʃaː","hæˈ","ahe","xæ","aht","aːl","ɑɾˈ","haˈk","ɑk"],
"i":["i","ɯ","iˈ","ɪ","iː","ɾ","j","ˈ","ɪˈ","n","ʃ","l","ɯˈ","e","m","s","z","t","eː","ɫ","k","iːˈ","ɛ","r","i'","ɑ","ʒ","i̯","iˌ","ʰ","d","v","aː","h","p","f","c","w","ɲ","a","ʲ","eˈ","o","ɟ","aˈ","'","i̞","ʊ","ɑˈ","æ","ɪ̯","u","t̪","jɑ","d̪ʐ","ʏ","i̞ˈ"],
"in":["in","iˈn","ɪn","inˈ","ɯn","i","iːn","iɲ","ˈn","en","ɪnˈ","iŋ","ɛn","iɾ","ɪŋ","eɾ","de","iː","nˈ","iˈ","nd","ɯnˈ","jn","iˌn","iɳ","ɪˈn","kɪ","ɑn","imˈ","s̪","ɛr","enˈ","ɛnˈ","im","sɪ","eˈn","ɾɯ","in̪","zl","jˈn","ʒɯ","ɯˈn","ˈd","iɣ","ɾi","an","iʃ","eˌn","dɛ","eːn","ci","nɫ","ɪŋˈ","sɯ","ej","aːn","ɾn","ʏn","ˈs","dʒ","i̞n","eɫ","ɯɲ","i̯n","ʃt","eɲ","iːˈn","ˈl","ˈi","ɛˈn","iɰ","i̯ˈn","ni","eˈ","ˈɯ","ʃe","ɛɲ","sɛ","jɛ","ɪˈnˈ","ɾiˈ","ɯr","ir","iːn̪","iˈr","iˈtʃ","rɫ","ʊɪ","lɯ","ɟɯ","ɪˈɰ","es","ɯs","ɑs","iˌɲ","ˈd̪","ɲe","jɯ","ˈɰ","eˈʃ","aˈn","iːr","sɫ","wɪ","itʃ","er","jm","ɾɯn","jnˈ","ɯŋ","no","sl","sn","iˈɾ","e̞ˈn","vɪ","iːnˈ","iːnˌ","ɫu","ɫɯ","ʃɯ","ɛɾ","nl","i̯ɾ","tɪ","liː","ˈj","ʲe","is","jˈ","nt","ɯˈs","on","ij","di","eːnˈ","ʒˈ","lɪ","ˈʒ","mɪ","ri","ˈɕ","me","ˈɾ","eˈr","ɛs"],
"j":["ʒ","dʒ","j","d","ʃ","a","ʒː","ˈ","ɟ"],
"jen":["dʒen","ʒen","dʒɛnˈ","dʒɛ","ʒɛˈn","jenˈ"],
"k":["k","c","kˈ","ˈk","ɫ","ɑ","ˈ","ʃ","ɯ","g","d","l","kː","ɪ","i","ɾ","ç","m","j","ɛ","ʒ","s","ɟ","a","tʃ","e","n","ʔ","cˈ","t","ʁ","b","ʰ","ŋ","χ","dʒ","æ","ʊ","y","kˌ","aː","iː","ç","f","uɣ","uː","eː"],
"kt":["kt","kˈt","t","ct","tʃ","tɯ","ke","tk","tˈk","ˈt","axt","kt̪","ktʰ","ɾk","cˈt","ˈk","çt̪","tˈd","kɛ","tˈc","ft","gˈt","tˈ","ɯt","ʃu","ɪk","ɑt","çt","ʊt","ki","kˈt̪","ʃt","kˈtʃ","fc","kˈ"],
"l":["l","ɫ","lˈ","ɫˈ","ɯ","i","ɾ","ˈ","ɪ","ɑ","b","u","d","ˈl","m","j","ˈɫ","ɛ","e","a","ɾˈ","r","t","dʒ","n","æ","ʒ","s","l̪","l'","ʎ","z","ɔ","ʃ","ɑː","mˈ","ł","c","k","ɣ","o","iː"],
"la":["ɫɑ","la","lɑ","ɑ","ɫa","ɫɯ","a","laː","ɫ","ɯ","laˈ","l","ɑm","ɫɑˈ","ɯɾ","lɑˈ","ɑn","lo","ɫɑː","ɑɾ","loˈ","n","ɑː","ˈɫɑ","ɫaʃ","la'","ɯn","ɯɫ","ɑj","ɑˈ","aɾ","an","ɫə","ɑʃ","lɑː","ʃ","ɫan","lɯ","ɫaɾ","lə","ɫaj","ɫaˈ","læ","ˈla","ɑɫ","ɫat","ɯˈ","ɫm","ɑˈd","ɫaː","ɫæ","ɾɑ","lɛ","laːˈ","aˈ","ɑɾˈ","uk","ˈɾ","jɯ","nɫ","ul","nl","ɑjɑ","loː","ˈlɑ","un","ɑˈj","ɫɑːˈ","ɑl","ɫɫa","ɫɫ","nɫa","ɫɯˈ","ɾa","nɯ","ˈt","ɯɑ","æɫ","ʰɯ","ɫah","ɯɫa","ɑːd","ɯda","ʎa","ɑˈn","jɑː","laˌ","ˈɫ","ɯl","ma","ʃɯ","ɫaːˈ","sɯ","łɾ","ɫar","rɯ","ɯʃ","ɫl","sɫa","aɯ","lɯˈ","aj"],
"le":["le","lɛ","ɫe","e","leˈ","l","ɫɛ","læ","le̞","ˈle","jɛ","leː","li","lə","lɛˈ","eɾ","iˈ","lɯ","in","le̞ˈ","ɫi","ɫɯ","leˌ","ɾi","iɾ","el","en","liˈ","ɛl","ɛt","ɾiˈ","le'","ˈlɛ","ɾe","æɾ","ele","łe","lˈ","ˈɫe","ɛɾ","ˈl","ˈɾ","ir","nʃ","ɫ̪e","ɫɛˈ","ɫeˈ","ci","ɛʃ","ɛn","ɾˈ","ɯɫ","ɯn","lẽ","ˈk","eʒ","eɫ","ɫæ","il","nɛ","ɾɛ","pe","ˈɫɛ","ke","sæ","lɪ","ɫ̪","ɫu","kˈ","kɪ","iːl","zɾ","ɫœ","yɾ","kæ","ki","l̪e","ʲɛ","ɛk","ɯɾˈ","iˈr","je̞","neˈ","ˈlæ","lɜ","er","ɪˈ","iz","tɪ","tɑ","ɛɾˈ","ɫe̞","be","ˈli","ni","sˈ","aˈ","ɾk","ˈɫ","ɛj","ɫɪ","iʃ","te","tˈ","cˈ","ʃt","ˈleˈ","lé","lœ","ji","ɛs","cɪ","ik","iˈl","ndʒ","ˈleː","dæ","ʰi","iˈn","ɯˈ","ze","ɯl","ne","jl","ɾɛˈ","jˈ","eli","ɯɾ","ˈt","ɪɾ","it","me","ɑt","ɪn","nɯ","zɫ","lo","ɫˈ","elɛ","ɫm","læˈ","ɫɾ"],
"ll":["ɫɫ","ll","ɫ","lː","lˈl","ɫɫa","ɫː","lɫ","ɫˈɫ","il","lˈ","ɪl","ˈl","ɯl","ɫˈ","ɫˈl","ɫl","al","lɾ","ɫːˈɫ","ɑl","lʰ","iˈ","ɑːl","lɯ","ɫɑ","ɫːɫ","ɑɫ","ˈj","iːl"],
"m":["m","mˈ","ˈm","e","ˈ","ɯ","i","ɑ","l","ɫ","n","ɛ","u","ɾ","d","a","ʃ","æ","k","ɪ","mː","eː","t","ɱ","ʊ","s","pˈ","ɰ","y","j","p","'","nˈ","z","n̪"],
"ma":["ma","mɑ","maˈ","ɑ","m","maː","mɑˈ","ˈmɑ","mɑː","ɑz","ˈm","ˈma","an","ma'","ɑj","km","aˈ","mæ","maːˈ","moː","ɑˈ","ˈ","mɯˈ","ɑn","aɫ","laː","aˈn","nˈ","ɯm","lɑː","ɯn","ɾɛ","me","ɾm","ɑd","dɑ","am","sm","imˈ","zˈ","mɯ","lɑ","tm","ɑs","uɾ","aj","miː"],
"n":["n","nˈ","ˈ","ˈn","ŋ","ɯ","ɑ","a","ɫ","ɲ","m","l","e","u","ɾ","y","d","i","ɯn","z","n̪","ɛ","ŋˈ","o","aː","ɳ","ɱ","ɣ","nˌ","ɰ","t","s","ɑː","ʒ","ʊ","j","ɪ","r","mˈ","ɴ","nː","'","dʒ","æ","d̪","g","ə","ʃ","k","h","iˈ","iː"],
"nn":["nː","an","nn","ɑn","en","æn","ˈn","nˈn","on","ʊn"],
"o":["o","ɔ","oˈ","oː","ɔˈ","oːˈ","o̞","ɑ","ʒ","ˈ","ɯ","ʃ","o'","oˌ","a","ə","ɒ","ʊ","n","e","l","u","ɾ","ɔː","ʰ","ɑː","d","k","s","t","p","j","ɫ","ɑˈ","eː"],
"oo":["uː","oo","oʊ","ɔːk","ul","oːɾ","ʒoː","ʊk","ɔɔ","oɔ"],
"or":["oɾ","ɔɾ","oɾˈ","or","ɔɾˈ","o","oːɾ","ɔr","oˈɾ","ɔˈɾ","aɾ","oː","o̞ɾ","oːr","ɾˈ","ɯɾ","oːˈɾ","ɾd","ɔːɾ","ɯf","ɾl","nɔ","ɔːˈɾ","o̞r","oʊ","kɔ","eːɾ","ɔrˈ","tɯː","aɾˈ","ˈɾ","ɾi","ɔm","ɾu","ʃɾ","ɔˈ","oːˈr","ɔːɹ"],
"p":["p","pˈ","ˈ","ɑ","ˈp","m","ɫ","h","ʰ","a","dʒ","i"],
"p3":["sˈpɯs"],
"ph":["ph","f","pʰ","pe"],
"q":["k","ˈ","q"],
"r":["ɾ","r","ɾˈ","ɯ","ˈ","rˈ","ɫ","i","ɑ","l","n","d","ˈɾ","e","a","t","m","s","ɹ","ɛ","g","ɯn","u","k","j","y","ɯˈ","r̥","nˈ","æ","o","ʃ","ɪ","ʒ","b","ə","ʰ","d̪","v","rˌ","ɾˌ","sˈ","ʊ","ɾː","ɳ","ɣ","aˈ","ʁ","oː"],
"s":["s","ˈs","ʃ","sˈ","ˈ","sɯ","i","z","e","s̪","ɑ","ɾ","t","n","ɯ","ʒ","a","ɛ","d","m","ɫ","k","ɪ","j","r","o","nˈ","ʲ","oː","f","l"],
"ss":["sː","sˈs","ˈs","sɛ","ɑs","ss","ɯs","ʃe","ɛs","æs","ʒi","ʒæ","ˈʃ","sɾ","sa","ɑˈ","sˈ","as","se","sˈɫ","es"],
"sı":["sɯ","ˈsɯ","ʃɯ","sɯˈ","sɯɫ","sɯt","si","ˈs","sɯd","sɯm","nsɯ","nʃ","ɯʃ","ɕɯ","ɯj","asɯ","ʃs","ɯz"],
"sın":["sɯn","ɯn","sɯnˈ","sɯˈn","sin","sɯ","ˈsɯn","nɯz","nɯs","ɑn","ɑˈs","siˈn","nˈs","nɑz","nɯʃ","ˈnɑ","aˈs","ˈsin","nɯ","sɯd","nɑs","ɯˈn","sɯs","ɾɯn","sɯŋˈ","ɯsɯ","aˈz","ɯʃɯ","mɑs","sɯt","sɯm","ɯnˈ","ɯɫ","ˈsi","kɯ","ɯˈd","aˈn","lɑs","ɑsɯn","ʃɯ","aˈd","ˈɑːn","ˈsu","iˈd","sɑn","ˈɫs","ˈnɯ","nɯl","asɯn","ˈas","sɯˈ","ndɑˈ","mas","ˈdɑ"],
"t":["t","tˈ","ˈt","t̪","tʰ","ˈ","ɯ","d","m","i","ɑ","e","s","l","ɛ","t̪ˈ","r","tʃ","ʃ","ɫ","k","'","n","ʰ","u","ʈ","o","ɾ","h","f","p","a","c","ʊ","ʒ","ɪ","ʔ","aː"],
"th":["θ","tʰ","ˈt","tʃ","ð","tˈh","ɾt","th","et","tˈ","tʃˈ","to","ɯt","ʊd","ht","θo","t̪ˈh","ot","t̪ʰ"],
"tt":["tː","tt","tˈt","t̪ˈt","t̪t̪","et","ˈt","tːɯ","t̪t","tɯ","t̪ˈt̪","tˈ","ti","te","dˈt","ˈti","it","et̪","aˈ","dʒ","tˈc","tɛ","aʈ","ˈt̪","ɯˈ","ʔt","tˈt̪","lt","ʊt̪","t̪ˈ","dt","ˈtɯ","tˈl","ˈɛ","ɪt","ɑt","ʊt","ht","etʃ","ud","tt̪"],
"u":["u","ʊ","uˈ","uː","ɯ","o","y","ˈ","u'","n","ʉ","ʰ","ʏ","w","k","ɾ","oˈ","b","u̯","d","r","ɫ","ʃ","m","oː","u̞","j","s","ʌ","t","a","ɰ","z","i","l","ɑː","ɣ","ʒ","ɛ","ɯˈ","o̞","ɔ","ɜː"],
"uğ":["uɣ","uɰ","uɰˈ","udʒ","utʃ","ɯɰ","uˈ","uɯ","du","uɾ","ut","uɫ","uɯˈ","tu","ty","uːɫ","da","ɾu","uɣˈ","uːɰ","ug","ɯɰˈ","uˈɰ","ʊɰˈ","uːɾ","ʊɰ","ɫu","tuː","uˈɣ","ud","ʒɯ","aɰ"],
"v":["v","ʋ","vˈ","β","a","f","e","ˈ","i","ʊ","ɛ","ɪ","eː"],
"w":["v","w","ʋ","ʊ","ˈ","a","oː","u̯","ɯ","o","u","t"],
"woo":["uː","woo"],
"x":["ʃ","x","ks","k","χ","ɛç","ɾs","kˈ"],
"y":["j","jˈ","i","ɯ","e","ˈ","y","ɪ","l","ɯˈ","d","i̯","ɛ","ʒ","ˈj","a","iː","ɑ","m","ʝ","ʏ","ɫ","ʊ","jɑ","ʲ","u","ɾ","s","ɯn","ɲ","t","n","iˈ","ɪ̯","ʃ","ʰ","jo","ʔ","j'","o"],
"ya":["jɑ","ja","jɑˈ","jɑp","jɑɾ","jɑk","jɑn","j","jɑz","jaː","jɑɫ","jɑt","jaˈ","jɑː","jɑm","jɯ","jɑl","jɑɾˈ","jɑs","ɯjɑ","jaːˈ","jɑkˈ","ji","ʲa","je","ɑm","jɑdʒɑ","aˈ","jɑːˈ","jæ","ʝa","jɑj","ʏjɑ","ujɑ","ɑjɑ","jɑd","ʲɑ","ya","ˈj","ɯˈ","ijɑ","ʒɑ","ajɑ","an","ʝɑ","iɑ","ɯz","ɑn","iˈa","ʔɑ","di","lɑ","yɑ","ak","aɯ","i̯aːˈ","jb","jˈa","ˈa","i̯aˈ","sj","aˈt","yaˈ","jɯˈ","ɑb","mɑ","iˈ","iˈʒ","ɾa","nɑ","as","ˈjɑ","ɯkˈ","aj","ʲɑˈ","ij","ma","ɫa","ɯb","ʒa","ˈja","uj"],
"yo":["jɔ","jo","jɯ","joː","jɑ","lo","jɔˈ","on","iɯ","ʲo","ijo","ʲoˈ","so","jo'","sjo","oːɾ","ɫɯ","joʊ","jo̞","nɯ","ɾo","jˈjo","iˈjɶ","ujo","do","ɫo","ɯɫ","yo"],
"yor":["joɾ","jɯɾ","jor","jɔɾ","jo","jɯɾˈ","jorˈ","yoɾ","juɾ","ɯjoɾ","ˈoɾ","oɾɫ","ˈjor","jɔɾˈ","joɾɯ","oɾˈ","jos","joːɾ","ɯˈjoɾ","ˈjoɾ","yor","ɯɾˈ","joˈɾ","ɾɯɫ","ˈjɔɾ","ˈjo","ˈjɯɾ","jɯˈɾ","ɯjɯ","ɯɾɯ","ioɾ","ijoɾ","josˈ","ɯɾɫ","jur","jo̞ɾ","ˈuɾ","ˈjɯ","ijɯ","ujor","jʊɾ","ujoɾ","uˈɾ","ujorˈ","jɔs","ˈjɔ","ˈɾɯ","ʒoɾ","joɾd","ɯɾd","ujɾ","ɯˈɾ","joːr","jod","ɾɯd","jˈjoɾ","ˈor","jˈuɾ","ʝoɾ","jˈɾy","jɾo","jɑɾ","muj","ˈju","jo'r"],
"z":["z","zˈ","ʒ","ˈz","s","ˈ","ʃ","dʒ","ɯ","i","z̪","d","ɫ","ɑ","e","a","n","ʐ","m","j","ʑ","sˈ","d̪","u","ɾ"],
"zu":["zu","zuˈ","zʊ","зу","ʒu","zuː","uɾ","ur","mu"],
"â":["aː","ɑː","ɑ","ɑːˈ","a","æ","h"],
"ç":["tʃ","ʃ","t","ç","ˈ","ʧ","ˈdʒ","tˈ","dʒ","ɛ","e","ʲ","j"],
"ö":["ø","œ","øˈ","o","oː","ɶ","oˈ","ɔ","ö","ɤ","e"],
"öp":["œp","op","øpˈ","øp","oːp","kœ","œˈp","œpˈ"],
"û":["y"],
"ü":["y","u","ʏ","yˈ","ɯ","yː","uˈ","uː","ʏˈ","ʃ","ü","ɾ","n","ø","ʉ","d","r","t","m","ɰ","k","e","œ","iː","ʊ","ɯˈ","ɥ","uˌ","l","j","i"],
"ğ":["ɣ","ɟ","ɰ","ɾ","g","d","ʒ","ɯ","eː","y","ˈ","i","ɫ","c","ʝ","j","dʒ","n","ʃ","e","ʁ","m","ʊ","iː","aː","k","u","tʃ","ɑː","t","ɑ","l","ɰˈ","tʰ","o","ç","i̯","ŋ"],
"ı":["ɯ","ɯˈ","i","ɾ","ˈ","ɫ","iˈ","ʃ","m","z","j","n","k","iː","t","d","aː","a","c","o","l","b","ɰ","ɣ","ɑː","ʒ","s","i'","y","dʒ","ɲ","aˈ","ɟ","iˌ","ɯn","ı","jˈ","p"],
"ın":["ɯn","n","ɯ","ɯˈn","in","ɯnɫ","ɯnɯ","ˈn","nɯ","ɾɯn","iːn","yn","iˈn","iˈ","aɾ","da","ˈd","ɫ","ˈɾ","sɯn","ɯɫ","aɫ","ɯɾ","ɲɯ","dɑ","ˈɯn","ɾɯ","ˈl","ɯ̃nˈ","ˈɫ","ɣɯn","ɯŋ","ɾˈ","dʒɯn","ɯʃ","ɯˈɾ","ɯna","daː","ɯl","ɯˈ","aːnˈ","ɑɾ","aɰ","aɯn","ɑn","zɯn","mɯn","ɑːr","iɲ","nɑ","dʒ","ɯr","ˈr","aɳ","ɰɑ","ɯɳ","iŋ","ɾy","ɯj","ˈg","ɰɯn","ɑɳ","ɯɣ","on","aːɰ","ʒɯn","tɯn","dɯ","ˈɰ","zɯ"],
"ına":["ɯna","ɯnɑ","nɑ","ɯˈnɑ","ɯ̃","ɯnaː","ina","naː","iˈnɑ","ɯn","iːnɑ","naˈ","iˈn","ɯ̃na","ɯnaˈ"],
"ında":["ɯnˈdɑ","ɯnda","ɯnˈda","nˈdɑ","da","ɯnˈ","nˈda","nda","ɯˈda","ɯndɑ","ɯdɑ","ɯnˈd̪a","daɾɯ","ɯŋˈ","ɯnɯ","ɯɾɯ","ɯndɯ","nˈd̪a","ɫɑɾ","ɯnˈdɯ","ɯda","ɯnˈd","nɯz","danɯ","ɯndas","iˈda","ɯˈdɯ","ɯˈdɑ","ɯnd","ndɑ","nˈd","ɯˈcɯ","aɯnˈda","ɯɾɑ","ɯˈnˈdɑ","nˈdɯ","ɯða","ɯˈn","ɯnɑ","ɫɯnɯ","ɯdaɾ","ɫɑn","ɣɯnˈdɑ","ɾɯnda","ɯðɑ","ɾɯnɯ","ɯnˈd̪ɑ","niˈ"],
"ş":["ʃ","ʃe","ʃˈ","s","ˈ","ɯ","ɫ","ɑ","a","i","s̪","l","r","y","sˈ","eˈ","u","d"],
"şm":["ʃm","m","sm","ʃˈm","s","ɯʃ","u","ˈm","ʃɯ","ʏʃ","ʃ'","ʉʃ","ʃˈ","sl","iʃ","lɛ","ɫˈm"],
"şt":["ʃt","t","ʃˈt","st","ʃtʰ","tɯ","sˈt","tʰ","ti","ʃt̪","ɯʃ","s̪t̪","iɾ","iʈ","s̪t","tʃ","ʃˈtʰ","uʃ","ɯɾ","it","sd","ir","iʃ","lɛ","ˈʃ","ʃi","ʃtˈ","us","sˈtʰ","şt"]},"SrcMulti":null,"DstMulti":null,"SrcMultiSuffix":null,"DstMultiSuffix":["ː"],
"DropLast":null,"DstMultiPrefix":["ˈ","'","ˌ"],
"PrePhonWordSteps":[{"ToLower":true}],
"SplitBefore":null,"SplitAfter":null,"IsDuplex":false,"IsSrcSurround":false}