{"Map":{"к¶Б":["≈Л"],
"к¶В":["r"],
"к¶Г":["h"],
"к¶Д":["a"],
"к¶Ж":["i"],
"к¶Й":["r…Щ"],
"к¶К":["l…Щ"],
"к¶П":["ka","k…Ф","k","…Фk…Ф","ak"," М Ф М"],
"к¶Пк¶ґ":["ki"],
"к¶Пк¶Є":["ku","k К"],
"к¶Пк¶Ї":["k…Ы"],
"к¶Пк¶Љ":["k…Щ"],
"к¶Пк¶њ":["kra","kr…Ф"],
"к¶ПкІА":["k","ak"," Ф"],
"к¶Т":["g"],
"к¶Тк¶Љ":["g…Щ","ag…Щ"],
"к¶Тк¶Њ":["gj…Ф"],
"к¶ТкІА":["k","g"],
"к¶Ф":["≈Л"],
"к¶Фк¶Ї":["a≈Лe","≈Лe"],
"к¶Х":["t Гa","t Г…Ф"],
"к¶Хк¶ґ":["t Гi"],
"к¶Хк¶Є":["t Гu"],
"к¶Хк¶Їк¶і":["t Гo"],
"к¶Хк¶Љ":["t Г…Щ"],
"к¶Ч":["d Тa","d Т","d Т…Ф","ja","j…Ф","ad Т","ad Тa"],
"к¶Чк¶ґ":["ad Т…™"],
"к¶Чк¶Є":["d Тu"],
"к¶Ъ":["…≤"],
"к¶ЪкІА":["an","n"],
"к¶ЪкІАк¶Х":["nt Гa"],
"к¶ЪкІАк¶Чк¶Љ":["a…≤d Т…Щ"],
"к¶Ы":[" И"],
"к¶Э":["…Цa","…Ц","da"],
"к¶Эк¶Є":["…Цu","adu","a…Цu","…Ц К"],
"к¶†":["t"],
"к¶†к¶ґк¶Б":["ati≈Л"],
"к¶†к¶Є":["tu","t К"],
"к¶†к¶Њ":["tj…Ф"],
"к¶†к¶њ":["tr…Ф"],
"к¶†кІА":["t"],
"к¶Ґ":["d…Ф","da","ad…Ф","dћ™"],
"к¶Ґк¶В":["dћ™ar"],
"к¶Ґк¶ґ":["di","adi"],
"к¶Ґк¶ґк¶†к¶Њ":["aditja"],
"к¶Ґк¶Є":["du","nd К"],
"к¶Ґк¶Єк¶±к¶Є":["d Кs К"],
"к¶Ґк¶Ї":["d…Ы"],
"к¶Ґк¶Љ":["d…Щ"],
"к¶Ґк¶Њ":["dj…Ф"],
"к¶Ґк¶њ":["dr…Ф","dr"],
"к¶ҐкІА":["t"],
"к¶£":["…Ц"],
"к¶§":["n"],
"к¶§к¶ґ":["ani","ni","n…™"],
"к¶§к¶Ї":["ane","an…Ы"],
"к¶§кІА":["n","an","a"],
"к¶•":["p"],
"к¶•к¶ґ":["api","p…™"],
"к¶•кІА":["p","pћЪ"],
"к¶І":["ba","b…Ф","b"],
"к¶Ік¶ґ":["bi"],
"к¶Ік¶Є":["bu","b К","bu Ф"],
"к¶Ік¶Ї":["b…Ы","ab…Ыh","be"],
"к¶Ік¶Їк¶і":["bo"],
"к¶Ік¶Їк¶ік¶Б":["w…Ф≈Л"],
"к¶Ік¶Љ":["b…Щ"],
"к¶Ік¶њ":["bra"],
"к¶ІкІА":["ap"],
"к¶©":["m"],
"к¶©к¶Є":["mu","m К","amu"],
"к¶©к¶Їк¶і":["m…Ф","amo"],
"к¶©к¶Љ":["m…Щ","am…Щ"],
"к¶©кІА":["m"],
"к¶™":["j…Ф","ja","aj"],
"к¶™к¶Єк¶™":["juj"],
"к¶™к¶Љ":["j…Щ"],
"к¶Ђ":["ra","r…Ф","…Фr…Ф","ar","r","a"],
"к¶Ђк¶ґ":["ri","ari","r…™"],
"к¶Ђк¶Є":["ru","r К","aru","ar К"],
"к¶≠":["l"],
"к¶≠к¶ґ":["ali","l…™","al…™"],
"к¶≠к¶Є":["lu","l К","alu"],
"к¶≠кІА":["l"],
"к¶Ѓ":["w"],
"к¶Ѓк¶В":["war"],
"к¶Ѓк¶Є":["wu","w К","awu","aw К"],
"к¶Ѓк¶Їк¶і":["w…Ф","aw…Ф","wo"],
"к¶±":["s"],
"к¶±к¶Б":["asa≈Л"],
"к¶±к¶ґ":["si"],
"к¶±к¶Є":["su","s К","as К"],
"к¶±к¶Ї":["ase","as…Ы","se","s…Ы"],
"к¶±к¶Їк¶і":["so","as…Ф"],
"к¶±кІА":["s","as"],
"к¶≤":["a","h","…Ф"],
"к¶≤к¶ґ":["i","…™"],
"к¶≤к¶Є":["u","hu"," К"],
"к¶≤к¶Єк¶Б":[" К≈Л"],
"к¶≤к¶Ї":["…Ы","e"],
"к¶≤к¶Їк¶і":["o"],
"к¶≤к¶Љ":["…Щ"],
"к¶ґ":["i","…™"],
"к¶Є":["u"," К"],
"к¶Ї":["e","…Ы"],
"к¶Їк¶і":["…Ф","o"],
"к¶Љ":["…Щ","u"],
"к¶љ":["r…Щ"],
"к¶њ":["ra","r М"],
"к¶њк¶ґ":["ri"],
"к¶њк¶Є":["r К"],
"к¶њк¶Ї":["r…Ы"],
"к¶њк¶Їк¶і":["ro"],
"к¶њк¶Їк¶ік¶†к¶Їк¶і":["roto Ф"],
"кІАк¶К":["l…Щ"],
"кІАк¶Кк¶Ґ":["l…Щdћ™"]},"SrcMulti":null,"DstMulti":null,"SrcMultiSuffix":null,"DstMultiSuffix":["ЋР"],
"DropLast":null,"DstMultiPrefix":["ЋИ","'","ЋМ"],
"PrePhonWordSteps":[{"ToLower":true}],
"SplitBefore":null,"SplitAfter":null,"SplitAt":null,"IsDuplex":false,"IsSrcSurround":false,"SrcDuplicate":null}