{"Map":{"a":["a"],
"ar":["ɑː"],
"b":["b̥"],
"d":["ˀ","ð"],
"e":["ə","ɛ"],
"er":["ɐ","ɛɐ̯"],
"f":["f"],
"g":["g̊"],
"h":["h"],
"i":["i","e"],
"k":["g̊","kʰ"],
"krog":["kʰʁɔwˀ"],
"l":["l"],
"m":["m"],
"n":["n"],
"ng":["ŋ","ng̊"],
"o":["ʌ","o"],
"p":["pʰ","b̥"],
"r":["ɐ̯","ʁ̥"],
"ra":["ʁɑ"],
"s":["s"],
"t":["d̥","tˢ"],
"u":["u"],
"v":["ʋ"],
"y":["y"],
"æ":["ɛ","ɛːˀ"],
"ø":["ø"]},"SrcMulti":null,"DstMulti":null,"SrcMultiSuffix":null,"DstMultiSuffix":["ː"],
"DropLast":null,"DstMultiPrefix":null,"PrePhonWordSteps":[{"ToLower":true}],
"SplitBefore":["-"],
"SplitAfter":null,"SplitAt":null,"IsDuplex":false,"IsSrcSurround":false,"SrcDuplicate":null}