{"Map":{"'":["ˈ","w","ə"],
"'au":["o"],
"'em":["ɑ̃","ˈɛm"],
"'en":["ɑ̃","ˈɛn"],
"'ex":["ɛks","ɛgz"],
"'im":["ɛ̃","ˈim"],
"'in":["ɛ̃"],
"'ou":["u"],
"-":["t","l","a","-","z","ʁ","k","i","d","ɔ̃"],
"2o":["aʃ"],
"a":["a","ˈ","t","aˈ","tˈ","-","ə","eɪ","iː","e","w","jˈ","ɐ","ɛ"],
"ach":["aʃ","aʃˈ","ʃˈ","ˈak"],
"ai":["ɛ","e","ˈa","tˈ","tˈɛ","eɪ","ˈɛ","tˈa","tɛ","aj","ta","jˈɛ"],
"ais":["ɛ","ɛzˈ","ɛz","tˈɛ","tɛz","eɪz"],
"ait":["ɛ","ɛtˈ","ɛt","tˈɛ"],
"am":["am","ɑ̃","amˈ","ˈa","eɪm","əm","iːm","tˈa","ˈɑ̃","ta","ɐmˈ"],
"an":["ɑ̃","an","anˈ","ˈa","ˈɑ̃","ən","aŋ","jˈa","iːn","eɪn","tˈɑ̃","tˈa","tɑ̃","ɐnˈ","ta"],
"ant":["ɑ̃","ɑ̃t","ɑ̃tˈ","ɑ̃s","tɑ̃t","wɑ̃t","tɑ̃tˈ","ant","wɑ̃tˈ"],
"ants":["ɑ̃","ɑ̃t"],
"aqu":["akˈ","ak","kˈ"],
"ation":["asjˈɔ̃","asjon","asjɔn","asjonˈ"],
"au":["o","ˈo","tˈ","ˈɔ"],
"aud":["o","od","odˈ"],
"ault":["o"],
"aux":["o","oks","ok"],
"ay":["ɛ","ɛjˈ","ɛj","ɛi","eɪ","ajˈ","ɛˈ","ai"],
"aî":["ɛ"],
"b":["b","bˈ"],
"c":["k","s","kˈ","sˈ","i","a","ɛ","ʁ","ˈ","ɔ","y","t"],
"ch":["ʃ","ʃˈ","tʃ","ʁʃ","ɛʃ","kˈ","ka"],
"cha":["ʃa","ʃˈ","ʃˈa","tʃa","tʃˈ","ʃaˈ","kaˈ"],
"che":["ʃ","ʃə","ʃˈ","ʃɛ","ʃˈɛ","ʁʃʁ","ʃˈœ","ʁʃə","tʃˈ","tʃɪ","ʃˈe","tʃə","ʃe"],
"ches":["ʃ","ʃˈ","ʃɛs","ʃɛ"],
"com":["kɔ̃","ɔ̃","kom","komˈ","kˈɔ̃"],
"cou":["ku","u","kˈu","kwˈ","kw","kˈaʊ","kaʊ","kˈʌ"],
"d":["d","dˈ","a","i","ʁ","ɛ"],
"di":["di","dˈ","djˈ","dj","dˈi","dɪ","dˈɪ"],
"dé":["de","deˈ","dˈ"],
"e":["ɛ","t","ʁ","i","ˈ","e","ə","z","l","s","n","d","y","j","p","m","ɪ","a","œ","o"],
"eau":["o","ˈo"],
"em":["ɑ̃","əm","əmˈ","tmˈ","ɛm","tɑ̃","em","ɪmˈ","ˈɑ̃","smˈ","emˈ","dmˈ","sɑ̃"],
"ement":["mˈɑ̃","əmɑ̃","əmˈɑ̃","tmˈɑ̃","əmɑ̃tˈ"],
"en":["ɑ̃","ɛ̃","nˈ","ɛʁ","ən","ənˈ","tɑ̃","ɛn","ˈɛ","tnˈ","jˈ","tn","ˈɑ̃","jɛ̃","tˈ","en","jɛ","enˈ","ɛŋ","tɛ","snˈ"],
"ens":["ɑ̃s","ɛ̃","ɑ̃sˈ","sɑ̃s","ɛ̃s","ɛns"],
"ent":["ɑ̃","ɑ̃t","ɑ̃tˈ","ɑ̃s","tɑ̃t","tɑ̃tˈ","sɑ̃t","sɑ̃tˈ","tɑ̃s","ɛ̃tˈ","ɛntˈ","ɛ̃t","ˈɑ̃t"],
"ents":["ɑ̃"],
"er":["e","ɛʁ","ʁˈ","ˈɛ","əʁˈ","əʁ","tʁˈ","tʁ","jˈ","ˈɜː","eʁˈ","tɛ","eʁ","jʁˈ","ʁi","əɹ","tˈ","zʁˈ","iə","jʁ","ˈə","sˈ","tə","ʁa","zˈ","dʁ","ˈœ","ɪə","zʁ","ˈɑː"],
"eu":["œ","ø","tˈ","jˈ","ˈœ","zˈ","ˈø","sˈ","jø","ˈy","œˈ"],
"eux":["ø","øz","øks","øksˈ"],
"ez":["e","əz","əzˈ","ɛz"],
"ez-":["ˈe","el","ez"],
"f":["f","fˈ"],
"fs":["if","fsˈ","fʃ"],
"g":["g","ʒ","ʒˈ","gˈ"],
"ge":["ʒˈ","aʒ","ʒʁ","ʒə","ʁʒ","ʒɛ","ʒˈɛ","ʒl","ʒˈe","ʒi","ʒn","gˈɛ"],
"ges":["aʒ","ʒɛs","ʒˈɛ","ʒˈɛs"],
"gn":["ɲˈ","ɲ","gn","gnˈ"],
"gne":["ɲ","ɲə-","ɲˈ","ɲˈe"],
"gnent":["ɲ"],
"gnes":["ɲ","ɲˈ"],
"h":["ˈ","a","k","ʃ","hˈ"],
"i":["i","ˈ","jˈ","j","iˈ","ɛ","ɪ","t","tˈ","s","iː","a"],
"i-":["ˈi","tˈi","it","iʁ","ik","il"],
"ign":["iɲˈ","iɲ","ɲˈ","ɛɲˈ"],
"im":["im","ɛ̃","imˈ","ɪm"],
"in":["ɛ̃","in","inˈ","tˈ","tɛ̃","ɪŋ","ɪn","ˈɛ̃","tˈɛ̃","ɪnˈ"],
"ins":["ɛ̃","ɛ̃s","ɛ̃sˈ"],
"ion":["jˈɔ̃","jɔn","jon","jonˈ","sjɔ","tjɔ","iˈɔ̃","ˈɔ̃","jɔ̃","ionˈ","ion","sjˈ","tjˈ"],
"j":["ʒ","ʒˈ"],
"k":["k","kˈ"],
"l":["l","lˈ","ɛ","i","ɔ","y","a","ˈ","j","ˈɛl","k","ɪ"],
"le":["lə","al","lɛ","lˈ","ə-","lʁ","lˈɛ","le","il","yl","ˈa","lˈe","lt","kl","lˈə","ɛl","lˈi","ˈɛ","li","ɔl","ɪl","ˈi","ˈe","lœ"],
"ll":["lˈ","jˈ","j","lj","ˈɛ","ɪl","ɛl","ijˈ","ij","ll","alˈ","ˈi","li","al","ilˈ","ˈɔ","la","ɛlˈ","il","ly"],
"lle":["j","lˈɛ","jˈ","ˈɛl","jə","ˈij","alʁ","lˈe","ɪlə","ˈal","alˈe","alɛ","ijˈ"],
"lles":["j","jˈ"],
"m":["m","mˈ","a","ɑ̃"],
"me":["mɛ","sm","mə","im","ʁm","mˈ","ɛm","mˈɛ","mʁ","mn","me","mˈe"],
"n":["n","nˈ","ˈ","ɛ","ɛ̃","ʁ","a","ɑ̃","ŋ","ɔ","ɔ̃","y"],
"ne":["in","nə","nˈ","nʁ","ˈɛ","nɛ","nˈɛ","ɛn","ˈe","ʁn","nl","ne","nˈe","nɪ","ɛʁ","an","ˈə"],
"ng":["ŋ"],
"nt":["ʁ","ɑ̃tˈ","ɑ̃t","nt","ntˈ"],
"o":["o","ɔ","ˈ","w","wˈ","ɒ","ə","uː","ʊ","ɔˈ","ɔ̃","j","t"],
"o-":["ˈo","ok","ot","ol"],
"oi":["wa","wˈ","wˈa","wˌa","waˈ","ɔɪ"],
"oie":["wˈa","waʁ"],
"ois":["wˈa","waz","wazˈ","was","wˈas"],
"om":["om","ɔ̃","omˈ","ɔm","ɒm","əm","ʊm"],
"on":["ɔ̃","on","ɔn","onˈ","ˈɔ","tɔ","jɔ","ən","tˈ","ˈɔ̃","ɒn","jˈ","uːn","tɔ̃","ɒŋ","ənˈ"],
"ons":["ɔ̃","ɔ̃s","ɔ̃sˈ","ɒns"],
"ont":["ɔ̃","ɔ̃t","ɔ̃tˈ","ɒnt","ɔ̃s"],
"ou":["u","w","wˈ","aʊ","tu","ˈu","tˈ","ˈʌ"],
"ous":["u","us","uzˈ","uz","ˈus"],
"oux":["u","uk","uksˈ","uks"],
"oy":["wajˈ","waj","wa","wˈ","wˈa","ɔjˈ","ɔɪ","ɔj"],
"oû":["u"],
"p":["p","pˈ","a","i"],
"ph":["f","fˈ"],
"phe":["f","fˈɛ","fə","fˈ"],
"pré":["pʁe","pɹˈeɪ","pʁˈ"],
"q":["k"],
"qu":["k","kˈ"],
"que":["k","kə","kˈ","kɛ","kˈe","kˈɛ"],
"ques":["k","kɛ","kɛs","kˈɛ","kzˈ"],
"r":["ʁ","ʁˈ","ˈ","a","ɔ","y","ɛ","ɹ","ɹˈ","œ","i","ɑː","ɜː","d","ə","u"],
"rd":["aʁ","ʁd","ʁdˈ","a","ɔ","ɔʁ","ɛʁ","yʁ","əd","ɑːd"],
"re":["ʁə","ʁɛ","tʁ","ʁˈ","iʁ","ʁʁ","ʁˈɛ","ʁˈe","yʁ","aʁ","ɹˈ","ˈɛ","ˈe","ʁt","ɛʁ","ɹˈɛ","ˈi","ɹˈi","ɹɪ","dʁ","ʁn","ʁe","əl","ət","ən","ɹə","ɹi","ʁd","ʁˈə","ˈa"],
"ré":["ʁe","ʁˈ","ʁeˈ","ɹˈeɪ","ɹeɪ","ʁˈe"],
"s":["s","z","i","zˈ","ʁ","sˈ","a","y","o","l","ɛ","ɔ","n","e","t","ø","k","d","ʃ","-","ˈ","p","m"],
"sou":["su","u","sˈu","zu","zˈu","sˈaʊ","swˈ","sw","saʊ"],
"ss":["sˈ","si","isˈ","ɛs","as","sɛ","asˈ","ˈa","is","ɛsˈ","ˈɛ","ˈi","sl"],
"t":["t","tˈ","s","ɛ","i","ˈ","a","ʁ","o","y","ɔ","k","l"],
"th":["θ","tˈ"],
"u":["y","ˈ","yˈ","ɔ","ʌ","œ","ø","u"],
"un":["yn","œ̃","ynˈ","ˈy","ʌn","ʌŋ"],
"v":["v","vˈ"],
"ve":["vɛ","iv","vˈ","və","vn","vʁ","av","vˈɛ","ɛv","vl","vˈe","vt","vd","ve"],
"vi":["vi","vˈ","vj","vjˈ","vˈi","vɪ","vˈɪ"],
"w":["w","wˈ"],
"x":["ks","gz","z","k","ksˈ","sˈ"],
"y":["i","ɛ","ˈ","j","jˈ","a","ɪ"],
"z":["z","zˈ","s"],
"à":["a"],
"â":["a","aː"],
"ât":["aː","at","atˈ"],
"æ":["a"],
"ç":["sˈ","s"],
"è":["ˈ","ɛ"],
"èr":["ˈ","ˈɛ","ɛʁ","ɛʁˈ"],
"é":["e","ˈ","eˈ","eɪ"],
"ê":["ɛ","ˈ"],
"ë":["ɛ"],
"î":["i","ˈ"],
"ï":["i","j"],
"ñ":["ɲ"],
"ô":["o"],
"û":["y"],
"œ":["ˈ"],
"’":["ˈ"]},"SrcMulti":null,"DstMulti":null,"SrcMultiSuffix":null,"DstMultiSuffix":["ː"],
"DropLast":["f","p","d","e","t","s","g","te","m","n","l","x"],
"DstMultiPrefix":["ˈ","'","ˌ"],
"PrePhonWordSteps":[{"ToLower":true}],
"SplitBefore":["-"],
"SplitAfter":null,"SplitAt":null,"IsDuplex":false,"IsSrcSurround":false,"SrcDuplicate":null}