{"Map":{"a":["a","la","ra","ma","sa","l","na","n","m","s","ar","g","b","r","t","-","d"],
"ar":["ar","mar","sar","lar","va","arr","rr","rar","rn"],
"at":["at","att","art","rt","ba","mat","tt","ts"],
"atˌ":["at"],
"atː":["att"],
"b":["b","l","s","e","n","g"],
"bə":["be","bä","ber","bel","sb","eb","ben","bb","lb"],
"bˈ":["ba","-b"],
"d":["d","dd","-","ds"],
"deːr":["de","dder"],
"ds":["ds","dd","dds","dss","d-"],
"də":["de","dde","dä","ddä","der"],
"dʒ":["ge"],
"dˈeː":["de"],
"dˈɛ":["de","dä","des","dep","den","-de"],
"dˌ":["ed"],
"dˌeː":["de"],
"dˌɛ":["de","dä"],
"eː":["e","et","x"],
"eːd":["ed","led"],
"eːr":["er","mer","era"],
"eːrˌ":["ler"],
"f":["f","ff","lf","a","s","n"],
"fˈ":["ff","fa","lf","-f","fe"],
"fˈuː":["fo","-fo"],
"fˈœ":["fö","lfö","sfö","föl","-fö"],
"fˌ":["sf","fa","ef"],
"g":["g","i","s","e"],
"gə":["ge","gge"],
"gˌ":["gg","lg","eg","ga","ig"],
"h":["h"],
"hˌ":["eh","nh","th","ha","lh"],
"iː":["i","ri","li","ic","-","il","l"],
"iːl":["il"],
"iːˌ":["i","ia"],
"j":["j","g","hj","dj","sj","l"],
"jøː":["gö","jö"],
"jə":["ge","je","gä","jä","hjär","hjä","ges","gen"],
"jˈ":["lj","hj","jä","gä","gj","-hj","pj"],
"jˈeː":["ge","je"],
"jˈuː":["jo","hjo","-jo"],
"jˈuːr":["jor","gjor","hjor"],
"jˌ":["sj","gj","hj","rhj","lg"],
"jˌeː":["ge"],
"k":["k","ck","g","c","-k","q","sk","x","a","ks","s"],
"ko":["lko"],
"ks":["x","ks","kt","ck","cc","cks","kc","ct","kss","c-"],
"kə":["k","ke","cke","kä","kär","ker","e-"],
"kˌ":["k","lk","sk","-k"],
"kː":["ck"],
"l":["l","el","b","la","li","-","g","n","sl","s"],
"lk":["lk"],
"lt":["lt","llt","-t"],
"ltiː":["lti","llti","lti-"],
"løː":["lö"],
"lɑː":["la","sla","lla","lag","bla"],
"lɔ":["lo","lop","los","llo","lå"],
"lˈ":["lä","-l","sl"],
"lˈa":["la","las","lad","-la","lab","lag","lam","lan"],
"lˈoː":["lo","lå","llo","glo"],
"lˈuː":["lo","slo"],
"lˈøː":["lö"],
"lˈɑː":["la"],
"lˈɔ":["lo","lå","los","log","lob"],
"lˌa":["la","lla","las","bla","sla","lag"],
"lˌɑː":["la","lla","sla"],
"m":["m","ma","l","s","-","g","e","r","t","n"],
"meːdˌɛ":["mede","lmed"],
"mə":["me","mä","mme","lmä","mel","gmä","nmä"],
"mɪt":["mitt"],
"mˈeː":["me","mé"],
"mˈɛ":["mä","me","män","mel","mäs","mär","-me"],
"mˈɵ":["mu","mun","-mu"],
"mˌeː":["me"],
"n":["n","s","-","l","g","e","a","b","t","d"],
"na":["na","nna","gna","lna","sna"],
"nuː":["no","no-","non"],
"nɪŋsf":["ningsf","nningsf"],
"nˈ":["n"],
"nˈa":["na","nab","nag","nna","nar","nall","nal"],
"nˈuː":["no","nor"],
"nˌeːr":["ne","nner"],
"nˌɪ":["ni","nni","gni","sni","lni","bni","ttni"],
"oː":["å","o","au"],
"oːdˈeː":["d"],
"oːgˈeː":["g"],
"oːl":["ål"],
"oːn":["ån","on","må","ånd"],
"oːˈ":["f"],
"p":["p","pp","-","a"],
"pl":["pl","ppl","rpl","sp","ppla"],
"pr":["pr","ppr"],
"puː":["po","por","ppo"],
"pˈeːl":["pel","spel"],
"pˈuː":["po","-po"],
"pˌ":["pp","pa","sp"],
"pˌuː":["po"],
"r":["r","ra","l","g","k","t","n","f","b","i","d"],
"rl":["rl","rr","rla","rli"],
"rn":["rn","rr","ar","nn","ur"],
"røː":["rö"],
"rə":["re","rä","res","rr","gr","br","ren"],
"rɪ":["ri","rri","lri","ril","nri"],
"rˈ":["ra","-r","pr","ri"],
"rˈiː":["ri","ris","rin"],
"rˈøː":["rö","röd"],
"rˈœ":["rö"],
"rˈɑː":["ra","-ra"],
"rˈɛ":["rä","re","res","rep","ren","red","rän","-re"],
"rˈɪ":["ri","ril","ris"],
"s":["s","c","sa","z","-","e","l","n","g","t","p"],
"sf":["sf","sfa","ce","ssf","ls"],
"siːd":["sid","bsid"],
"sk":["sk","ssk","lsk","sc","esk","nsk","gsk","sq","-sk"],
"skˌ":["sk","ssk","lsk","esk","gsk"],
"sl":["sl","ssl","gs","esl","gsl","ns"],
"sm":["sm","sma","ss","es","ls"],
"st":["st","lst","sst","t-","te","ta","est","gst","ts","-st","bst","nst"],
"stˈɛlnɪŋ":["ställning"],
"suː":["so","zo"],
"sv":["sv","esv","lsv","-sv","sw"],
"sx":["sk","ti","sj","si","ssi","sh","lsk","rti","ch","stj","-sk","nsk","gsk"],
"sxʊ":["jou"],
"sxˈ":["j","stj","-ch","sja"],
"sə":["se","ce","sä","sse","ä","sed","cel","en","ze","sel"],
"sɪt":["sit","cit","sitt"],
"sˈa":["sa","sam","sab","ssa","san"],
"sˈeː":["se","ce","ze","c-","-se"],
"sˈuː":["so","zo"],
"sˈɑː":["sa"],
"sˈɛ":["sä","se","ce","cel","sse","ces","-se","-ce"],
"sˌa":["sa","ssa","esa","nsa"],
"sˌɛ":["se","sä","ce","ssä","cel","sel","ces","ese","sse"],
"sˌɪ":["ci","si","ssi","cei","zi","esi"],
"t":["t","tt","rt","st","lt","-","s","e","r","pt","ä","a"],
"ta":["ta","rta","tar","as","al","gta"],
"trˌiː":["tri","rtri"],
"tˈ":["te","tä","rt","ta","lt","-t","t-"],
"tˈɪ":["til","ti"],
"tˌ":["te","st","rt","tä","stä","et","ta","rte"],
"tˌeː":["te","rte","ste","tet"],
"tˌɪ":["ti","til","rti"],
"tː":["tt","ät","rtt"],
"tːə":["tte","tter","e-"],
"u":["no"],
"uː":["o","lo","o-","bo","os","-","ot","t"],
"uːr":["or","jor","nor","bor"],
"v":["v","w","sv","s","l"],
"vˈ":["va","vi","nv"],
"vˌ":["v","va"],
"vˌɛ":["vä","ve","sve","svä","web"],
"w":["u"],
"x":["i","k","tj"],
"xˈ":["si"],
"xˌ":["k","j"],
"y":["y"],
"ys":["ys","sy"],
"yː":["y"],
"z":["zz"],
"ø":["gö"],
"øː":["ö"],
"øːr":["ör","er","gö"],
"ŋ":["ng","n","g"],
"ŋsf":["ngsf","ngsfa","ingsf"],
"œ":["ö"],
"ɑː":["a","ar","al","ra","so","at"],
"ɑːl":["al"],
"ɑːr":["ar","bar"],
"ɑːrn":["ar","arn","arns","arn-"],
"ɔ":["o","å","ål","so","au","om"],
"ɔm":["om","omm","oms","som"],
"ɕ":["k","skj","tj","rtj"],
"ɕən":["kän","tjän","än","rtjän","jän"],
"ɕˈ":["tj","kä","kj"],
"ə":["e","ä","er","le","ne","är","en","me","äm","n","p","s","r","mä","äl"],
"əh":["neh","eh","leh"],
"əl":["el","äll","ell","äl","bel","nel","lel","eli"],
"ən":["en","än","nen","len","ern"],
"ər":["er","är","ler","ärr","ner","er-","ver","err"],
"ərˌiː":["eri","leri","erri"],
"əs":["ec","es","nes","re","le","mä","äs"],
"əsp":["esp","resp"],
"ɛ":["ä","e","r","n","c","l","t","p","m","g","s","b","tt","v",":","d","f"],
"ɛd":["ed","dd","edf"],
"ɛs":["äs","es","äpo","k"],
"ɛː":["ä","är","e","rä","rt","mä","nä","sä","rs","vä","to","lä"],
"ɪ":["i","ni","li","il","is","m","r","ri","a"],
"ɪl":["il","ill","ils"],
"ɪs":["is","ic","si","iss","iz"],
"ɵ":["u"],
"ɵn":["un","mu"],
"ɵp":["upp","up","ru"],
"ɵː":["u"],
"ʂ":["rs","s","r"],
"ʂt":["rst","st","rs","rsst"],
"ʃ":["ch","sch","rs","e"],
"ʃˌ":["sch"],
"ʉ":["u"],
"ʊ":["o","so"],
"ˈ":["s"],
"ˈa":["a","as","al","av","an","ag","am","e","ar","ma","ab","att","ss","ra"],
"ˈaf":["af","ff","aff","ff-"],
"ˈaj":["aj","j:t","ui"],
"ˈaltɪŋ":["allting"],
"ˈar":["ar","arr"],
"ˈat":["at","art","att"],
"ˈatː":["att"],
"ˈeː":["e","é","-","en","/o","se","v",")","-e","h","ê","et"],
"ˈiː":["i","si","in","if","mi","is","il","it"],
"ˈoː":["å","o","å-","ål","ås","on","lo"],
"ˈoːl":["ål"],
"ˈoːʂklas":["årsklass"],
"ˈu":["lo"],
"ˈuː":["o","o-","o:s"],
"ˈuːm":["om"],
"ˈuːr":["or"],
"ˈy":["y","sy"],
"ˈøː":["ö","ö-","ön"],
"ˈøːr":["ör","er"],
"ˈøːveːʂˌɛtnɪŋ":["översättning"],
"ˈœ":["ö","lö","sö","mö"],
"ˈɑ":["a"],
"ˈɑː":["a","ar","al","-a","ag","da","at","an"],
"ˈɒv":["of"],
"ˈɔ":["o","å","ål","au","so","po","-au"],
"ˈɔk":["ok","ock","auk","h"],
"ˈɔm":["om","omm"],
"ˈɛ":["ä","e","er","är","än","es","en","äg","em","äm","ep","äc","ef","äp","ed","äs","eg","äd","pe","mä","-e","mf","s:"],
"ˈɛl":["äl","el","äll","ell","ält"],
"ˈɛʃ":["äsch","esch"],
"ˈɛː":["äs","ä-","ef","äl"],
"ˈɪ":["i","is","il","g","im","b","v","-in","ia","-i"],
"ˈɵ":["u","-u"],
"ˈɵpf":["uppf"],
"ˈʉ":["u","-u","u:s"],
"ˈʊ":["on"],
"ˌ":["r","s","b","l","m","n","a","e"],
"ˌa":["a","na","ra","ma","ga","sa","la","ta","al","as","ag","an","am","ea","ar","ba","tra"],
"ˌadə":["ade","nade"],
"ˌat":["at","att","art","rat","gat"],
"ˌatː":["att"],
"ˌe":["se","me"],
"ˌeː":["e","le","re","et"],
"ˌeːdˈeː":["d"],
"ˌeːhˈoː":["h"],
"ˌeːpˈeː":["p"],
"ˌeːsˈeː":["c"],
"ˌeːsˌeː":["c"],
"ˌeːvˈeː":["v","v:n"],
"ˌiː":["i","ni","si","li","in"],
"ˌo":["o"],
"ˌoː":["å","rå","lå","så","bå"],
"ˌoːl":["ål","ol","sål"],
"ˌuː":["o","o-","ro","bo","lo","jo","so"],
"ˌy":["y","yd","ey","ny","sy"],
"ˌø":["ö"],
"ˌøː":["lö","gö","sö","öt","fö","rö"],
"ˌɑː":["a","sa","ba"],
"ˌɔ":["o","so","no","au","ro","sål","eo","lo","om"],
"ˌɔm":["om","som","oms","omm","lom"],
"ˌɔː":["o"],
"ˌɛ":["e","ä","el","äl","än","äg","es","rä","äs","ne","me","re","är","äf","en","nä","le","mä","se","sä","er","et"],
"ˌɪ":["i","ni","il","li","ri","g","sil"],
"ˌɵ":["u","um","su","ru","nu","lu"],
"ː":["t","d","s","o","n","f"],
"ːd":["d"],
"ːg":["g"],
"ːk":["k"],
"ːl":["l","l-"],
"ːm":["m"],
"ːn":["n"],
"ːni":["ni"],
"ːr":["r","rl","r-","är","ra"],
"ːrəs":["res"],
"ːʂ":["rs"]},"SrcMulti":null,"DstMulti":null,"SrcMultiSuffix":["ː"],
"DstMultiSuffix":null,"DropLast":null,"DstMultiPrefix":null,"PrePhonWordSteps":[{"ToLower":true}],
"SplitBefore":null,"SplitAfter":null,"SplitAt":null,"IsDuplex":false,"IsSrcSurround":false,"SrcDuplicate":null}