{"Map":{"":[""],
"a":["་","པ","བ","ག","མ","འ","ར","ད","ལ","ས","༔","་འ","་བ","་མ","རྒྱ","་ད","་ག","ཀ","་པ","་ལ","ན","ྭ","ང","ར་","ཨ","བྱ","ཟླ","རྣ","་ཐ","ཐ","ཡ","་ན","ཏ","ཆ","གྲ","ཞ","རྡ","ལྟ","ཧ","ལྔ","སྐྱ","དྲ","རྩ","སྐ","ཙ","ཟ","ཕ","དུ","ཐའ","ཀྲ","ཇ","ཤ","ཅ","ཝ","ཁྱ","བླ","ཛྲ","ཝཱ","རྟ","ཌཱ","ཧཱ","སྣ","མཐའ","ཚ","ལྷ","རྦ","ན༔","་ལྔ","་་","སྔ","སྩ"],
"ab":["བ","བ་","བས་","བས","རབ","ས་","དབ","ས་བ","སྐྱབ","རྡབ","་བ","རྒྱབ","ག་","བ་བ","ཨ་","་འ","རྡབས"],
"abja":["བ་འབྱམ","བ་འབྱ","་འབྱམ"],
"abyu":["བས་ཡུལ","བས་ཡུ"],
"ak":["ག","ག་","གས་","གག","གས","དྲག","བག","གགས","་བདག","ཨ་","ག་འ","ཨག","གས༔","ས་","བ་","གྲག","་དཔ","འག","ཀྲག","་ཀ","་སྐ","ག་མ","རག","་བ","ག་ད","ཆགས","འ་","ཨ་ད","་པ"],
"al":["ལ","ལ་","གལ","རལ","་བླ","རྡལ","ལ༔","་ལ","བ་","གྲ་","དལ","ལ་བ","མ་","་ལ་","ལ་མ","ཀ་ལ","བལ","ཨ་","ྭ་","དཔལ","ས་","ཀ་","རྦ་"],
"am":["མ","མ་","་མོ","རྒྱ་","མས༔","མས་","ཨ་","མས","་མེ","་མ","ཀྲམ","་མི","བས","གམ","བམ","་མ་","འ་","ད་","ྭ་མ","ཨ་མ","ྭ་ད","ཨམ","ལ་","བས་"],
"an":["ང","ང་","ངས","ངས་","་ད","དང","རང","དངས","་ག","ད་","གའ","གང","འབ","་དང","མད","བང","དང་","གྲང","སྐྱང","ཨ་","ན་","བངས","ནག","ནང","ང་བ","་ན","སྣང","ག་","ྭང","་བ་","་དང་","དྲང","པའ","་ཉི","ྭངས","་པ་","ང་ག","དན་","པ་","་འ","གད","སྐང་","བ་","རྒྱས་","ང་ན","ཀ་","་གངས","ས་","རྒྱ་","ལང","རྟན་","འང","སྣ","སྐབ"],
"ang":["ང","ང་","རང","རང་","་","ངས་","བ","ངས","ང་བ","དྲང་","ང་ས","་དང","ད","བྱ","ང་ག","ས་དང","ང་གནས","ྭངས་","་དང་","་དབང","ཡང་","དྲངས","ནང་","་དང༌","འང","བང","གྲངས","ན་དང","བྱངས","ང་གས","ཨ་","ང་ད","བང་","་ཡང","པ་དང"],
"angy":["ང་ཡ"],
"ar":["ར","ར་","དར","རྡར་","ར༔","་ལྟར","འ་","ཀར་","ག་","ར་ས","ར་བ","་ར","གའ","་ད","་རི","འ་ར","ཨ་","ད་"],
"b":["བ","་","བུ","ས","འ","བས","ས་","་བ","བོ","་འ","་འབ"],
"bab":["བབ་","བས་","་བབ","འབབ","བབས་","་འབབ་","་འབ","་བ","བབས"],
"bar":["བར་","་བར","བར","འབར་","འབར","་བར་","་འབར་","བར་ས","་བར་ས","་འབར","བ་ར","བར་བ","ས་བར","བད་","་བར༔"],
"bpé":["པའི"],
"bul":["འབུལ","བུལ་","བུ་ལོ","་བུ་","་འབུལ","བུ་སློ","་འབུལ༔"],
"c":["ཅ","ད","ས","བ","མ","་","ཅི","འ","སྤྱ","ག","་མ","བྱ","ས་","ཕྱ"],
"ch":["་","ས་","་ཆེ","ཆེན","་ཅ","་ཆུ","ཆེ","་ཆ","་བ","ཆད","ཅན","ཆུ","བཅ","་སྤྱོ","་ཕྱུ","བ","ད་","བཅུ","་ཕྱ","འཆ","ཕྱེ","མཆོ","མཆི","མཆེ","ཅས","་ས","ཆ","་བྱ","མ་","ཅད","་ལྕ","་ག","་སྤྱ","་ཆོ","ཆ་","ཆོད","ག་","བཅོ","་ཅུ","འཆི","་བཅུ","་ཅན","ཆས","འ་","་ཕྱོ","གཅོ","སྤྱད","སྤྱན","་བཅ","ཆོས","ཕྱི","ཆུ་","གཅ","ཆེ་","བྱ་","ཅི་","ཆོ","་མཆི","ཆེར","་ཅོ","་འཆ","་ཆི","ཆེའི","ཅིག","ཆེས","་ད","འཕྱ","་འཆོ","་མཆེ","་འཆི","ཕྱག","འཆོ","མཆ","ཆུང","ཆེད","བ་","གཅུ","་མཆོ","འཆུ","ཕྱ་","་མ","ཆག","ཅི་བ","ཆུར","ཆུའི","ཆུད","འཆེ","ཅིང་","འ་བ","ད་ག","ས་སྤྱོ","བྱས","བྱད","གཅིག","ག་བ","དང","བྱར","ཕྱང","ཅིར","ཅིང","འ་ཆེ","ཅའི","ཆའི","་མ་","མཆུ","ས་ཆོ","ད་བ","་ཅད","བྱང","ཆུས","ཅིས","ས་སྤྱ","ད་ཆེ","ཆོག","མའི","ས་བ","བྱའི","་འཕྱ","ཕྱར"],
"cha":["ཆགས","་ཆག","་ཆ","་ཕྱག","ཕྱག","ཕྱག་","་ལྕག","ད་ཆ","་ཆར","ཆ་","ས་ཆ","་ཆ་","་བྱ་","་ཅ","་བྱ","་ཕྱམ","་ཅག","ག་ཅ","་ཆབ","ག་ཆ","ཅ","ཆག་","་ལྕམ","ཆབ","ཕྱག་ན","བཅའ","ཆག","ས་ཕྱག","ས་བྱ","བཅག","བྱ་བ","དག་","མ་ཆ","ཆར","འཆང","་ཅག་","གཅལ","་བཅ","་དང","བྱ་བས","འཆར","ཆར་","ཆ་བྱ","ཕྱགས","་ཅར","གཅམ","་ཕྱར","་ཕྱ་","ཆ་ཤ","ད་བྱ","་འཆང","་འཆལ","འཆའ"],
"chang":["འཆང་","བྱང་","་བྱང","ས་བྱང་","ས་བྱང","་བྱང་","་ཅང་","་འཆང་","་ལྕང","འཆང","་ད","འཆང་བ","ད་བྱང","་ལྕང་","་འཆང","་ཕྱང","ཅང་","་སྤྱང","ས་ཅང་"],
"changc":["་བྱང་","་བྱང་ཆུ","མ་བྱང་","ས་བྱང་","ད་བྱང་","བྱང་ཆུབ","འ་བྱང་","ག་བྱང་","བྱང་ཆུ"],
"char":["་ཆར་","འཆར་","་ཆར","ཆར","ཆར་","་འཆར་","འཆར","ད་ཆར","་བྱ་","་འཆར","ས་ཆར","ཆར་བ","འཆར་བ"],
"chen":["ཅན","་ཆེན་","་སྤྱན་","་ཆེན","ཆེན་","ས་ཆེན","་ཅན་","ཆེན","ད་ཆེན","ད་ཆེན་","ས་སྤྱན","་སྤྱན","ཅན་ག","ག་ཆེན","འ་སྤྱན","མཆན","་ཅན","གཅན་ག","མ་ཆེན","འཆད་","འ་ཆེན","ས་ཆེན་","་འཆད་","་ཆན","ས་སྤྱན་","ད་སྤྱན་","་ཅན༔","སྤྱན་འ","་ཆད་","འཕྱན","ས་ཅན","མ་སྤྱན","སྤྱན་ག","ས་ན"],
"chi":["འཆི་","་སྤྱི","་ཕྱི","་ཅི","ཅིག་","གཅིག་","མཆིས་","་གཅི","ཕྱིན","ཕྱི་","ཕྱི","ས་ཅི","་འཆི་","མཆི་","ད་ཅི","་བཅི","ཕྱི་མ","ས་ཕྱི","་བྱི","མཆིས","ག་ཕྱི","་འཆི","་མཆི་","ད་ཕྱི","ཅིས་","་མཆིས་","བ་ཕྱི","་ཆིས་","གཅིག་ཡི","འཕྱི","གཅིག་གི","ས་བྱི","བ་ཅི","ཅིང་","ག་ཅི","མ་བྱི","ཅིག་གི","ཅི་མཆི","་ཆིག","མ་ཕྱི","གཅིག་ནི","ཅིར་","ཆོད་","་ག","་ཆིལ","འ་ཅི"],
"chik":["་གཅིག","་ཅིག","གཅིག་བ","་ཅི","ཅིག་བ","་གཅི","ཅིག་པ","ད་གཅིག","གཅིག་ཆོ","མ་ཅིག","གཅིག་པ","་ཅིག༔","ད་ཅིག","ས་ཅི"],
"chin":["ཕྱིན་","་ཅི་","་ཅིང་","ད་ཅིང་","ཕྱི་ན","་ཕྱིན","ཕྱི་","ཕྱིན","་ཕྱི་","ས་ཕྱི་","་བྱིན་","་བཅིང","་ཅིང","ད་ཕྱི་","ས་ཕྱིན","ད་ཅིང","་བྱིངས","ས་ཕྱི་ན","བ་ཅིང","་བྱིན","ས་བྱིན་","ག་ཅིང་","ཅིང་ཁ","མ་ཕྱི་ན","ག་ཅིང","་བཅིངས"],
"ching":["་བཅིང","འཆིང་","་བཅིངས་","་བཅིངས","་ཅིང་","་ཅིང","་བྱིན་","་འཆིང","བཅིངས་","་ཅིང༌","འཆིང"],
"chir":["་ཕྱིར","་ཅིར","ས་ཅིར","ས་ཅིར་","ཕྱིར","ཕྱི་རོ","ད་ཅི་རི","ཕྱི་","ཕྱིར་","ཕྱི་ར","་ཕྱི་","་ཕྱིར་","ག་ཅིར","ས་ཕྱིར"],
"cho":["མཆོག","བཅོམ","ཕྱོགས","ཆོག་","་ཕྱོག","་ཆོ་","་བཅོ","་མཆོག","་བཅོམ","་ཆོ","བཅོལ","ས་མ","་མ","བཅོ","ས་མཆོ","་བཅོལ","འཆོལ","་ཅོ","ས་ཆོ","་ཆོག","ཅོ","ཆོ་","ད་བཅོ","ཆོག","་ཆོམ","་ཅོག","་གཅོ","ཆོག་འ","་འཆོལ","ད་མཆོ","དག་","་འོ","གཅོང","ག་མཆོ","གཅོག","བཅོ་","གནས","་མཆོ","་ཅོར","བསོ","ཆོ་ག","་བཅོ་"],
"chok":["ཕྱོགས་","མཆོག","མཆོག་","་ཕྱོགས","་མཆོ","ཕྱོག","ཕྱོགས","་མཆོག","་མཆོག་","ས་མཆོག","་ཕྱོགས་","ད་མཆོ","་ཕྱོག","ས་མཆོ","་ཆོག་"],
"ché":["་བྱེ","ཅས་པ","བཅས","་ཆེ་","་ཆེ༔","་ཆེ","ཅས་","ཆད་པ","བྱས་པ","་བཅ","་བཅས་","བཅད","་ཆད","འཆད","སྤྱད་","་བྱས","ཕྱེ་","བྱས་","ཆད་","་ཆེའི","ས་པ","འ་བྱེ","ཅད་"],
"chö":["མཆོད","ཆོས་","་ཆོས","་སྤྱོད","ཆོད་","ཆོས","་ཆོས་","་ཆོ","ཆོ","་མཆོད","བཅོས་","་སྤྱོ","གཅོད","ས་ཆོ","མ་ཆོ","་ཆོད","་གཅོ","་ཅོད","ག་ཆོ","ས་ཆོས་","ས་ཆོས","བཅོས","ད་ཆོ","་བཅོ","མའི་","་ད","འ་ཆོ","་བཅོས་","འཆོས","ས་སྤྱོད","བཅོ","་ཅོན"],
"chü":["་ཆུད","བཅུད","བཅུའི","ཆུན་","ཆུད་","ཆུད","མ་བཅུ","་ཆུའི"],
"d":["་","འ","ད","བ","ས","དོ","ག","དུ","མ","་འ","ཟླ","ས་","འི","་ད","་བ","གྲུ","དེ","སྡུ","་དོ","སྒྲུ","དི","་མ","འི་","ལྡ","སྒྲི","་འདི","་ག","རྡོ","བདེ","་དུ","་སྒྲུ","་དེ","ཌ","་བདེ","་གད","་དག","་དམ","འགྲུ","དྡྷི","གི","ངོ","རྫོ"],
"dak":["བདག","དག་","་དག","དག","ག་པ","་དག་","བ","་ཌཱ་","་བདག","དྭགས","བདག་","་བད","འི་བ","་དག་པ","དད་","་དྭགས","འདའ","་པ་","ག་ས","བད","ས་བད","འ་བད"],
"dam":["དམ་","་དམ","དམ","གདམས","་དམ་","མས་","འདམ","དམས་","གནས","་གདམས་","དམས","ས་ད","་དམ་བ","་གདམས","་ཟླ་","མ་བ","ཟླ་མེད","མ་ད","དང་མི","གདམ","ད་ད","འི་ག","ཟླ་མེ","ས་བ","འ་གདམ","ས་དམ","འི་ད","འགྲམ"],
"dang":["་དང་","་དང","དྭངས་","ས་དང","དང་","་དྭངས་","དྭང","དང","ལྡང་","་མདང","འི་","མདངས་","མདངས","གདངས","དང་བ","་དྭང་","དངས་","ལྡང","་དང་༔","དྭངས","དྭང་","ག་དང","་དང༔","ད་དང་","ས་དང་","དེ་དང"],
"de":["་ལྡ","ལྡན","དེ་","ལྡན་","དེ","་ལྡན","བདེ","བདེ་","་དེ","འདེ","་བདེ","་འདེ","ས་","་བདེ་","དད","གད","འི་","དན","འད","བདེན་","་གདེ","ས་བདེ","དན་","དང","དགེ","དུན","བདེན","་མེ","དས","་གདན","དོ་","དེང","དེན་","་ད","གདེ","ད་","དས་","ཟླས","ག་","ས་དེ","་བདེན"],
"deb":["འདེབས","འདེབས༔","་འདེབས༔","་འདེབས","འདེབ","དེ་"],
"den":["ལྡན","ལྡན་","བདེན","བདེན་","དེན་","དེ་","དེང","ལྡན་འ","་དེ་","་ལྡན་","་དེང","་ལྡན","གདེང","་བདེན་","དེངས","དན་","དེ་ན","གདན","དེ་ཉི","དེ་རྣ","་བདེན","བདེ་","དཔའི","དེས་ན","དེངས་","གདེངས","གདན་","དེས་","འི་ག","དེན"],
"denpa":["་ལྡན་པ","བདེན་པ","ལྡན་པར","དེན་པ་","་ལྡན་པར","་ལྡན་པར་","བདེན་པར"],
"dep":["ད་པ","དད་པ","འདས་པ","འདེབས","་དད","འདས་","་དད་པ","བདས་པ","དེད་ད","དད་","་ལ་ད","ཟླས་པ","དས་པ","དེབ","་དེད","་པས་","ས་འ","མ་འ","ཟླས་","དེས་པ","་འདས་པ","འི་ད","་དད་","དས་"],
"des":["བདེ་གཤེག","དེ་","དེ་གཤེག","བདེ་","དེ་སྲི","་དེ་","་བདེ་","་གཤེག","དེ་གཤེགས","་དེ་སྲི"],
"di":["འདི","དི་","ས་","་འདི","གདི","དི","་འདི་","དོན","ད་","་གི","འི་","བ་","་དི","མ་","འ་"],
"dir":["འདི་རུ","འདི་","དི་","་འདི་རུ"],
"do":["་སྡོ","་དོ","མདོ","གདོ","དོག","དོར","འདོ","་རྡོ","དོ་","་དོག","་གདོ","བསྡོ","རྡོལ","་མདོ","རྡོར","་འདོ","ད་","དོམ","བརྡོ","མས","དོལ","རྡོ་","ག་","ས་སྡོ","དོང","འི་","དུ་"],
"dok":["་ཟློག","མདོ་","མདོག","བདོག","དོག་","འདོག","ས་ཟློག","དོགས་","དོག་ད"],
"dor":["་རྡོ་","རྡོ","མདོར་","་རྡོ","ད་རྡོ","འདོར་","་རྡོར","ས་རྡོ","འི་རྡོ","དོར་","་དོར་","འདོར","ས་རྡོ་","རྡོར་","མ་རྡོ","རྡོར","འ་རྡོ","བ་རྡོ","མདོར","་འདོར་","དུལ་","་རྡོར་","ག་རྡོ"],
"dro":["་གྲོལ","་གྲོ","་སྒྲོལ","འགྲོ་","་གྲོག","་འགྲོ","འི་གྲོ","ས་གྲོ","་སྒྲོག","འགྲོག","ས་འགྲོ","་འགྲོ་","ད་གྲོ","འགྲོ","འགྲོར","་དྲོང","འགྲོ་བ","་གྲོ་","་གྲོང","་སྒྲོ་","འ་འགྲོ","འ་གྲོ","ད་འགྲོ","མ་གྲོ","་སྒྲོམ","བསྒྲོལ","ས་གྲོག","་འགྲོ་བ","འགྲོ་འ","འི་གྲོལ","ས་སྒྲོལ","བགྲོ་"],
"drub":["་སྒྲུབ","་གྲུབ་","གྲུབ","སྒྲུབ","ས་སྒྲུབ","་བསྒྲུབ","་གྲུབ","་བསྒྲུབས","འགྲུབ་","ས་གྲུབ","ག་སྒྲུབ","བསྒྲུབ","་","ད་གྲུབ","་འགྲུབ","་འགྲུབ་","སྒྲུ","ད་སྒྲུབ","བསྒྲུབས","འགྲུབ","མ་སྒྲུབ","གྲུབ་བ","འི་གྲུབ","ད་འགྲུབ","ག་གྲུབ","སྒྲུབ་བ","འི་གྲུབ་","འི་སྒྲུབ"],
"du":["གདུ","དུ","འདུ","་དུ","དུལ","དུ་","དུག","སྡུག","་འདུ","་གདུ","་སྡུ","་རྡུ","བདུ","དུང","འ་","མདུ","བསྡུ","་དུ་","སྡུ་","དུབ","ད་","་གདུག","སྡུ","ས་ག","ས་","བརྡུ","་གདུལ","་དུག","འི་","ད་དུ","འི་སྡུ","འི་རྡུ","་དུ༔","་མ","དུ་དུ","དུམ","་ཨུ","ག་"],
"dz":["འཛི","མཛ","་འ","རྫོག","་རྫོ","་རྫ","་མཛ","འཛ","་མཛེ","་འཛི","ས་","་ཛ","འི་","་འཛ","ད་","གའ","བ་","ས་འ","འ་","་བ","བས"],
"dza":["འཛམ","མཛའ","་ཛྭ","་ཛ་","་རྫ་","་འཛམ","་ཛབ","་ཛ་ག","འཛབ","་རྫབ","་ཛམ"],
"dzin":["འཛིན་","་འཛིན","་འཛིན་","འཛིན","་འཛིངས","་འཛིན༔"],
"dzok":["རྫོགས་","་རྫོགས","་རྫོགས་","་རྫོག","ས་རྫོག","ད་རྫོག","་རྫོགས༔","ས་རྫོགས"],
"dzé":["མཛད","་མཛད","་རྫས་","་མཛེས་","་མཛད༔"],
"dzö":["་མཛོད"],
"dé":["དེ་","བདེ","དད","ད་","་དེ","་སྡེ","བདེ་","་ལ","དེའི་","དས་","འད","ད་དེ","དོན","ད་པ"],
"dön":["དོན་","་དོན","དོན","་དོན་","གདོད","དོད་ན","འདོད","དོད་","འདོན་","་གདོད"],
"dü":["བདུ","དུད","འདུ","དུས་","བདུད","འདུས","དུས","མདུ","སྡུད","་བདུད","ས་","་བདུ","་འདུ","སྡུས","་དུ","མདུད","་འདུས","་མདུ","སྡུས་","འ་","གདུ","འི་","་དུས་"],
"e":["་","ན","ཆེ","ད","ཅ","ས","གེ","ན་","ས་","ལ","ཕེ","ལེ","པ","ཡེ","ཉེ","ཟེ","བེ","རྒྱ","བྱེ","སྤེ","ཕ","ཡ","རྗེ","ང","ཕྲེ","ངེ","ཛྲ","སྐྱེ","ཨེ","ཞ","སེ","དེ","མེ","ཞེ","སྤྱ","ལྡ","ྨ","སྟ","ཏེ","ཤེ","ཧེ","ཏ"],
"eb":["བེབས","ས་","ཕེབས","་བུ","བེབ","ལ་"],
"ek":["གས","ལེགས","ས་","ག","གེགས","ས་སྐ","ཨེ་","ལེག","ད་ད","་སྐ","་འ","་བ","་པ","་ག","ད་","་ད"],
"em":["དྨ་","པདྨ","་མ","དྨ","ད་","ད་མ","ྨ་","ད་མེད","ད་མེ","ས་མེད","མེད","དྨས་","ཆེ་","་མེ","་མོ","ཨེ་མ","སྐྱེ་","་མེད","དམི","པད","ཨེ་","ས་","་ད","ལས་","དྨས","གེ་","ས་མེ","སྐྱེད"],
"en":["ན","ན་","ཛྲ་","ངན","ཕྲེང","བེན་","ཞན","ངས","ཡེང","ཞེང","ཕྲེང་","ལྡན","ས་","ན་བ","ཕེན་","་གན","་འ","ཡེངས","ཕན","ཛྲ་མ","སྐྱེ་","ཟེངས","གེ་","བེན","་བ","ཕེན","ཞེན","ཞན་","ལྡན་","གེ་བ","ན་ས","་ག","ཡེ་ན","ནས","ལེན","ཉེན","རྒྱན","ཧེ་","ལག","གེང","ས་ག","ཡན་","ངས་","གེངས","ལན","ཡེང་","མེད་","ཡན","་ད","ན་འ","ན་ག"],
"ep":["་པ","ས་པ","ད་པ","ད་","ས་","ཡས་པ","པ་","ཅས་པ","ཡས་","སྐྱེད","་བ","་མེད་པ","ཅད","་པོ","ངེས་པ","ནས","ཞད","ད་པོ","སྐྱེས་","ལས་པ","ཞེད","ཉེས","ནས་པ","བྱེད","པས","ངེས་","སྐྱེས་པ","ཞེས་པ","བེབས"],
"epa":["ས་པ","ད་པ","་པར","ས་པར","ད་པར","་པར་","ས་པར་","ད་པ་","ངེས་པར","ད་པར་","ངེས་པར་","ངེས་པ","ས་པ་"],
"er":["ཉེར","ར","ར་","ཉེར་","བྱེར་","ཝེར་","བྱེར","་ར","ད་","ས་","ཉེ་","་རི","ས་ར","ཡེར","ཆེར་","ཝེར","གཏེར","ས་རོ","ས་རི","གེར་","བེར"],
"es":["་ཤི","་ས","གེ་","་སྲ","་བ","ལེ་","ཝེ་","སྐྱེ་","གེ་བ","ད་","གེ་ས","ངེས་","ས་ཤེ"],
"eta":["་བཏ","ས་བཏབ"],
"ewa":["་བ","་བར","ཉེ་བ","ཆེ་བ","སྐྱེ་བ","་བར་","གེ་བ","ས་དབ","བྱེ་བར","་བ་ལྔ"],
"g":["་","ག","ད","ས","འ","བ","ང","མ","གུ","གེ","གོ","གི","་དག","ས་","རྒྱ","རྒུ","་ད","༌༔","་འ","་ག","་བ","འི་","ང་","་གི","དགོ","རྒྱུ","སྔ","གྱི","ངོ","ལྔ","ཨོ","རྒྱུད","་དགོ"],
"gang":["་གང་","གང་","་གང","གང","གངས་","་གངས","གངས","ས་གང","ད་གང","གང་ད","ང་གང","་གངས་","ས་གང་","གངས་ད","གང་གི","གང་བ","གང་ནས"],
"gi":["་གི","་གིས","གི་"],
"go":["་སྒོ","གོ་","བསྒོ","་གོ","གོམ","འགོ","་བསྒོ","གོལ","མགོ","གོ་འ","་འགོ","དགོ","གོར","མས","གོང","འི་སྒོ","་བསྔོ","དག","་དགོ","གུ་","ས་བ"],
"gon":["དགོང","དགོངས","ས་ད","གོང་","་དགོང","འགོང","་སྒོ་","་སྒོ་ན","གོངས་","མགོན་","་གོང","གོངས","ས་གོ","་དགོངས","དགོངས་","ད་གོ"],
"gong":["དགོངས་","གོངས་","་གོང་","་གོང","གོང་","འགོང་","དགོངས","་དགོངས་","གོང་མ","གོང","དགོངས་བ","འགོང","ས་དགོ","་འགོང་","གོངས་འ","་དགོངས","གོངས་བ","་སྒོ་ང","དགོངས་ག","ངས་བ","ས་འགོང","དགོང"],
"gpa":["་པར","ས་པ","་པ་","་པ","ག་པ"],
"gy":["་རྒྱ","བརྒྱ","ས་","་བ","་རྒྱུ","རྒྱ་","རྒྱུད","ད་","རྒྱས","་འ","་བརྒྱ","བརྒྱུ","དགྱེ","་གྱི","རྒྱན","མ་","ག་","ང་","རྒྱལ","་བརྒྱུ","རྒྱད","གྱི་","རྒྱ་ག","ངོན་","རྒྱུན","་རྒྱས","རྒྱུ་","རྒྱན་","རྒྱས་","་གྱེ","བགྱི","གྱིས","འ་","རྒྱུར་","འགྱེ","རྒྱུན་","་དགྱེ","རྒྱབ","་རྒྱ་","་བགྱི","གྱི་ག","རྒྱུད་","ཨོ་","གྱིས་","ས་རྒྱ","་རྒྱས་","ས་བ","མར་","བ་","་ད","གོན་","་རྒྱན","་ན་","་ག","་ས","འི་རྒྱ","རྒྱུ་ད","ད་རྒྱ","ལྔ་","རྒྱུ་ཡི","རྒྱུས","ངོས","འག","གི་","དབ","་བར་","དན་","ས་འ","རྒྱག","རྒྱུག","གས","ས་རྒྱུ","གཡོ","་ཡ","བས","གྱིད","གེ་","འ་རྒྱ"],
"gyal":["་རྒྱལ་","རྒྱལ་","་རྒྱལ","རྒྱལ་བ","ས་རྒྱལ","ག་རྒྱལ","རྒྱལ་སྲ","མ་རྒྱལ","ས་རྒྱལ་","་རྒྱལ་བ","ད་རྒྱལ","བརྒྱལ་","འི་རྒྱལ་བ","ད་རྒྱལ་","ང་རྒྱལ","་རྒྱས་","ལྔ་རྒྱལ","ང་རྒྱལ་","་རྒྱལ་མ","གི་རྒྱལ","རྒྱལ་བ་","རྒྱལ་འ","་རྒྱལ་སྲ"],
"gyi":["་བགྱི","་འགྱི","གྱིད་","འགྱི","བགྱི་","གྱིས་","་གྱི","བགྱིས","བགྱིད","བགྱིས་","ས་","་བགྱིས་","་གྱིས","་གྱིས༔"],
"gyur":["་གྱུར","་འགྱུར་","་བསྒྱུར་","འགྱུར","ས་གྱུར་","་འགྱུར","ད་གྱུར་","ང་གྱུར་","ག་གྱུར་","་བསྒྱུར","གུར་སྒྱུར་","གོན་གྱུར་","ས་སྒྱུར་","རྒུ་སྒྱུར་","ས་བསྒྱུར","ང་སྒྱུར་"],
"gyurpa":["་གྱུར་པ","་གྱུར་པར"],
"gyé":["རྒྱས་","་རྒྱས","་རྒྱས་","དགྱེས་","དགྱེས","བརྒྱད","རྒྱན་","་བརྒྱ"],
"gö":["་མ","གོད","གོན","གོས་","ས་","གོས","དགོས་","མགོ","ད་","འི་མ","ག་","འི་","ས་མ","དགོས","མ་","དས","མའི་"],
"gön":["་མགོན","གོན་","མགོན་","གོན","འི་མགོན","མགོན","་དགོན་","ས་མགོན","དགོན་གན","གོན་གན","གོན་མ"],
"h":["་","ཤ","ས","ཤེ","ཤུ","ཤི","ག","ཧྲཱིཿ","ད","ཧཱུྃ","ཧཱུྃ","བ","ར","ན","ང","ཁོ","ཆུ","་བ","ལྷ","ཁ","ཞི","ཆི","ང་","ཕྱོ","འི","ཞུ","ཨཱཿ","ཞོ","ཕྱ","སྤྱོ","ཞེ","ཆ","ཁུ","་ག","ཕྱུ","འཁོ","་ཆེ","ཅུ","ཅ","ཞ","ཆོ","ལྕ"],
"ha":["ཤར","ལྷ","ར་","ཤམ","ཤ་","བཤ","་ཤ","་ཧ","ཁམ","ག་","ཞལ","ཤྭ","་བ","ཤག","་ཧཱ","ངས","་ཁ","བ་","ཁར","་ཨ","ར་ན","་འ","་བཤ","གས","་ཟ","ཤའ","ཤང","ཁ་","ཤལ","་པ"],
"hab":["་ཞབས"],
"hak":["་ཧཱ་","གས་"],
"he":["ས་","གཤེ","ཤེ","་ཧེ","ཤད","ཤེས","ཤེས་","གས","ད་","གས་","ན་","ཤེལ","ཤེད","ཆེན","ཅན","་ཤེ","ར་","བཤེ","ཞད","་ད","ཤེ་","ཤེན","་པ","ཞན"],
"hen":["ཤེས་ག","ས་ག","ཤན་","ཤེས་","ཞེ་འ","་ཅན༔","ན་འ","ཤན"],
"hi":["ཞི","ས་","་ཤི","ཤིས","ང་","ཤིན","ག་","ཤིག","གས","་བའི","བཞི","ན་","་མཆི","་ཞི","གཤི","ང་ཡི","ཕྱི","ང་ལ","བཤི","ཤི་","ག༔","་བི"],
"hik":["་ཅིག༔"],
"hin":["ཤིན་","་ཤིང","ཤིན","ང་གི","ང་བ","ང་མཉེ","་ཤིན","ང་གི་","གཤིན","་བཞིན","ང་ད","་ཤིང་","ཞིན་"],
"hing":["ཤིང་","ཤིང","་ཤིང་","་ཤིང","ང་ད"],
"hingk":["ཤིང་"],
"hir":["འི་ཕྱིར"],
"ho":["་ཧོ","གས","ཕྱོག","ཧོ༔","ཁོར"],
"hok":["་ཤོག"],
"hor":["ཁོར"],
"huk":["ཤུགས","ཤུལ་","ཤུགས་","གས་","ཤུག"],
"hung":["ཧཱུྃ","་ཧཱུྃ","ཧཱུྃ་ད","ཧཱུྂ༔"],
"hy":["ཁྱ","ཞིན","ཞིན་"],
"hé":["ད་","ཤེས","ས་པ","ཤད","བཅས","ས་"],
"hü":["ལྷུ","ད་"],
"i":["་","ག","ད","ན","ས","རི","འི","ས་","ལ","༔","ཛི","ཉི","སྲི","འི་","སྒྲི","ཐི","་མ","ཇི","སི","ཏི","བྱི","ཀྱི","ཞི","ལི","གྱི","མི","ནི","རྩི","་ཡི","ཡི","ཉིས","དྲི","གླི","ས༔","བི","དི","ཀི","ཀྱི་","་མི","ཕྱི","ཟི","་ནི","ཤི","ཅི","གི","ཁྲི","་རི","ཉི་","་གི","་འདི","ྤྱི","གཉི","ནི༔","སྤྲི","སྙི"],
"ik":["ག","ཇིགས","ཇིག","ག་","གས་","ཅི","ཐིག","ཟིགས","གས","་འ","ཏི་","ས་","་བ","ལི་"],
"im":["མ","མས","རིམ","ཐིམ","བི་","་མ","བི་མ","་མེད","དྲི་","་མ་","ཏི་","་མོ","ས་","ས་མེ","་མ་མེ","ས་མེད","སིམ","་མུ","་མེ","་ས","རིམས","རི་","་མས"],
"imé":["་མེད"],
"in":["ན","ན་","དྲིན","རིང","གླིང","རིང་","རིན","གླིང་","ཐིང","ཐིང་","སྲིང","ཏིང","སྲིང་","ཀི་","ཏིང་","སྲིན","ལིང","བྱིན","ཟིན"],
"ing":["ང་","ང","ཏིང་","རིང་","ཏིང","ཐིང","་བྱིན","ཐིང་","རིང","སྲིང་","ལིང་","་ངད","ཅིངས་","རྩིངས་","སིང","སྲིངས་","ཏིང་ག","སྲིང"],
"inpoche":["རིན་པོ་ཆེ"],
"j":["་","འ","རྗེ","བྱ","ད","བྱེ","སྦྱོ","་འ","་བྱ","བྱེད","ས","བྱི","་རྗེ","་འཇི","་བརྗི","ཇ","བྱུ","ཇུ","་སྦྱོ"],
"ja":["་བྱ","བྱ","འཇ","བྱ་","བྱམ","ཇམ","་འཇ","ཇལ","ཇའ","བྱར","འབྱ","བྱ་བ","ས་","་བྱ་","་ཇ","་བྱམ","་ཡ","་བྱར","བྱང","དབྱ","བྱེད","ཇག","་འབྱ"],
"je":["་རྗེ","་བྱེ","རྗེ་","རྗེས","རྗེས་","བྱད","བྱེད་","བྱེ་","བྱས་","ས་","བྱེད","་རྗེ་","བྱས","རྗེན","་བྱད","་རྗེས","རྗེ","་འབྱེ","འབྱེ","རྗེད","་རྗེས་","ད་","་རྗེན"],
"jepa":["་བྱེད་པ","བྱེད་པ་","་འབྱེད་པ","བྱས་པ","བྱེད་པར","བྱེད་པ"],
"jin":["བྱིན་","་བྱིན","་བྱིང","་བྱིན་","བྱིན་བ","་ཇི་","བྱིན","་བྱིངས","འབྱིན་","་བྱིང་","་གི་","འབྱིན","་ནི་","་འབྱིན་","་གིས"],
"ju":["འབྱུ","་བྱུ","འཇུ","བྱུང","་འབྱུ","ཇུག","་བྱུང","་འཇུག","ས་","བྱུག","་འཇུ"],
"jung":["འབྱུང་","་བྱུང་","་འབྱུང་","འབྱུང","བྱུང་གནས","བྱུང་ག","བྱུང་","བྱུང་བ","འབྱུང་ག","་བྱུང","བྱུང་གནས་","འབྱུང་བ","་འབྱུང","ས་ད","བྱུང","ས་འབྱུང","ཇུངས་","འ་འབྱུང","དགུ་འ"],
"jé":["་རྗེ","རྗེས","རྗེའི","བྱས་","་འབྱེ","རྡོ་རྗེ","རྗེས་","་བྱེ","་རྗེའི","རྗེ་","་བྱའི","་རྗེ་"],
"jön":["་བྱོན","འབྱོན","་འབྱོན","་བྱོན༔"],
"k":["ག","་","ས","ས་","གས","ད","ཀ","བ","་བ","འ","་ག","གས༔","་འ","མ","་ད","པ","སྐུ","་མ","སྐ","ཆོ","ཀྱི","བཀ","ཀུན","སྐྱེ","ཕྱ","ས་ཀྱི","ཁྱེ","ཁྱ","འཁོ"],
"ka":["བཀའ","ཀའ","བསྐ","སྐལ","་ཀ","་སྐ","ཀ་","དཀ","བཀ","་བཀ","ཀར","་དཀ","སྐ","སྐབ","་བསྐལ","ཀར་","་བསྐ","ཀ་ད","སྐང","ཀ་ན","འ་","བཀག","སྐ་","སྐམ","སྐར","ས་","ཀྱིས","ཀན","་བསྐམ","མ་","ཀང","སྐྱེད","པས","་བ","པད","སྐག","ས་ད","ཀབ","ག་"],
"kang":["བསྐང་","བསྐང","བཀའ་","བཀང་","བསད"],
"kar":["དཀར་","དཀར","ཀར་","་དཀར","་དཀར་","སྐར་","སྐར","ཀ་ར","་ཀ་","་ཀ་ར","ཀར","་སྐར","ཀ་རི","་སྐར་","སྐ་ར"],
"kh":["་ཁ","མཁ","་ཁོ","འཁོ","་ཁུ","་འཁོ","་མཁ","འཁོར","ཁ","ས་","འཁུ","འཁོད","་ཁྱེ","ཀྱིས","ས་ད","མཁོ","་ཁྱོ","པའི","་མཁོ","ས་ག","ས་མཁ","འཁོན","ས་བ","ད་","ཁཱ་","འཁྱོ","མཁྱེ","མའི"],
"kha":["ཁ","མཁའ","་ཁ་","་ཁམ","་མཁའ","ཁ་","ཁའ","ཁམ","་ཁ","ད་ཁ","་ཁང","མཁར་","མ་མ","ས་མ","ས་ད","་ཁབ","མཁར","ཁབ","་མཁར","ས་ཐ","གངས","ས་བ","་ཁ་པ","ཁར","ས་ག","ས་ཁྱ","་ཁརྟ","ས་འ","ཀྱི་མ","་ཁར་","་ཁྭ","ད་མ","པའི་མ","ཀྱི་ཁ","ས་ཁམ","ས་གན","ས་ན","་ཁར","པའི་","ག་མ","འཁར་","ས་སྣ","ས་རྒྱ","འཁར","ས་ར","་ཁ་ག"],
"khor":["འཁོར་","འཁོར","འཁོར་བ","་འཁོར་","འཁོར་འད","་འཁོར","་འཁོར་འ","འཁོར་ལོས","ས་འཁོར་འ","འཁོར་འ","་ཁོར་","འཁོར་ལོ་","འཁོར་བས","ས་འཁོར་","་ཁོར"],
"khy":["་ཁྱ","ཁྱེ","འཁྱ","མཁྱེན","ཁྱོ","ཁྱ","་མཁྱེ","ཁྱད","ཁྱབ","་མཁྱེན","་ཁྱེད","ཁྱེར་","ཁྱབ་","་འཁྱ","ཁྱེད་","འཁྱོལ","མཁྱེ","ཁྱད་","་ཁྱོན","་ཁྱོད","བདག","པས་","ས་མཁྱེ","ད་འ","ཁྱེན་","མཁྱེན་"],
"khyab":["་ཁྱབ་","ཁྱབ་བ","་ཁྱབ","ཁྱབ་","ཁྱབ་པ་","ཁྱབ","གས་ཁྱབ"],
"khyen":["་མཁྱེན་","མཁྱེན་","་མཁྱེན","མཁྱེན","ཁྱེན་","ཁྱེན","ཁྱེན་པས","ཁྱེན་པའི","མཁྱེན་པའི","ས་མཁྱེན་"],
"khyé":["ཁྱད་","་ཁྱད"],
"kor":["་བསྐོར","ས་བསྐོར","འཁོར་","པས་"],
"ku":["་སྐུ","སྐུ་","སྐུ","བསྐུ","ཀུ","་ཀུ","བཀུ","ཀུན་","སྐུལ","ས་","འ་སྐུ","དགུ","ས་ཀུ","ཀྱི་སྐུ","་བསྐུ","ས་སྐུ","ཀུན","་བཀུ","པ་","ད་"],
"kul":["བསྐུལ","སྐུལ་","སྐུལ་མ","་ཀུ་","ཀུ་"],
"kun":["་ཀུན་","ཀུན་","་ཀུན","ཀུན་བ","ཀུན","ཀུན་འ","ཀུན་ད"],
"kur":["བསྐུར་","་ཀུ་","ཀུ་","་སྐུར","བཀུར","་སྐུར་","བཀུར་","སྐུར་","་བཀུར"],
"ky":["་སྐྱེ","ས་","་སྐྱོ","་སྐྱ","སྐྱེ","སྐྱ","སྐྱེས","་བ","ད་","་རྐྱེ","བསྐྱེ","ཀྱ","སྐྱེད","ཀྱི་","བསྐྱོ","སྐྱེས་","བསྐྱ","སྐྱེ་","་སྐྱི","་བསྐྱེ","མ་","ཀྱིས་","པ་","ཀྱིས","འ་","ག་","ས་ཀྱི་","ས་བ","་གྱི","ཆོས","ས་ཡུ","ས་ཀྱིས","གན","ས་ཀྱིས་","བསྐྱི","དས","་ཡུ","མས","ཀྱི་ག","་བསྐྱོ","གས་","ཀྱི་ད","མས་","གས་ཡུ","ས་སྐྱ","སྐྱེ་ག"],
"kyang":["་བསྐྱང་","བསྐྱངས་","་ཀྱང","་བསྐྱངས་","ཀྱང"],
"kyi":["་སྐྱིད","དཀྱི","བསྐྱིལ","་དཀྱི","་སྐྱིལ","་སྐྱིན","་ཀྱིས","ད་དཀྱི","ད་ཀྱི","ས་ཀྱི","་ཀྱི༔","་ཀྱིས༔","ད་ཀྱིས","་ཀྱི","ས་དཀྱི","ཀྱིས་","་བསྐྱིལ"],
"kyong":["ས་སྐྱོང་","་སྐྱོང་","་སྐྱོང་བ","ས་སྐྱོང","ད་སྐྱོང་","་སྐྱོང"],
"kyé":["སྐྱེས","་སྐྱེད","སྐྱེས་","་སྐྱེ་","སྐྱེ་","་སྐྱེས","སྐྱེ་མེ","་བསྐྱེ"],
"kü":["ཀུན་","་ཀུ","་སྐུའི་","ས་","དབུ","སྐུད","པ་","་ད","ད་","ས་ཀུ","མ་","སྐུའི"],
"kün":["་ཀུན་","ཀུན","་ཀུན","ཀུན་འ","ཀུན་ན","ཀུན་ད","ད་ཀུན","ཀུན་མ","ཀུན་བ","ཀུན་ག","དབུས","ས་ཀུན་","གན","་འདུས","་དག"],
"l":["་","ལ","་བ","ལེ","བ","ལོ","༔","འ","་མ","་ལ","ལ༔","ས་","མ","གླ","ལུ","་ལེ","བླ","་ལོ","ཀློ","ཀླུ","བརླ","སྲ","རླ","དུལ","གློ","སློ","གླི","་རླ"],
"la":["་ལ","ལ","ལག","ལ་","ལམ","རླབ","བརླབ","་བླ","བླ་","་རླ","བླ","ལང","་ལ་","བརླ","བླག","་བ","བླང","་ལམ","རླང","མ་","་ལག","ས་བླ","གླང","ལྭ","མ་འ","ལ་ལ","སློབ","བླ་ན","ལར","་བརླ","བླ་མ","་རླང","རླག","ས་ལ","འ་ལ","བཏ","གླག","་ལ༔","བླར","་རླབ"],
"lam":["ལམ་","བླ་མ་","་བླ་མ","བླ་མ","བླ་","༔བླ་མ","་ལམ","་བླ་","བླ་མེད","བླ་མས་","ལམ","་ལམ་","བླ་མེ","འདུས་","་ལ་","༔བླ་","་བླ་མེ","་བླ་མེད","ལ་","བླ་མས"],
"lh":["་ལྷ","ལྷུ","ལྷ","་ལྷུ","འ་","མ་"],
"lha":["་ལྷ","ལྷ་","་ལྷག","་ལྷ་","ལྷག","་ལྷབ","མ་ལྷ","ལྷར་","་ལྷམ","ལྷར","་ལྷང","་ལྷ༔","་ལྷར་","ས་ལྷ","ལྷང","་ལྷར"],
"ling":["་གླིང་","་གླིང","གླིང་"],
"lo":["་ལོ","ལོག","བློ","་བློ","ལོ","་སློ","་རློ","ལོ་","ཀློང","་ཀློ","་ལོ་","་ལོག","གློ་","ཀློག","ལོང","གློག","ས་ལོ","ལོར","བསློ","ས་སློ","སློང","་ལོ༔","ས་བློ","་ལོང","སློག"],
"lob":["་སློབ","སློབ","་བློ་","་རློབ","བློ་"],
"long":["་ལོངས","ལོངས་","་ཀློང་","ཀློང་","ལོངས","་ཀློང","ཀློང","ཀློང་ག","་སློང","ས་ལོངས","ལོང་བ","་ལོང","་ལོངས་","ལོང་","་སློང་","་ལོང་"],
"lop":["་སློབ","ལོ་"],
"lu":["་ལུ","ལུག","་རླུ","ལུ","ལུང","ཀླུ་","་བསླུ","་ཀླུ","ཀླུང","ལུ་","བཀླུ","ས་ལུ","ཀླུབ","སློབ"],
"lé":["་ལེ","་ལ","ལས","ལས་","་ལས","ལེ་","་ལས༔"],
"lü":["ལུས་","ལུས","་ལུ","ཀླུའི","ལུད"],
"m":["་","མ","མོ","ས","ས་","མེ","མེད","མས","་མ","ད","་མེ","ག","་མེད","མུ","བ","མི","་ད","སུ","རྣ","རྨ","དྨ","་མི","དམ","་རྣམས"],
"ma":["་མ","མ","མ་","མར","་མ་","དམ","་དམ","ས་","དམར","རྨ་","དམག","་མར","མར་","མག","མང","་འ","ད་མ","མ་འ","ད་","ས་མ","་མང","མལ","་ཧཱ","མཐའ","དམར་","དམའ","མའ","་ད","བང","དང","མེད","་མར་","་ང","་མ་མ","མ་མ","་མ༔","མ་བ","མན"],
"me":["མེ་","་མེ","སྨ","རྨད","་ད","དམན","་མེ་","མན","ས་","མན་","མེད","དམེ","དམན་","མལ","མེད་","མེལ","ས་མེ","་མན","ད་"],
"mep":["མེད་པ","་མེད་པ","་མེད","ད་པ","མེ་ད","མེད་","་མེད་","མེ་ཕུ","་མེ་","་པ་","རྨད་པོ","དམས་པ","མེས་","སྨད","མེས་པོ","་པས","་མེ་ད","གཏད"],
"mepa":["་མེད་པ","མེད་པར་","མེད་པར","་མེད་པར","ས་མེད་པར","ད་པར","མེད་པ","དམས་པ"],
"mi":["་མི","མི་","མི","མིན","་མི་","མིག","དམི","མི་མ","་མིན","མིད","་ག","མ་","ད་མི","ས་མི","ད་","་མིག","་དམི","ས་","སུ་"],
"mé":["མེད","་མེ","་མེད","མེད་","མེ་","་མེད་","མེས","་མེད༔","རྨད"],
"n":["་","ན","ང","ན་","བ","ག","ས","འ","ད","མ","ང་","གན","ྣ","ནུ","་ག","་བ","རྣ","ས་","ངས","ནོ","་མ","་ན","་གན","་རྣ","གོན","ཁ","སྣ","ཀུན","གི","འི","ཉི","་སྣ","ན་གྱི","རྙེ","རྔ","ཡོན","་ནོ","གོ"],
"na":["ན","་ན","་སྣ","་ས","ནག","སྣང","སྣ","ྣང","རྣལ","ྣ་","རྣམ","མན","ན་","་རྣ","ནང","་སྣང","སྣ་","གན","་རྣམ","ནར","ས་","འི་","རྣ་","་རྣལ","ྣམ","་ག","རྣ","མ་","རྣག","ད་ན","བརྣ","་ནག","མས","ནད","བསྣ","་ན་","་མན","ས་རྣ","ནམ","ནས","འི་ན","ན་བ","ད་","གནམ","་སྣ་","སྣམ","་བསྣ","་ན༔","མ་ག","གནག","ང་","ནལ","ན་ག","ས་ན","་རྣ་","ས་པ","གས","ས་རྒྱ","་ནང","འ་","བཟ","་དུ","་གན","ག་","ྣལ","དང"],
"nam":["རྣམ་","་རྣམ","རྣམ","ནམ་","་རྣམ་","་ནམ","ྣམ་","ས་རྣམ","ནམ","་ནམ་","ན་མེ","རྣམ་ད","གནམ","ས་རྣ","ན་མེད","་ན་","ན་","མ་ད","སྣམས་","མ་རྣ","་ན་མོ","སྣམ་","ན་མོ","འི་རྣ","ནམ་མ","ྣམ","ང་རྣ","ད་རྣ","ྣམས་","་ན་མ","ྣ་མི","འ་ནམ","ྣམ་ད","་ནམས","ས་ནམ","མས་","རྣམ་མེ","་རྣམས","་རྣམ་ད","་སྣམ","་གནམ","འ་རྣ","་བསྣམས༔","ན་མ"],
"ng":["ང","ང་","་","ངས","ས","ས་","ངེ","་བ","་ང","དངོ","་ལྔ","ད","་མ","མ","མངོ","་ད","ངས་","རྔ་","ྣང","་ངོ","ད་","་ག","ནང","འི་","སྔ","་མངོ","ང་བ","ང་ག","་གེ","ཧཱུྃ","ན་","མང","ངང","་བས","ག་","གིས","ྣ་","ས་མ","ང་གེ","ངའ","རྔམ","ས་ལྔ","འི་ད","ངའི་","མ་","་སྔ","འ་","དག","གི་","དང","རྔ་བ","་ས","་བ་","རྔད","ན་གྱི","གས","ཉིས","ནས","ས་ད","ཅིང","བགྱི","གས་","སྣང་","ནོང","གོས་","་གོ","ང་ད","བསྔ","་བ་ད","་མང"],
"nga":["མངའ","་ལྔ","བསྔག","་སྔག","་ངལ","རྔ་ཡ","སྔག","ངའ་","་ལྔ་","་ང་","ངག་","་སྔ","་མངའ","་ངག","་བསྔ","་ང","འི་ང","ས་སྔ","ང་སྔ","ས་ལྔ","བསྔལ","རྔམས","གས་","་མང","ང་","ངང་","སྔ་","ད་ང","ས་ང","་སྔ་","ངག","ས་","་སྔར","འ་བ","ད་ལྔ","ད་བསྔ","་བསྔལ","འི་སྔ","མ་ང","ངའ་བ","མངལ","ངའ་ག","ད་སྔ","་བསྔག","འགག","་ངང","་དང","མ་སྔ","ཉིད་","ང་ལྔ","་འག","ས་ད","བས་","་བྱ","གས་བ","ད་","ང་ཅ","ངང་ལ","རྔམ་ལ","་ད","དས་","འ་ག","ག་ག","དམ","་ངར","ང་ང","་པ","མངར","མ་ལྔ","་ལྔ་པ","་ངམ","་འ","དངར","སྔར","མང","རྔམ་","་ལྔར","ས་ངག","མ་པ","རྔམ་པ","ངང","གས་ལ","ངལ"],
"ngang":["་ངང","འི་ངང","ངང","ངང་"],
"ngc":["ང་","ང་ཕྱོ","ང་ཅ","ངས་","ྣང་","ང་ཆོ","ང་ཆེ","་ཅ","ས་ཆེ","ང་བ"],
"ngo":["་ངོ་","ངོ","་ངོ","་ངོམ","ས་ངོ","་ངོར","འི་ངོ","ད་ངོ","་ངོག","ས་བསྔོ","མ་ངོ","ས་","མ་","ས་ངོ་","ས་ངོར"],
"ni":["་ནི","་ནི༔"],
"no":["་ནོ","ནོར","ནོ","ནོང","་ནོར","གནོ","འི་","ད་ནོ","ས་","་ག","མནོ"],
"ny":["་","་ཉ","སྙི","ས་","་ཉེ","་ག","ཉེ","མྱུར","ཉི","་མྱོ","ཉིད","གཉེ","བསྙེ","ད་","ཉེས","མཉ","ཉོ","མཉེ","རྙེད","འི་","བརྙ","གཉ","རྙེས","་བརྙེ","མ་","རྙེས་","ག་","འ་","་མཉ","ང་","་བ","་བསྙེ","ཉེན","ཉེས་","ཉིས","ཉིས་","་སྙེ","ངས","ད་ག","ཉོས","བ་","ས་ག","ཉི་","་གཉ","ཉོ་","བས","་མཉེ","ས་ཉེ","དག","ྣ་","ས་མྱོ","ན་","ནས","་གཉེ","ཉེ་ག","་ལ","གཡོ"],
"nya":["་ཉམ","ཉ","མཉམ","་ཉ་","་མཉམ","་ཉལ","ས་མཉ","་གཉག","ས་ད","་ཉར","་ཉ","གཉའ","ན་ཉམ","གཉག","་ན་","་ཉག","་ད","འི་ད","ནུས་"],
"nyi":["་སྙི","་གཉིས","ས་སྙི","ཉི་","འི་སྙི","་ཉི","གཉིས","ཉིས་","ང་སྙི","ཉིས","ད་སྙི","ས་ཉི","འི་ཉི་","ད་ཉི","ས་ཉི་","་ཉི་","ཉིན","འི་ཉི","ཉི་མ","ག་སྙི","སྙིག","་ཉིད","ད་ཉི་","འ་སྙི","ཉིད་","་བསྙི","མ་སྙི","་གཉི","བ་སྙི","གི་སྙི","ང་ཉི","ཉིད","སྙིལ","ད་","ན་ཉི","ས་གཉིས","མ་ཉི་","ང་","ན་གཉིས","ངས་སྙི"],
"nyik":["སྙིགས་","ས་སྙིགས","སྙིགས","འི་སྙིགས","སྙིག","གཉིས་","་གཉིས","ད་སྙིགས","ཉིད་སྐུ","གཉིས","་སྙིགས་"],
"nyé":["་ཉེ་","་བརྙེས","རྙེད་","་སྙེ་"],
"né":["ས་","ནས་","་ནས","་ནས༔","ནས","གནས","ད་","གནས་"],
"o":["་","པོ","མོ","ག","ར","ང","ས","བོ","་བ","ཐོ","སྟོ","་འ","༔","བྱོ","ཡོ","ཏོ","ལ","འོ","སྐྱོ","ཇོ","རྟོ","གྲོ","མ","ཚོ","སྦྱོ","་སོ","ལོ","སོ","ལྗོ","གོ","དོ","རྫོ","ཕྲོ","ཕོ","སྒོ","རོ","ཨོ","ཧོ","ཅོ","་པོ","ཙོ","ཀློ","རྡོ","མཆོ","སློ","ངོ","བློ","་དོ","ནོ"],
"ob":["བ","སྐྱོབ","བས","སྐྱོབས","རློབས","་ཐོབ"],
"ok":["ག","་","ག་","ཇོག","འོག","གས","་ཟློག","མཆོག","གས་","་སོགས","ཕྲོག","་ཤོག","གས༔","ཕྱོག","གས་ག"],
"ol":["ལ","ལ་","་ལོ","བྱོལ","གསོལ","ཡོལ","ཡོ་","སོལ༔"],
"om":["མ","ཇོམས","མ་","་མོ","ག་མི","ཇོམ","འོག","འོ་མ","ཨོཾ","་མེ","ཡོ་མེད","འོ་","ཇོ་","་མེད","ཡོ་མེ","ག་","མ་མེ"],
"ong":["ང","ངས་","ཐོང་","ང་","སྟོང་","སྟོང","ཐོང","ངས","ཡོངས","སྦྱོང་","ཏོང་","ཡོང","འོང་","བྱོངས","ངས་འ","ས་","སྦྱོང","བྱོངས་","བྱོང་","སྟོངས","ཏོང་བ","འོང་བ"],
"ongp":["སྟོང་པ","ངས་པ","ང་པ","ང་","སྟོང་","བྱོངས་པ","བྱོངས་","་སྟོང་པ","མོངས་","དགོངས"],
"op":["ཐོབ","འོད"],
"or":["ར","བྱོར་","ར་","བྱོར","ཏོར་","སྦྱོར","ཨོ་","་ཨོ","ཨོ","ཏོར","ག་","ཐོ་རི","་ར","་རི","་ཨུ","ས་","༔ཨོ","སྐོར༔","ཐོ་","བོར","ཐོར","སོ་","བསྐོར"],
"p":["པ","་","་པ","པོ","ད","ས","བ","ས་པ","འ","་པོ","ཕ","ཕུ","ས་","བས","་ད","་འ","་ཕུ","ན","་དཔ","ང","འཕ","དཔ"],
"pa":["་པ","པར","་པར","པར་","པ་","དཔ","་པར་","་ཕ","དཔའ","ཕ","ཕ་","ས་པ","ད་པ","་འཕ","ཕམ","འཕ","ཕབ","་དཔལ","པའ","པལ","་དཔ","དཔལ","ཕང","་དཔའ","་པ་","ཕ་མ","ཕག","པག","འཕག","ས་","འ་","ཕར","དཔག","པད","ད་","་ད","་ར","་དཔག","བར","ཕར་","ས་དཔ","པན","་མ","་བླ","པཙ","་བ","ན་པ","པོན"],
"pak":["འཕགས་","པག་","་དཔག་","དཔག་","དཔག","ཕགས་","འཕག","འཕགས","ཕག་","་དཔ","་འཕགས","ཕགས","་དཔག","་ཕག","ཕག","པགས་","པག་བ","་པགས་","དཔག་བ","་འཕག","དཔའ་མ","་པགས","་པ་"],
"pal":["དཔལ་","དཔལ","པལ་","་དཔལ་","་དཔལ","ཕལ་","ཕལ","པལ་མ","དཔལ་མ","་དཔལ་མ","པལ","་ཕལ","ཕ་","་ཕ་"],
"po":["་པོ","་ཕོ","པོར","འཕོ","པོ་","ས་","ད་","་པོར","་འཕོ","་པོ་","པ་","་པ་","དང","དཔང","ན་"],
"pul":["ཕུལ་","་ཕུལ","་ཕུལ་","ཕུལ","ཕུལ་བ"],
"pulwé":["ཕུལ་བས"],
"pé":["པའི","པས","་པའི","་པས","་པ","པད","ད་པ","ཕས"],
"pö":["དཔོ","་པོ","་དཔོ","པོའི","པོན","ས་","པའི","པོས"],
"pü":["་ཕུ","དགུ","ས་"],
"r":["་","ར","ར་","རི","བྲ","དྲ","གྲ","བ","འ","གྲོ","ད","དྲི","ར༔","ས","སྒྲ","སྒྲོ","གྲི","་ར","་འ","རུ","་རི","དྲུ","དྲེ","རོ","ས་","པྲ","དྲོ","ཏྲ","་རུ","གྲུ","ཀྲ","རྡོ","ཟེར","ཨུ","ཕྲ","་རོ","ཕྲུ","ཁྲི","ཀྲུ","སྤྲོ","ཁྲུ","ཁྲ","ཁྲོ","ཀར་","སྤྲུ"],
"re":["་རེ","འབྲེ","ཕྲེ","དྲེ","དྲེན","བྲེ","རས་","དྲན","གྲན","དྲེས་","བྲས་","བྲ","དྲེན་","བྲལ","བྲས","དྲེས","དྲན་","བྲན","་བྲེ","རལ","བྲན་","རས","ར་","་སྤྱ","་རས","གྲས་","་ས","གྲན་","དྲེད","རན"],
"rik":["རིག་","་རིག","རིགས་","རིག","རིགས","རིག་ག","་རིགས","བསྒྲིག","རིག་འ","གྲིག་","་རིག་","་རིགས་","ད་རིག","བསྒྲིགས"],
"ro":["རོལ","་རོ","རོ","རོ་","་རོལ","གྲོ","་རོ་","ས་རོ","རོར","རོག"],
"ru":["གྲུབ","བ་","་རུ","གྲུ","དྲུག","་གྲུ","སྒྲུ","་རུ་","་སྒྲུ","བསྒྲུ","རུང","དྲུང","རུ་","འགྲུ","གྲུ་","རུབ","་གསུ","་འ","་རུ༔","རུམ","བ་དུ"],
"rub":["བ"],
"s":["་","ས","ཤེ","སྲི","བ","ག","ཤ","ཤི","ས་","སྲ","སོ","མ","་བ","སྲོ","་ག","་ས","ཤུ","ཙ","གས","ལ","་སོ","སེ","ཚོ","ཚ","ཀྲ","ཚེ","བས","གསུ","་བས","རྩོ","་གསུ","ཚི","རྩེ"],
"sa":["་ས","ས་","གས","སང","བས","གསལ","་ག","སལ","སར","་གས","་གསལ་","སམ","་བ","བསག","་གསལ","སར་","སག","གསང","་བསག","བསམ","མས","་བས","སྲ་","བསང","མ་འ","་སརྦ","་སར་","་གསང","་ས་","གན","བསལ","་གསར","ག་","ས་ར","མ་","སྲབ","ལ་","སརྦ","་བསམ","ས་ག","ས་བ","བཟ","གསར","ས་ས","་བསལ","སེམ","གས་","་ཡ","་ས་ག","་བསམ་","སྲང","་སར","སྭ","གསག"],
"sal":["གསལ","གསལ་","སལ་","་གསལ་","་གསལ","ས་ལམ","བསལ","ས་ལ","་ས་","ས་ལེ","་ལམ","་ལ","བསལ་","ས་བླ","གསལ་བ","་གསལ་བ","་ས་ལ"],
"sam":["བསམ་","སམ་","བསམ","་བསམ་","་ས་","སམ","ས་མ་","ས་མ","་ཡ་","་བསམ","ས་བ","་བསམ་ག","མ་ག","ས་མོ","་ས་མ","བང་"],
"sang":["གསང་","གསང","གསང་བད","་གསང་","་གསང","སང་","གསང་བ","གསང་བ་","མ་སང","བསང","་སངས","སང་བ","་ད","གསང་འ","སང","གསང་མ","སངས་","སང་བ་","སང་ག"],
"sangy":["སངས་རྒྱས་","་སངས་རྒྱ","་སངས་རྒྱས","སངས་རྒྱ","་སངས་","སངས་","སངས་རྒྱས","ས་ས","་སངས་རྒྱས་","་རྒྱས་","ས་སངས","ས་རྒྱས་"],
"se":["་སེ","སེ","སེམས་","གསེ","སེམས","བསྲེ","སེལ","་སྲེ","སད","སེང","་གསེ","སྲས་","བསད","སྲན","གསན","གསན་","སན","གས","སེན","སེ་","་བསད","་གས","སྲད","་སད","སལ","་གསལ","ས་སེ","སྲས","ཚེ","་བསྲེ"],
"sel":["སེལ་","་སེལ","གསལ"],
"sem":["སེམས་","་སེམས","སེམས","་སེམ","སེམས་ད","སེམ","མས་","མས་ད","ས་སེམས","སྲས་མོ","སེམས་བ","་སྲེད","ས་སེམ","སྲས་","་སྲེ་"],
"shak":["ཤགས་","བཤགས","བཤགས་","་ཤ་འ","་བཤགས་","་བཤགས","་ཤ་མ"],
"shik":["་ཞིག་","་བཤིག","བཤིག་","ས་ཤིག"],
"shok":["་ཤོག","ས་ཤོག","་ཤོག༔"],
"so":["་སོ","སོ","སྲོང","སོ་","སོག","གསོ","སོར","སྲོག","སོལ","ཚོ","སོང","་སོག","སོམ","ས་སོ","་གསོ","ས་","སྲོལ","སོ་སོ","མག","བསོ","་སོ་","་བསོ","སྲོ་"],
"sok":["སྲོག","སོགས་","སྲོག་","སོགས","སོག","སོག་","་སོག","་སོགས","སོ་སྐྱེ","སོ་","་སོགས༔","་སོ་"],
"sol":["གསོལ","་གསོལ","སོལ་","སོལ་བ","་སོལ","སོལ","་སྩོལ༔","་གསོལ༔","་སོལ༔"],
"su":["་སྲུ","་སུ","གསུ","གསུམ","གསུང","རྩུ","་ག","བསུ","་གསུ","་གསུམ་","བསྲུ","མ་","་གསུམ","་བསྲུ","ས་","ས་སྲུ","ག་","ཚུ","ས་གསུ","་བསུ","གཟུ","ཚིག","ས་སུ"],
"sum":["གསུམ་","་སུ་མེད","་སུམ","གསུམ","་གསུམ་","ས་སུ","་སུ་མེ","་སུ་","་གསུམ","་སུ་མ"],
"sung":["་སྲུང་","གསུངས་","་སྲུང་མ","བསྲུང་","་བསྲུང་","བསྲུང","་སྲུང","་སྲུངས་","གསུངས","་གསུང","་བསྲུངས་","གསུང","བསྲུངས་བ"],
"sé":["སད","སྲས་","སྲིད","་སྲ"],
"sö":["གསོ","སོན","སོས་","སོའི","ས་"],
"sön":["སོན་","་བསོད","སོད་ན","བསོད","སོད་","གསོན་"],
"sü":["ས་","གསུས"],
"t":["་","མ","ག","སྟོ","ཐོ","ད","འ","ཏོ","ཏི","རྟོ","སྟ","བ","ཏ","ཏུ","ཐི","ལྟ","ཐ","རྟ","ས","་མ","ས་","་ག","ཐུ","ཚེ","རྩ","་རྟོ","་སྟོ","་མཐོ","་ཐོ","་ལྟ","་མཐ","་བ","ལྟུ","་ཏུ","འི་","ཚུ","འི","ཚོ","ཚི","སྤྲུ","རྟེ","་བརྟ","སྤྲོ","་རྟ","སེ","་འ","་ཐ","་བསྟ"],
"ta":["་ཐ","ཐ","་ལྟ","ཐའ","མཐའ","ལྟ་","བཏ","ཐབ","རྟག","ཐ་","ཏབ","བལྟ","་རྟ","སྟབ","ལྟར","ཐལ","ལྟར་","ཏ་","་མཐའ","མཐ","ཐར","གཏ","་ཏ","་ལྟ་","་བཏ","འཐ","ལྟ་བ","་ལྟར་","ཐམ","་བཏབ","རྟ་","སྟང","་རྟག","བ","ས་","་ཐབ","་ཡ","་བ","་ལྟར","ཐག","་ཐག","མས","ས་ཐ","ཐར་","ཏམ","་ཐམ","སྟག","་ཅ","་མཐ","བཀྲ","ལྟམ","བས","་བསྟབ","་ཐ་","བརྟ","་བལྟ","འི་","་བཀྲ","ཐང","ཏག","ཐ་ད","་རྟ་","་ཐལ","རྟར","་ད","་མཐར","་ཐང","རྟ་མ","འ་ཐ","དཀ","གས","་གཏ","་བཏང","དྭ","བ་ན","རྩལ","བད","་འཐ","སྟ་","ལྟག","དས","ཐ་མ","་མཐར་","སེ་ཐ","་ཐར"],
"tak":["རྟག་","སྟག","་རྟག","རྟག","ཐག་","བཏགས","་རྟག་","ཐག","རྟག་བ","སྟག་","རྟགས་","་ཐག","མཐའ","གས་","མཐའ་འ","ཏགས་","ས་རྟག","ག་པ","་རྟགས","བརྟགས","བརྟག","ས་ཐག","རྟ་སྐ","་བཏགས་","རྟགས","་མཐའ་འ","ཐ་","་རྟག་བ"],
"tar":["ཐར་","མཐར་","་ཐར","་ལྟར","ཐར","མཐར","་མཐར་","་མཐར","ལྟར","་ཐར་","་ཏ་","ཏ་རི","ཏ་ར","བལྟར་","ཐའ་རུ","་བསྟར་"],
"te":["་ཐེ","གཏེ","བརྟ","གཏ","སྟན་","བསྟ","་སྟེ","རྟེན་","་གཏེ","་རྟེ","ཏན","བཏེ","ཏན་","སྟན","རྟན","ལྟས་","་ཏ","རྟེན","ས་","ཐད","་ཏེ","བརྟེ","ཏད","་བརྟན་","རྟས་","ད་","་སྟ","འི་ཐེ","་བརྟ","རྟན་","ཏ་","ཐལ","མ་","་བརྟེ","་བསྟན","་བསྟ","གན","ས་པ","་གཏ","་བརྟན","ག་","་ཐན་","ལྟས","ལྟད","འི་"],
"ten":["བསྟན་","སྟན་","རྟན་","བརྟན་","བསྟན","རྟེན་","་བསྟན་","་བརྟན་","་བསྟན","གཏན་","བརྟན","་རྟེན","་བརྟན","་སྟེང","སྟན","་རྟེན་","བརྟེན","བརྟེན་","རྟེན","ཏན་","རྟན་ག","་སྟེང་","་ཐེངས","་བརྟན་ག","ད་བ","་ཏན","འི་རྟེན","ག་བ","གཏན","ཐན་","མ་བ","་རྟེན་གྱི","་གཏན་","ས་བ"],
"teng":["་སྟེང་","་སྟེང","དན་"],
"ter":["གཏེར","གཏེར་","་སྟེར་","་གཏེར","་སྟེར"],
"tob":["་ཐོབ","་སྟོབས","ཐོབ","་སྟོབ","སྟོབས","འཐོབ","སྟོབ"],
"tok":["རྟོགས་","ཐོགས་","ཐོག་","་རྟོག","རྟོག་","རྟོག","་ཐོག","ཐོགས","རྟོགས","་རྟོགས","ཐོག་མ","ཐོག","་རྟོགས་","་ཐོག་","ཏོག་","་རྟོག་","་ཐོགས","་ཐོགས་"],
"tr":["་ཁྲོ","འཁྲུ","་སྤྲུ","་འ","་ཕྲ","འཕྲོ","་ཁྲི","འཕྲུ","་སྤྲོ","ས་","་ཁྲ","ཁྲོ","བཀྲ","་འཕྲོ","སྤྲུ","འཕྲ","ད་","འི་","་ཏྲ","་བ","སྤྲོས","་འཁྲུ","་སྤྲི","དཔྲ","ས་སྤྲུ","་ཕྲི","དཀྲུ","་ཁྲུ","་ཕྲུ","བཀྲུ","ག་","འཁྲོ","་པྲ","་ཕྲོ","་འཕྲུ","སྤྲོད","ས་ཁྲོ","འཕྲི","དའ","་ད","མས","མཁྲི","སྤྲོ་","་ཀྲུ","འཁྲི","་བཀྲ","་འཕྲི","ས་སྤྲོ","་ཀྲ"],
"tri":["་སྤྲིན","འཁྲིག","་ཕྲིན","མས་","་འཁྲི","འི་སྤྲི","འཕྲིན","ཕྲི","འཁྲིལ","་ཁྲི་","ས་སྤྲི","་འཁྲིག","་འཕྲིན","འཁྲིད","འི་ཁྲི","ས་ཁྲི","ད་སྤྲི","་འཁྲིལ","་ཁྲིག","སེ་ཁྲི","འ་སྤྲི","མས་ག","འ་ཁྲི","སེ་སྤྲི","་འཁྲིད","་ཕྲི་"],
"ts":["་","མཚོ","་མ","་ཚི","་རྩི","བརྩོ","ཚོ","་ཚེ","ཚེ་","བརྩེ","་རྩོ","་ཚུ","་ཚོ","མ","མཚུ","་ཚ","་རྩེ","ས་","གཙུ","ཚིག","་རྩ","ཚུ","ད་","འ་","བཙ","རྩ་","ཚོ་","་བ","་བརྩོ","འཚེ","་ག","ཚ","་འ","བཙུ","་གཙུ","འཚོ","འཚུ","ཚོས","འི་","ཚུལ","ཚིམ","ག","་མཚོ","་ཙ","་མཚུ","ཚེས","་རྩ་","་བཙ","རྩལ","་སྩོ","ཚོག","ཚུགས","ག་","ཚིགས","ཚེས་","དམ","་སོ","ཚུག","རྩ་བ","བསྩོ","ཚོས་","བ་","ཚོ་སོ","ཚེ་ག","རྩམ","རྩ་ག","འི་ཚུ","ས་ཚི","བརྩི","རྩས","མ་","ས་མ"],
"tsa":["་ཚ","མཚམ","་གཙ","རྩ","་ཙ","་མཚ","ཚ","་ཚལ","གཙ","་རྩ","རྩ་བ","་རྩ་","ས་ཚ","་རྩལ","ཚང","འཚ","འཚལ","རྩལ་","་ཙམ་","་ཚང","མ་ཚ","འི་ཚ","་ཙ་","ས་རྩ","བརྩམ","་ཙམ","་ཚབ","གཙང","མཚ","་མཚར་","འི་རྩ","ད་ཚ","ཚལ","མཚར་","་འཚ","ཚབ","་ཚ་","མཚར","ས་གཙ","་ཚར","ཚར","ད་རྩ","་མཚར","་བརྩ","འཚམ","་ཙཀྲ","ག་ཚ","་འཚལ","་ཚྭ","ཐུ་རྩ","ག་རྩ","་ཚ་ག","མ་","ག་ཙ","་སྩལ","མཚང","འཚང","ས་སྩ","རྩམ་","ས་ཙ","ཐུ་སྩ","མ་ཙ","ཚེ་ད","རྩ་བ་","འ་ཚ","་ཚར་","་བསྩ","འ་སྩ","ཚ་","འ་ཙ","བཙའ","་བཙ","ཚོ་སྩ","རྩ་ག","་རྩལ་","བཙལ","ད་སྩ","་བཀ"],
"tsal":["འི་རྩལ","་རྩལ་","ས་རྩལ","འཚལ་","་ཚལ་","་རྩ་ལ","་རྩ་","ཚལ","བཙལ་","རྩ་","ས་རྩ་","་རྩལ","རྩལ","་སྩལ་","འི་རྩ་","་བཙལ","་བསྩལ","མ་རྩ་"],
"tse":["ཚེ","མཚན་","་ཚེ","་ཚེ་","་མཚ","་བརྩེ","བརྩེ་","ཚེ་ད","་ཚད","་རྩེ་","མཚན","བརྩེ","འཚེ","ཚད","ས་ཚེ","་རྩེ","མཚ","འི་རྩེ","འཚེ་","་མཚན","་མཚེ","བཙད","བཙན","་ཚ","་བརྩེ་","་མཚན་","ད་ཚེ","ད་རྩེ","་འཚེ","ས་རྩེ","ཚན","ཚེགས","ཚེམས","བཙས་","་རྩེན","་སྩལ","ས་ཚེ་","འི་མཚ","བརྩེས་","ཚན་","མ་ཚེ","བཙན་","ས་མཚ","ཚེམ་","ད་ཚ","་བསྩལ","ས་རྩེ་","ས་ཚ","་རྩལ","་འཚེ་","ག་ཚེ","འི་ཚེ་","་བཙན","ཚེ་བད","འཚལ"],
"tsen":["མཚན་","་མཚན","བཙན་","བཙན","མཚན","མཚན་མ","་བཙན་","་མཚན་","་རྩད་ན","ས་རྩད་ན","ཚན་","་རྩད་","་རྩེན་","ཚན","ཚེ་","་ཙན་"],
"tso":["ཚོགས་","་ཚོག","་ཚོ","ཚོགས","་གཙོ","་མཚོ","འཚོ་","ས་ཚོ","་ཚོམ","འཚོ","གཙོ","་རྩོམ","འི་ཚོ","མཚོ","མཚོ་","མཚོར","་རྩོལ","ད་ཚོ","་ཚོར","ཚོག","འི་གཙོ","ཚོང","་ཙོ","ས་ཙོ","ཚོར","་མཚོ་","་སྩོལ","་མཚོར","ཚོམ","་བཙོ","ས་གཙོ","་འཚོ་","ཚོལ","ག་ཚོ","ད་མཚོ","འཚོག","་ཚོང","འི་ཚོག","་ཚོལ","ས་སྩོལ","རྩ་གསུམ","འཚོར"],
"tsok":["ཚོགས་","་ཚོགས་","་ཚོགས","ཚོགས","་ཚོག","ཚོགས་པ","ས་ཚོག","གཙོ་འ","་མཚོ་","ཚོག","ཚོགས་ག","ཚོགས་བ","ཚོགས་མ","མཚོ་","ད་ཚོག","མཚོ་སྐྱེ","་ཚོག་"],
"tsol":["་རྩོལ་","་སྩོལ་","་རྩོལ","་སྩོལ","་ཚོལ་","འཚོལ"],
"tsul":["ཚུལ་ཁྲི","ཚུལ","ཚུལ་བ","ས་ཚུལ","་ཚུལ","ཚུལ་","འི་ཚུལ","་ཚུལ་","ད་ཚུལ","ག་ཚུལ"],
"tsé":["་ཚེ","་ཚད","ཚད","འཚེ་","་བརྩེ","ཚེ་འ","་རྩེ","་རྩེ་","བརྩེ་"],
"tsü":["བཙུ","འི་བཙུ","ཚུལ་","ས་བཙུ","་ཚུད","མཙུ","འ་བཙུ"],
"tu":["ཏུ་","་ཐུ","ཐུབ","འཐུ","གཏུ","ཐུག","མཐུ","ཐུ","ལྟུང","ཐུ་","་གཏུ","བརྟུ","་ཏུ","བཏུ","ད་","སྤྲུལ","་བཏུ","་སྤྲུ","ཐུང","་མཐུ","ཏུལ","་བརྟུ","་ཐུག","ཐུལ","མདུ","ཐུམ","་རྟུ","ས་","་ཐུབ","འ་","འ་ཐུ","ག་","འི་ཐུ","ད་ཐུ","ཏུམ","ཏུབ","ས་ཐུ","ས་སྤྲུ","་མ"],
"tuk":["ཐུགས་","ཐུགས","་ཐུགས་","་ཐུག","ཐུག","གཏུག","ཐུག་","འ་ཐུགས","་ཐུགས","འི་ཐུགས","འཐུག","ས་ཐུགས","གཏུགས"],
"té":["་ཏེ","་ཏེ༔","་སྟེ༔","་སྟེ"],
"tö":["ཐོད","་ཐོ","་སྟོ","སྟོན","ཐོས་","བསྟོ","སྟོད","ཐོས","་སྟོན","་ཐོད","ས་སྟོ","འ་","་བསྟོད","་དོ","ཐོན","ཏོན","མཐོ"],
"tön":["སྟོན་","ཐོན་","་སྟོན","མཐོན་","་སྟོན་","མཐོན","་མཐོན་","རྟོན","སྟོན","ཏོན་","འཐོན་"],
"tü":["མཐུ","་ཐུ","ཐུ","་མཐུ","ཐུད","ཏུད","འི་","་མཐུས"],
"u":["་","བུ","ག","ང","གུ","ལ","གྱུ","ཕུ","བ","ཟུ","དུ","ཅུ","པུ","ཆུ","མ","མྱུ","སྒྱུ","༔","་དུ","འ","ཏུ","ཚུ","ཕྱུ","སུ","ནུ","སྐུ","ཞུ","ཨུ","མུ","ཕྲུ","ཁྲུ","ཀུ","སྤྲུ","རུ","ཙུ","རླུ","ཐུ","ཛུ","་རུ","ཀླུ","སྡུ","ཡུ","ཉུ","ལུ","གྲུ","་སྐུ","་ཐུ","ཇུ","ས་སུ","་ཏུ","་ཕུ"],
"ub":["བ་","ནུབ","ཆུ་","ཛུབ","ཅུ་"],
"uk":["ག","ག་","གས་","གས","ཉུག","བུགས","གུགས","ཙུག","ཁྲུག","་སྐྱེ","མུ་","རུ་","མུག","ས་","ཆུ་","་པ","་ད","ག་མ","ཛུགས","་སྐ","ཕྱུག","གས༔","བུག"],
"ul":["ལ་","ལ","ཁྲུལ","སྤྲུལ","བུལ","ཆུ་","ཀུ་","གུལ","་ཀླུ","སྒྱུ་","བུལ༔"],
"umé":["སླུ་མེད"],
"ung":["ང","ངས་","ཚུངས","པུང","ཕུང་","ང་","པུང་","་འབྱུང","ཆུང","ཞུང་","ཕུང","ཆུང་","བུང་","༔","ཉུང་","ང་བ","ཅུང་","ངས","ཞུང","་མ་","བུང","པུང་ག","གུང","ཧཱུྃ","གུང་","ཚུང"],
"v":["ྦ"],
"w":["བ","་","་བ","བོ","་བའི","ད","འོ","་ད"],
"wa":["་བ","བར","དབ","་ད","་བར","བ་","བར་","་དབ","བང","་ཝཱ","བབ","་པ","ད་","ད་ད","་བར་","དའ","དག","་དུ","་བ་","་ཝ","བ་འ"],
"wang":["་དབང","དབང་","དབང","་དབང་","དབ","བང","་དབང་བ","བང་བ","ད་དབ","བང་","ད་དབང","་དབ"],
"war":["་བར","་ཝཱ་","་ཝཱ་ར"],
"wé":["བའི","་བའི","་བས","འི་"],
"y":["་","ཡོ","ག","ཡ","ད","ས","་ཡོ","བ","འ","་ག","སྐྱེ","ཡུ","ཡི","་ད","ཉེ","ཉ","ས་","སྙེ","ན","་ཡི","་ཡུ","རྒྱུ","ལ","སྐྱོ","རྒྱ","གྱི","སྐྱ","སྐྱི","ར་","ན་"],
"ya":["་ཡ","རྒྱ","ཡང","དབྱ","ལ","གཡ","ཡ་","ཡལ","་དབྱ","ཡར","་གཡ","ཡམ","ཡབ","ཡག","བ་","ཡར་","ཉམ","ན་ཡ","ཡའ","བ་བ","བ་པ","ས་","་ན"],
"yab":["ཡབ","ཡབ་","་ཡབ","ས་ཡབ","གཡབ","རྒྱབ"],
"yang":["ཡང","་ཡང","་ཡང་","ཡང་","ཡངས་","གཡང","དབྱངས","ཡངས","ཡང་ད","་ཡངས","དབྱངས་","གཡང་","་ཡངས་","དབྱང","དབྱངས་ག","གཡང་ས","་ཡ་ང","་དབྱང","ཀྱང","ད་ཡང","་གཡང","་བྱད","ཡང་ག","་ཡང་ད","དབྱ"],
"yes":["་ཡེ་","་ཡེ་ཤེས","ཡེ་ཤེ","་ཤེས","་ཡེ་ཤེས་","དབྱེ་བས","གནས","ས་ཡེ་","དབྱེ་བ"],
"yi":["་ཡི","ཡིད","ཡིན","དབྱི","་","ཡི","ཡི་","གྱི","་དབྱི","་ཡིད","་ཡིག","་ཉིད","ཀྱི","ད་","ཡིག","ད་ཡི","་ཀྱིས","་ཡི་","་ཡིན","ཀྱི་","ཉིས","ས་ཀྱི","ས་ཡི","ས་","ཉི","་ཡིས","སྐྱིལ","ས་ལ"],
"ying":["དབྱིངས","དབྱིངས་","དབྱིང","་དབྱིངས"],
"yu":["་ཡུ","ཡུལ","གཡུ","སྒྱུ་","ཡུ","་ཡུལ","་དབྱུ","དབྱུ","ཡུམ","འགྱུ","ཡུག","་ཡུམ","དབུ","་གཡུ","ཡུ་","ས་ཡུ","་ཡུ་","ཡུང"],
"yum":["སྒྱུ་མ","་ཡུམ","ཡུམ་","ཡུམ","ཡུ་མོ"],
"yur":["གྱུར","་ཡུར"],
"yé":["་ཡེ","་ཡ","་རྒྱས","ཡས"],
"yü":["རྒྱུ","་ཡུད","ཡུད"],
"z":["་","ཟ","ག","ས","བ","ཛ","ཟུ","འ","ཟེ","ད","་བཟ","་ག","བཟུ","རྫ","ཞི","་བ","་ཟ","ཛི"],
"za":["བཟ","ཟབ","་ཟ","ཟ","ཟང","ཟག","ཟ་","་ཟབ","གཟ","་བཟ","་བཟའ","ཟའ","ཟམ","་ཟག","་གཟ","གའ"],
"zang":["བཟང་","བཟང","་བཟང་","ཟང","་ཟང","ཟང་","་བཟང","་ཟང་","ཟངས་མ","་ཟངས","ཟང་མ"],
"zh":["་ཞ","གཞ","་ག","་ཞེ","་ཞུ","གཞོ","ཞ","བཞེ","ཞེ","ཞབ","་བ","བཞ","གཞི","བཞི","ས་","་ཞི","གཞུ","ཞི་","བཞུ","་གཞ","གཞེ","་བཞེ","་ཞོ","ད་","ཞིའི","ད་ག","ས་བ","ཞག","ཞི་བ","་གཞོ","ཞད","་གཞི","ཞན","་ཞིའི","་གཞུ","་བཞི","ད་བ","འ་བཞི","ས་ག","ཞིན","ག་","་བཞུ","འ་བ","ཞིང","ཞིག","་ཞི་","ཞིང་","དང་","་བཞིས","འ་ག","ཞིས","བས","་བཞི་","འ་","བཞོ","་ཞིང","་ཤི","ཞས","་བཞིའི","་བཞ","་ན"],
"zhak":["བཞག་","ཞགས་","་ཞགས","གཞག་","ཞག་པ","་ཞགས་","བཞག","་ཞག","་བཞག","ཞག་"],
"zhi":["་བཞི","་ཞི","བཞིན","་ཞིག","ཞིག་","ཞིན་","་ཞི་","་གཞི","་བཞིན་","བཞི་","ས་ཞི","བཞི","གཞི་","ཞི་བའི","ཞིང་","་བཞིན","ད་ཞི","འ་ཞི","་བཞི་","གཞི","གཞིག","་གཞི་","ཞི་བ་","ཞི་བས","་ཞིང་","ག་ཞི","ད་བཞི","ད་བཞིན","་བཞིའི","ཟུགས་","ཞིར་","ཞེད","གཞིལ","འ་བཞིན","་ཞིའི","་ཞིའི་","ཞིང་ཡི","དེ་ཞི","་ཞིར་མི","བཞིའི","ཞིག་གི","གཞི་ཡི","བཞི་མ"],
"zhin":["བཞིན་","་ཞིང་","བཞིན","་བཞིན","་བཞིན་","ས་ཞིང","་ཞིང","ས་ཞིང་","གའི་ཞི","ཞིང་བ","ཞིང་གི","འ་ཞིང","དང་ཞི","ཞིང་རྔ","ཞིང་རྣ","ཞིང་འ","ཞིང་དང","དེ་ཞིང","ཞིང་ཁ","གཞི་","ད་ཞིང","ཞིང་ད","ཞིང་ན","ཞིང་གི་","གང་ཞི","དེ་ཞིང་","འ་བཞིན་","ཟང་ཞི","ཞི་གན"],
"zhindu":["་བཞིན་དུ"],
"zhing":["ཞིང་ཁམ","་ཞིང","ས་ཞིང","་ཞིང་","གའི་ཞིང","ད་ཞིང","ད་ཞིང་","ད་ཞིང་ས"],
"zhuk":["་བཞུགས་","་ཞུགས་","བཞུགས་","བཞུགས","་བཞུགས","་བཞུག","་ཞུགས","་ཞུག","བཞུག"],
"zhé":["བཞད","ཞད་","་ཞེ་","བཞེད"],
"zi":["གཟི","་ཟི","་གཟི","བཟི","ས་","ད་"],
"zik":["གཟིགས","་གཟིགས","གཟིག","་གཟིག"],
"zin":["་ཟིན་","་ཟིན","་ཟིང","འཛིན","གཟིངས","་འཛིན","གཟིང"],
"zok":["་རྫོགས"],
"zuk":["གཟུགས","ཟུགས་","ཟུགས","གཟུག","་གཟུགས","ཟུག་","ཟུག"],
"zung":["བཟུང་","གཟུང་","ཟུང་འ","་བཟུང","་བཟུང་","གཟུང","་གཟུང་","་ཟུང་","གཟུང་བ","བཟུང་བ","གཟུངས་","་གཟུང","་ཟུང་འ","་ཟུང","ཟུང་","གཟུངས","བཟུང","ཟུངས་"],
"zé":["ཟད","ཛད༔","མཛད"],
"zö":["བཟོ","མཛོད","་བཟོ"],
"é":["འི","འི་","ས","་","ད","ས་","པ","བ","མེ","ས༔","་མ","བྱེ","འ","ན","རྗེ","ད༔","ལ","་པའི","ཅ","ཚེ","་པས","་ན","སྡེ","གེ","་མེད","རྒྱ","ཡེ","་པ","དེ","ཆེ","རེ","ཡ","་མེ","་པའི་","སྲ","སྐྱེ","རྩེ","་ནས","པེ","ལེ","ལྔ","་རྗེ","ནས","ལས","་ལས","མེད","་སྟེ","་དེ","གན","་ཏེ","་ལྔ","་ཅ","་རྒྱ","པས"],
"ö":["ད","ས","འི","འི་","་","ས་","ན","དོ","འོད","པོ","མོ","ནོ","ཚོ","ཡོ","ངོ","ཀོ","ྤྱོ","ཆོ","མ","འོ","ད༔","་འོད","ཅོ","ཟོ","སྟོ","ཐོ","ཞོ","ཆོས"],
"ön":["ན་","ན","ངོན","ཀོན་","ཡོན་","ཡོན","ཚོན","་མ","ནོན་","བྱོན","ཞོན","ན་མ","་དོན","ནོན","འོན","འོད་","ཀོན","ཞོན་","་ཡོན","འོད་སྣ","ས་རྣ","མགོན","ན་བ","ས་","འོན་"],
"ü":["ད","ས","་","ས་","འི","འི་","བུ","གུ","དུ","ནུ","དུས","ཐུ","བཅུ","ལུ","མུ","ལུས་","དུད","ཀུ","ཕུ","རྒྱུད","ཐུས"],
"ün":["ན་","ན","མུན་","མུན","་ཀུན","དུ་ག"],
"üpa":["ས་པར","ནུས་པ","ད་པ","་པར","ས་པ","ད་པ་","་པར་","ནུས་པར","ད་པར་"],
"ŋ":["ང"],
"ŋɑ˨˧˩":["ང"],
"ŋɑ˩˧":["ང"],
"ŋɒ":["ང"],
"ȵæ":["ཉ"]},"SrcMulti":null,"DstMulti":null,"SrcMultiSuffix":["ː"],
"DstMultiSuffix":null,"DropLast":null,"DstMultiPrefix":null,"PrePhonWordSteps":[{"ToLower":true}],
"SplitBefore":null,"SplitAfter":null,"SplitAt":null,"IsDuplex":false,"IsSrcSurround":false,"SrcDuplicate":null}